Workbook

Sheet 4K
A1: Cost of a Financial Advisor
A2: my old advisors fee for AUM:
A3: 0 - 250,000 | B3: 0.0175
A4: 250,000 - 500,000 | B4: 0.015 | D4: They calculate their fee based on the daily closing value of your account, averaged over each month x the monthly portion of your annual rate.
A5: 500,000 - 1,000,000 | B5: 0.0125 | D5: Ex. 1. If daily average closing value of my account is $12,000 and the monthly fee is 0.146% (1.75%/12) then my fee for the month is (12,000 * 0.00146) = $17.52
A6: 1,000,000 - 2,000,000 | B6: 0.01 | D6: Ex. 2. If the following month I have $16,000 in my account, the fee for that month is 16,000 x 0.00146 = 23.36
A7: 2,000,000 - 6,000,000 | B7: 0.01 | D7: Ex. 3. What is the cost of all of this? You might think it is 17.52 + 23.36 = $40.88. You would be wrong! You've also lost out on the interest you would have gained on that 17.52 and 23.36. And the compounded interest on that interest. And the compounded interest on the interest of the interest. You get the idea. So what does that actually look like in real numbers?
A8: 6,000,000+ | B8: 0.0075
D10: Scenario 1 | AI10: Scenario 1 | AJ10: WITHOUT AN ADVISOR
D11: Assume I don't invest anything. It just sits there in a cash account. What would be the raw dollar cost of the financial advisor. (i.e. lost opportunity of compounding not realised) | AI11: Assume I don't invest anything. It just sits there in a cash account. What would be the raw dollar cost of the financial advisor. (i.e. lost opportunity of compounding not realised)
D12: Assume I save $4K/mo | AI12: Assume I save $4K/mo
D13: Y1 | E13: Y2 | F13: Y3 | G13: Y4 | H13: Y5 | I13: Y6 | J13: Y7 | K13: Y8 | L13: Y9 | M13: Y10 | N13: Y11 | O13: Y12 | P13: Y13 | Q13: Y14 | R13: Y15 | S13: Y16 | T13: Y17 | U13: Y18 | V13: Y19 | W13: Y20 | X13: Y21 | Y13: Y22 | Z13: Y23 | AA13: Y24 | AB13: Y25 | AC13: Y26 | AD13: Y27 | AE13: Y28 | AI13: Y1 | AJ13: Y2 | AK13: Y3 | AL13: Y4 | AM13: Y5 | AN13: Y6 | AO13: Y7 | AP13: Y8 | AQ13: Y9 | AR13: Y10 | AS13: Y11 | AT13: Y12 | AU13: Y13 | AV13: Y14 | AW13: Y15 | AX13: Y16 | AY13: Y17 | AZ13: Y18 | BA13: Y19 | BB13: Y20 | BC13: Y21 | BD13: Y22 | BE13: Y23 | BF13: Y24 | BG13: Y25 | BH13: Y26 | BI13: Y27 | BJ13: Y28
D14: 0 | AI14: 0
C15: J | D15: =(D14+4000)-(0.00146*(D14+4000)) -> 3994.16 | E15: =(D26+4000)-(0.00146*(D26+4000)) -> 51471.651 | F15: =(E26+4000)-(0.00146*(E26+4000)) -> 98123.984 | G15: =(F26+4000)-(0.00146*(F26+4000)) -> 143965.5 | H15: =(G26+4000)-(0.00146*(G26+4000)) -> 189010.29 | I15: =(H26+4000)-(0.00146*(H26+4000)) -> 233272.2 | J15: =(I26+4000)-(0.00125*(I26+4000)) -> 277207.35 | K15: =(J26+4000)-(0.00125*(J26+4000)) -> 320689.49 | L15: =(K26+4000)-(0.00125*(K26+4000)) -> 363523.86 | M15: =(L26+4000)-(0.00125*(L26+4000)) -> 405720.12 | N15: =(M26+4000)-(0.00125*(M26+4000)) -> 447287.77 | O15: =(N26+4000)-(0.00125*(N26+4000)) -> 488236.17 | P15: =(O26+4000)-(0.00104*(O26+4000)) -> 529545.46 | Q15: =(P26+4000)-(0.00104*(P26+4000)) -> 570651.16 | R15: =(Q26+4000)-(0.00104*(Q26+4000)) -> 611246.78 | S15: =(R26+4000)-(0.00104*(R26+4000)) -> 651338.66 | T15: =(S26+4000)-(0.00104*(S26+4000)) -> 690933.04 | U15: =(T26+4000)-(0.00104*(T26+4000)) -> 730036.1 | V15: =(U26+4000)-(0.00104*(U26+4000)) -> 768653.94 | W15: =(V26+4000)-(0.00104*(V26+4000)) -> 806792.57 | ... AB15: =(AA26+4000)-(0.00104*(AA26+4000)) -> 990503.25 | AC15: =(AB26+4000)-(0.000833*(AB26+4000)) -> 1027774 | AD15: =(AC26+4000)-(0.000833*(AC26+4000)) -> 1065288.2 | AE15: =(AD26+4000)-(0.000833*(AD26+4000)) -> 1102429.2 | AH15: J | AI15: =(AI14+4000)-0 -> 4000 | AJ15: =(AI26+4000)-0 -> 52000 | AK15: =(AJ26+4000)-0 -> 100000 | AL15: =(AK26+4000)-0 -> 148000 | AM15: =(AL26+4000)-0 -> 196000 | AN15: =(AM26+4000)-0 -> 244000 | AO15: =(AN26+4000)-0 -> 292000 | AP15: =(AO26+4000)-0 -> 340000 | AQ15: =(AP26+4000)-0 -> 388000 | ... BJ15: =(BI26+4000)-0 -> 1300000
A16: =0.0175/12 -> 0.0014583333 | B16: 1.75 | C16: F | D16: =(D15+4000)-(0.00146*(D15+4000)) -> 7982.4885 | E16: =(E15+4000)-(0.00146*(E15+4000)) -> 55390.663 | F16: =(F15+4000)-(0.00146*(F15+4000)) -> 101974.88 | G16: =(G15+4000)-(0.00146*(G15+4000)) -> 147749.47 | H16: =(H15+4000)-(0.00146*(H15+4000)) -> 192728.49 | I16: =(I15+4000)-(0.00146*(I15+4000)) -> 236925.78 | J16: =(J15+4000)-(0.00125*(J15+4000)) -> 280855.84 | K16: =(K15+4000)-(0.00125*(K15+4000)) -> 324283.63 | L16: =(L15+4000)-(0.00125*(L15+4000)) -> 367064.46 | M16: =(M15+4000)-(0.00125*(M15+4000)) -> 409207.97 | N16: =(N15+4000)-(0.00125*(N15+4000)) -> 450723.66 | O16: =(O15+4000)-(0.00125*(O15+4000)) -> 491620.87 | P16: =(P15+4000)-(0.00104*(P15+4000)) -> 532990.57 | Q16: =(Q15+4000)-(0.00104*(Q15+4000)) -> 574053.52 | R16: =(R15+4000)-(0.00104*(R15+4000)) -> 614606.92 | S16: =(S15+4000)-(0.00104*(S15+4000)) -> 654657.1 | T16: =(T15+4000)-(0.00104*(T15+4000)) -> 694210.31 | U16: =(U15+4000)-(0.00104*(U15+4000)) -> 733272.7 | V16: =(V15+4000)-(0.00104*(V15+4000)) -> 771850.38 | W16: =(W15+4000)-(0.00104*(W15+4000)) -> 809949.35 | ... AB16: =(AB15+4000)-(0.00104*(AB15+4000)) -> 993468.97 | AC16: =(AC15+4000)-(0.000833*(AC15+4000)) -> 1030914.6 | AD16: =(AD15+4000)-(0.000833*(AD15+4000)) -> 1068397.5 | AE16: =(AE15+4000)-(0.000833*(AE15+4000)) -> 1105507.5 | AH16: F | AI16: =(AI15+4000)-0 -> 8000 | AJ16: =(AJ15+4000)-0 -> 56000 | AK16: =(AK15+4000)-0 -> 104000 | AL16: =(AL15+4000)-0 -> 152000 | AM16: =(AM15+4000)-0 -> 200000 | AN16: =(AN15+4000)-0 -> 248000 | AO16: =(AO15+4000)-0 -> 296000 | AP16: =(AP15+4000)-0 -> 344000 | ... BJ16: =(BJ15+4000)-0 -> 1304000
A17: =0.015/12 -> 0.00125 | B17: 1.5 | C17: M | D17: =(D16+4000)-(0.00146*(D16+4000)) -> 11964.994 | E17: =(E16+4000)-(0.00146*(E16+4000)) -> 59303.952 | F17: =(F16+4000)-(0.00146*(F16+4000)) -> 105820.16 | G17: =(G16+4000)-(0.00146*(G16+4000)) -> 151527.92 | H17: =(H16+4000)-(0.00146*(H16+4000)) -> 196441.27 | I17: =(I16+4000)-(0.00146*(I16+4000)) -> 240574.03 | J17: =(J16+4000)-(0.00125*(J16+4000)) -> 284499.77 | K17: =(K16+4000)-(0.00125*(K16+4000)) -> 327873.27 | L17: =(L16+4000)-(0.00125*(L16+4000)) -> 370600.63 | M17: =(M16+4000)-(0.00125*(M16+4000)) -> 412691.46 | N17: =(N16+4000)-(0.00125*(N16+4000)) -> 454155.25 | O17: =(O16+4000)-(0.00125*(O16+4000)) -> 495001.35 | P17: =(P16+4000)-(0.00104*(P16+4000)) -> 536432.1 | Q17: =(Q16+4000)-(0.00104*(Q16+4000)) -> 577452.34 | R17: =(R16+4000)-(0.00104*(R16+4000)) -> 617963.57 | S17: =(S16+4000)-(0.00104*(S16+4000)) -> 657972.1 | T17: =(T16+4000)-(0.00104*(T16+4000)) -> 697484.17 | U17: =(U16+4000)-(0.00104*(U16+4000)) -> 736505.94 | V17: =(V16+4000)-(0.00104*(V16+4000)) -> 775043.49 | W17: =(W16+4000)-(0.00104*(W16+4000)) -> 813102.84 | ... AB17: =(AB16+4000)-(0.00104*(AB16+4000)) -> 996431.6 | AC17: =(AC16+4000)-(0.000833*(AC16+4000)) -> 1034052.5 | AD17: =(AD16+4000)-(0.000833*(AD16+4000)) -> 1071504.2 | AE17: =(AE16+4000)-(0.000833*(AE16+4000)) -> 1108583.3 | AH17: M | AI17: =(AI16+4000)-0 -> 12000 | AJ17: =(AJ16+4000)-0 -> 60000 | AK17: =(AK16+4000)-0 -> 108000 | AL17: =(AL16+4000)-0 -> 156000 | AM17: =(AM16+4000)-0 -> 204000 | AN17: =(AN16+4000)-0 -> 252000 | AO17: =(AO16+4000)-0 -> 300000 | AP17: =(AP16+4000)-0 -> 348000 | ... BJ17: =(BJ16+4000)-0 -> 1308000
A18: =0.0125/12 -> 0.0010416667 | B18: 1.25 | C18: A | D18: =(D17+4000)-(0.00146*(D17+4000)) -> 15941.685 | E18: =(E17+4000)-(0.00146*(E17+4000)) -> 63211.528 | F18: =(F17+4000)-(0.00146*(F17+4000)) -> 109659.82 | G18: =(G17+4000)-(0.00146*(G17+4000)) -> 155300.84 | H18: =(H17+4000)-(0.00146*(H17+4000)) -> 200148.63 | I18: =(I17+4000)-(0.00146*(I17+4000)) -> 244216.95 | J18: =(J17+4000)-(0.00125*(J17+4000)) -> 288139.15 | K18: =(K17+4000)-(0.00125*(K17+4000)) -> 331458.43 | L18: =(L17+4000)-(0.00125*(L17+4000)) -> 374132.38 | M18: =(M17+4000)-(0.00125*(M17+4000)) -> 416170.6 | N18: =(N17+4000)-(0.00125*(N17+4000)) -> 457582.56 | O18: =(O17+4000)-(0.00125*(O17+4000)) -> 498377.59 | P18: =(P17+4000)-(0.00104*(P17+4000)) -> 539870.05 | Q18: =(Q17+4000)-(0.00104*(Q17+4000)) -> 580847.63 | R18: =(R17+4000)-(0.00104*(R17+4000)) -> 621316.73 | S18: =(S17+4000)-(0.00104*(S17+4000)) -> 661283.65 | T18: =(T17+4000)-(0.00104*(T17+4000)) -> 700754.63 | U18: =(U17+4000)-(0.00104*(U17+4000)) -> 739735.81 | V18: =(V17+4000)-(0.00104*(V17+4000)) -> 778233.29 | W18: =(W17+4000)-(0.00104*(W17+4000)) -> 816253.05 | ... AB18: =(AB17+4000)-(0.00104*(AB17+4000)) -> 999391.15 | AC18: =(AC17+4000)-(0.000833*(AC17+4000)) -> 1037187.8 | AD18: =(AD17+4000)-(0.000833*(AD17+4000)) -> 1074608.3 | AE18: =(AE17+4000)-(0.000833*(AE17+4000)) -> 1111656.5 | AH18: A | AI18: =(AI17+4000)-0 -> 16000 | AJ18: =(AJ17+4000)-0 -> 64000 | AK18: =(AK17+4000)-0 -> 112000 | AL18: =(AL17+4000)-0 -> 160000 | AM18: =(AM17+4000)-0 -> 208000 | AN18: =(AN17+4000)-0 -> 256000 | AO18: =(AO17+4000)-0 -> 304000 | AP18: =(AP17+4000)-0 -> 352000 | ... BJ18: =(BJ17+4000)-0 -> 1312000
A19: =0.01/12 -> 0.00083333333 | B19: 1 | C19: M | D19: =(D18+4000)-(0.00146*(D18+4000)) -> 19912.57 | E19: =(E18+4000)-(0.00146*(E18+4000)) -> 67113.4 | F19: =(F18+4000)-(0.00146*(F18+4000)) -> 113493.88 | G19: =(G18+4000)-(0.00146*(G18+4000)) -> 159068.27 | H19: =(H18+4000)-(0.00146*(H18+4000)) -> 203850.57 | I19: =(I18+4000)-(0.00146*(I18+4000)) -> 247854.56 | J19: =(J18+4000)-(0.00125*(J18+4000)) -> 291773.97 | K19: =(K18+4000)-(0.00125*(K18+4000)) -> 335039.11 | L19: =(L18+4000)-(0.00125*(L18+4000)) -> 377659.71 | M19: =(M18+4000)-(0.00125*(M18+4000)) -> 419645.38 | N19: =(N18+4000)-(0.00125*(N18+4000)) -> 461005.58 | O19: =(O18+4000)-(0.00104*(O18+4000)) -> 501855.12 | P19: =(P18+4000)-(0.00104*(P18+4000)) -> 543304.43 | Q19: =(Q18+4000)-(0.00104*(Q18+4000)) -> 584239.39 | R19: =(R18+4000)-(0.00104*(R18+4000)) -> 624666.4 | S19: =(S18+4000)-(0.00104*(S18+4000)) -> 664591.75 | T19: =(T18+4000)-(0.00104*(T18+4000)) -> 704021.68 | U19: =(U18+4000)-(0.00104*(U18+4000)) -> 742962.33 | V19: =(V18+4000)-(0.00104*(V18+4000)) -> 781419.77 | ... AA19: =(AA18+4000)-(0.00104*(AA18+4000)) -> 966666.1 | AB19: =(AB18+4000)-(0.000833*(AB18+4000)) -> 1002555.3 | AC19: =(AC18+4000)-(0.000833*(AC18+4000)) -> 1040320.5 | AD19: =(AD18+4000)-(0.000833*(AD18+4000)) -> 1077709.8 | AE19: =(AE18+4000)-(0.000833*(AE18+4000)) -> 1114727.2 | AH19: M | AI19: =(AI18+4000)-0 -> 20000 | AJ19: =(AJ18+4000)-0 -> 68000 | AK19: =(AK18+4000)-0 -> 116000 | AL19: =(AL18+4000)-0 -> 164000 | AM19: =(AM18+4000)-0 -> 212000 | AN19: =(AN18+4000)-0 -> 260000 | AO19: =(AO18+4000)-0 -> 308000 | AP19: =(AP18+4000)-0 -> 356000 | ... BJ19: =(BJ18+4000)-0 -> 1316000
C20: J | D20: =(D19+4000)-(0.00146*(D19+4000)) -> 23877.658 | E20: =(E19+4000)-(0.00146*(E19+4000)) -> 71009.574 | F20: =(F19+4000)-(0.00146*(F19+4000)) -> 117322.34 | G20: =(G19+4000)-(0.00146*(G19+4000)) -> 162830.19 | H20: =(H19+4000)-(0.00146*(H19+4000)) -> 207547.11 | I20: =(I19+4000)-(0.00125*(I19+4000)) -> 251539.74 | J20: =(J19+4000)-(0.00125*(J19+4000)) -> 295404.26 | K20: =(K19+4000)-(0.00125*(K19+4000)) -> 338615.31 | L20: =(L19+4000)-(0.00125*(L19+4000)) -> 381182.64 | M20: =(M19+4000)-(0.00125*(M19+4000)) -> 423115.83 | N20: =(N19+4000)-(0.00125*(N19+4000)) -> 464424.32 | O20: =(O19+4000)-(0.00104*(O19+4000)) -> 505329.03 | P20: =(P19+4000)-(0.00104*(P19+4000)) -> 546735.23 | Q20: =(Q19+4000)-(0.00104*(Q19+4000)) -> 587627.62 | R20: =(R19+4000)-(0.00104*(R19+4000)) -> 628012.59 | S20: =(S19+4000)-(0.00104*(S19+4000)) -> 667896.42 | T20: =(T19+4000)-(0.00104*(T19+4000)) -> 707285.34 | U20: =(U19+4000)-(0.00104*(U19+4000)) -> 746185.49 | V20: =(V19+4000)-(0.00104*(V19+4000)) -> 784602.93 | ... AA20: =(AA19+4000)-(0.00104*(AA19+4000)) -> 969656.6 | AB20: =(AB19+4000)-(0.000833*(AB19+4000)) -> 1005716.9 | AC20: =(AC19+4000)-(0.000833*(AC19+4000)) -> 1043450.5 | AD20: =(AD19+4000)-(0.000833*(AD19+4000)) -> 1080808.8 | AE20: =(AE19+4000)-(0.000833*(AE19+4000)) -> 1117795.3 | AH20: J | AI20: =(AI19+4000)-0 -> 24000 | AJ20: =(AJ19+4000)-0 -> 72000 | AK20: =(AK19+4000)-0 -> 120000 | AL20: =(AL19+4000)-0 -> 168000 | AM20: =(AM19+4000)-0 -> 216000 | AN20: =(AN19+4000)-0 -> 264000 | AO20: =(AO19+4000)-0 -> 312000 | AP20: =(AP19+4000)-0 -> 360000 | ... BJ20: =(BJ19+4000)-0 -> 1320000
C21: J | D21: =(D20+4000)-(0.00146*(D20+4000)) -> 27836.957 | E21: =(E20+4000)-(0.00146*(E20+4000)) -> 74900.06 | F21: =(F20+4000)-(0.00146*(F20+4000)) -> 121145.21 | G21: =(G20+4000)-(0.00146*(G20+4000)) -> 166586.61 | H21: =(H20+4000)-(0.00146*(H20+4000)) -> 211238.25 | I21: =(I20+4000)-(0.00125*(I20+4000)) -> 255220.31 | J21: =(J20+4000)-(0.00125*(J20+4000)) -> 299030 | K21: =(K20+4000)-(0.00125*(K20+4000)) -> 342187.04 | L21: =(L20+4000)-(0.00125*(L20+4000)) -> 384701.16 | M21: =(M20+4000)-(0.00125*(M20+4000)) -> 426581.93 | N21: =(N20+4000)-(0.00125*(N20+4000)) -> 467838.79 | O21: =(O20+4000)-(0.00104*(O20+4000)) -> 508799.33 | P21: =(P20+4000)-(0.00104*(P20+4000)) -> 550162.46 | Q21: =(Q20+4000)-(0.00104*(Q20+4000)) -> 591012.33 | R21: =(R20+4000)-(0.00104*(R20+4000)) -> 631355.29 | S21: =(S20+4000)-(0.00104*(S20+4000)) -> 671197.65 | T21: =(T20+4000)-(0.00104*(T20+4000)) -> 710545.6 | U21: =(U20+4000)-(0.00104*(U20+4000)) -> 749405.29 | V21: =(V20+4000)-(0.00104*(V20+4000)) -> 787782.78 | ... AA21: =(AA20+4000)-(0.00104*(AA20+4000)) -> 972644 | AB21: =(AB20+4000)-(0.000833*(AB20+4000)) -> 1008875.8 | AC21: =(AC20+4000)-(0.000833*(AC20+4000)) -> 1046578 | AD21: =(AD20+4000)-(0.000833*(AD20+4000)) -> 1083905.1 | AE21: =(AE20+4000)-(0.000833*(AE20+4000)) -> 1120860.8 | AH21: J | AI21: =(AI20+4000)-0 -> 28000 | AJ21: =(AJ20+4000)-0 -> 76000 | AK21: =(AK20+4000)-0 -> 124000 | AL21: =(AL20+4000)-0 -> 172000 | AM21: =(AM20+4000)-0 -> 220000 | AN21: =(AN20+4000)-0 -> 268000 | AO21: =(AO20+4000)-0 -> 316000 | AP21: =(AP20+4000)-0 -> 364000 | ... BJ21: =(BJ20+4000)-0 -> 1324000
C22: A | D22: =(D21+4000)-(0.00146*(D21+4000)) -> 31790.475 | E22: =(E21+4000)-(0.00146*(E21+4000)) -> 78784.866 | F22: =(F21+4000)-(0.00146*(F21+4000)) -> 124962.49 | G22: =(G21+4000)-(0.00146*(G21+4000)) -> 170337.56 | H22: =(H21+4000)-(0.00146*(H21+4000)) -> 214924 | I22: =(I21+4000)-(0.00125*(I21+4000)) -> 258896.29 | J22: =(J21+4000)-(0.00125*(J21+4000)) -> 302651.21 | K22: =(K21+4000)-(0.00125*(K21+4000)) -> 345754.31 | L22: =(L21+4000)-(0.00125*(L21+4000)) -> 388215.28 | M22: =(M21+4000)-(0.00125*(M21+4000)) -> 430043.7 | N22: =(N21+4000)-(0.00125*(N21+4000)) -> 471248.99 | O22: =(O21+4000)-(0.00104*(O21+4000)) -> 512266.02 | P22: =(P21+4000)-(0.00104*(P21+4000)) -> 553586.14 | Q22: =(Q21+4000)-(0.00104*(Q21+4000)) -> 594393.52 | R22: =(R21+4000)-(0.00104*(R21+4000)) -> 634694.52 | S22: =(S21+4000)-(0.00104*(S21+4000)) -> 674495.44 | T22: =(T21+4000)-(0.00104*(T21+4000)) -> 713802.47 | U22: =(U21+4000)-(0.00104*(U21+4000)) -> 752621.75 | V22: =(V21+4000)-(0.00104*(V21+4000)) -> 790959.33 | ... AA22: =(AA21+4000)-(0.00104*(AA21+4000)) -> 975628.29 | AB22: =(AB21+4000)-(0.000833*(AB21+4000)) -> 1012032 | AC22: =(AC21+4000)-(0.000833*(AC21+4000)) -> 1049702.9 | AD22: =(AD21+4000)-(0.000833*(AD21+4000)) -> 1086998.9 | AE22: =(AE21+4000)-(0.000833*(AE21+4000)) -> 1123923.8 | AH22: A | AI22: =(AI21+4000)-0 -> 32000 | AJ22: =(AJ21+4000)-0 -> 80000 | AK22: =(AK21+4000)-0 -> 128000 | AL22: =(AL21+4000)-0 -> 176000 | AM22: =(AM21+4000)-0 -> 224000 | AN22: =(AN21+4000)-0 -> 272000 | AO22: =(AO21+4000)-0 -> 320000 | AP22: =(AP21+4000)-0 -> 368000 | ... BJ22: =(BJ21+4000)-0 -> 1328000
C23: S | D23: =(D22+4000)-(0.00146*(D22+4000)) -> 35738.221 | E23: =(E22+4000)-(0.00146*(E22+4000)) -> 82664 | F23: =(F22+4000)-(0.00146*(F22+4000)) -> 128774.21 | G23: =(G22+4000)-(0.00146*(G22+4000)) -> 174083.02 | H23: =(H22+4000)-(0.00146*(H22+4000)) -> 218604.37 | I23: =(I22+4000)-(0.00125*(I22+4000)) -> 262567.67 | J23: =(J22+4000)-(0.00125*(J22+4000)) -> 306267.9 | K23: =(K22+4000)-(0.00125*(K22+4000)) -> 349317.12 | L23: =(L22+4000)-(0.00125*(L22+4000)) -> 391725.01 | M23: =(M22+4000)-(0.00125*(M22+4000)) -> 433501.15 | N23: =(N22+4000)-(0.00125*(N22+4000)) -> 474654.93 | O23: =(O22+4000)-(0.00104*(O22+4000)) -> 515729.1 | P23: =(P22+4000)-(0.00104*(P22+4000)) -> 557006.25 | Q23: =(Q22+4000)-(0.00104*(Q22+4000)) -> 597771.19 | R23: =(R22+4000)-(0.00104*(R22+4000)) -> 638030.28 | S23: =(S22+4000)-(0.00104*(S22+4000)) -> 677789.81 | T23: =(T22+4000)-(0.00104*(T22+4000)) -> 717055.96 | U23: =(U22+4000)-(0.00104*(U22+4000)) -> 755834.87 | V23: =(V22+4000)-(0.00104*(V22+4000)) -> 794132.57 | ... AA23: =(AA22+4000)-(0.00104*(AA22+4000)) -> 978609.48 | AB23: =(AB22+4000)-(0.000833*(AB22+4000)) -> 1015185.7 | AC23: =(AC22+4000)-(0.000833*(AC22+4000)) -> 1052825.2 | AD23: =(AD22+4000)-(0.000833*(AD22+4000)) -> 1090090.1 | AE23: =(AE22+4000)-(0.000833*(AE22+4000)) -> 1126984.2 | AH23: S | AI23: =(AI22+4000)-0 -> 36000 | AJ23: =(AJ22+4000)-0 -> 84000 | AK23: =(AK22+4000)-0 -> 132000 | AL23: =(AL22+4000)-0 -> 180000 | AM23: =(AM22+4000)-0 -> 228000 | AN23: =(AN22+4000)-0 -> 276000 | AO23: =(AO22+4000)-0 -> 324000 | AP23: =(AP22+4000)-0 -> 372000 | ... BJ23: =(BJ22+4000)-0 -> 1332000
C24: O | D24: =(D23+4000)-(0.00146*(D23+4000)) -> 39680.203 | E24: =(E23+4000)-(0.00146*(E23+4000)) -> 86537.471 | F24: =(F23+4000)-(0.00146*(F23+4000)) -> 132580.36 | G24: =(G23+4000)-(0.00146*(G23+4000)) -> 177823.02 | H24: =(H23+4000)-(0.00146*(H23+4000)) -> 222279.37 | I24: =(I23+4000)-(0.00125*(I23+4000)) -> 266234.46 | J24: =(J23+4000)-(0.00125*(J23+4000)) -> 309880.06 | K24: =(K23+4000)-(0.00125*(K23+4000)) -> 352875.47 | L24: =(L23+4000)-(0.00125*(L23+4000)) -> 395230.36 | M24: =(M23+4000)-(0.00125*(M23+4000)) -> 436954.27 | N24: =(N23+4000)-(0.00125*(N23+4000)) -> 478056.61 | O24: =(O23+4000)-(0.00104*(O23+4000)) -> 519188.58 | P24: =(P23+4000)-(0.00104*(P23+4000)) -> 560422.8 | Q24: =(Q23+4000)-(0.00104*(Q23+4000)) -> 601145.34 | R24: =(R23+4000)-(0.00104*(R23+4000)) -> 641362.57 | S24: =(S23+4000)-(0.00104*(S23+4000)) -> 681080.74 | T24: =(T23+4000)-(0.00104*(T23+4000)) -> 720306.06 | U24: =(U23+4000)-(0.00104*(U23+4000)) -> 759044.64 | V24: =(V23+4000)-(0.00104*(V23+4000)) -> 797302.51 | ... AA24: =(AA23+4000)-(0.00104*(AA23+4000)) -> 981587.56 | AB24: =(AB23+4000)-(0.000833*(AB23+4000)) -> 1018336.7 | AC24: =(AC23+4000)-(0.000833*(AC23+4000)) -> 1055944.8 | AD24: =(AD23+4000)-(0.000833*(AD23+4000)) -> 1093178.7 | AE24: =(AE23+4000)-(0.000833*(AE23+4000)) -> 1130042.1 | AH24: O | AI24: =(AI23+4000)-0 -> 40000 | AJ24: =(AJ23+4000)-0 -> 88000 | AK24: =(AK23+4000)-0 -> 136000 | AL24: =(AL23+4000)-0 -> 184000 | AM24: =(AM23+4000)-0 -> 232000 | AN24: =(AN23+4000)-0 -> 280000 | AO24: =(AO23+4000)-0 -> 328000 | AP24: =(AP23+4000)-0 -> 376000 | ... BJ24: =(BJ23+4000)-0 -> 1336000
C25: N | D25: =(D24+4000)-(0.00146*(D24+4000)) -> 43616.43 | E25: =(E24+4000)-(0.00146*(E24+4000)) -> 90405.286 | F25: =(F24+4000)-(0.00146*(F24+4000)) -> 136380.95 | G25: =(G24+4000)-(0.00146*(G24+4000)) -> 181557.56 | H25: =(H24+4000)-(0.00146*(H24+4000)) -> 225949 | I25: =(I24+4000)-(0.00125*(I24+4000)) -> 269896.66 | J25: =(J24+4000)-(0.00125*(J24+4000)) -> 313487.71 | K25: =(K24+4000)-(0.00125*(K24+4000)) -> 356429.37 | L25: =(L24+4000)-(0.00125*(L24+4000)) -> 398731.32 | M25: =(M24+4000)-(0.00125*(M24+4000)) -> 440403.08 | N25: =(N24+4000)-(0.00125*(N24+4000)) -> 481454.04 | O25: =(O24+4000)-(0.00104*(O24+4000)) -> 522644.47 | P25: =(P24+4000)-(0.00104*(P24+4000)) -> 563835.8 | Q25: =(Q24+4000)-(0.00104*(Q24+4000)) -> 604515.99 | R25: =(R24+4000)-(0.00104*(R24+4000)) -> 644691.39 | S25: =(S24+4000)-(0.00104*(S24+4000)) -> 684368.26 | T25: =(T24+4000)-(0.00104*(T24+4000)) -> 723552.78 | U25: =(U24+4000)-(0.00104*(U24+4000)) -> 762251.07 | V25: =(V24+4000)-(0.00104*(V24+4000)) -> 800469.16 | ... AA25: =(AA24+4000)-(0.00104*(AA24+4000)) -> 984562.55 | AB25: =(AB24+4000)-(0.000833*(AB24+4000)) -> 1021485.1 | AC25: =(AC24+4000)-(0.000833*(AC24+4000)) -> 1059061.9 | AD25: =(AD24+4000)-(0.000833*(AD24+4000)) -> 1096264.8 | AE25: =(AE24+4000)-(0.000833*(AE24+4000)) -> 1133097.5 | AH25: N | AI25: =(AI24+4000)-0 -> 44000 | AJ25: =(AJ24+4000)-0 -> 92000 | AK25: =(AK24+4000)-0 -> 140000 | AL25: =(AL24+4000)-0 -> 188000 | AM25: =(AM24+4000)-0 -> 236000 | AN25: =(AN24+4000)-0 -> 284000 | AO25: =(AO24+4000)-0 -> 332000 | AP25: =(AP24+4000)-0 -> 380000 | ... BJ25: =(BJ24+4000)-0 -> 1340000
C26: D | D26: =(D25+4000)-(0.00146*(D25+4000)) -> 47546.91 | E26: =(E25+4000)-(0.00146*(E25+4000)) -> 94267.454 | F26: =(F25+4000)-(0.00146*(F25+4000)) -> 140176 | G26: =(G25+4000)-(0.00146*(G25+4000)) -> 185286.65 | H26: =(H25+4000)-(0.00146*(H25+4000)) -> 229613.28 | I26: =(I25+4000)-(0.00125*(I25+4000)) -> 273554.29 | J26: =(J25+4000)-(0.00125*(J25+4000)) -> 317090.85 | K26: =(K25+4000)-(0.00125*(K25+4000)) -> 359978.84 | L26: =(L25+4000)-(0.00125*(L25+4000)) -> 402227.91 | M26: =(M25+4000)-(0.00125*(M25+4000)) -> 443847.58 | N26: =(N25+4000)-(0.00125*(N25+4000)) -> 484847.23 | O26: =(O25+4000)-(0.00104*(O25+4000)) -> 526096.76 | P26: =(P25+4000)-(0.00104*(P25+4000)) -> 567245.25 | Q26: =(Q25+4000)-(0.00104*(Q25+4000)) -> 607883.14 | R26: =(R25+4000)-(0.00104*(R25+4000)) -> 648016.75 | S26: =(S25+4000)-(0.00104*(S25+4000)) -> 687652.36 | T26: =(T25+4000)-(0.00104*(T25+4000)) -> 726796.13 | U26: =(U25+4000)-(0.00104*(U25+4000)) -> 765454.17 | V26: =(V25+4000)-(0.00104*(V25+4000)) -> 803632.51 | ... AA26: =(AA25+4000)-(0.00104*(AA25+4000)) -> 987534.45 | AB26: =(AB25+4000)-(0.000833*(AB25+4000)) -> 1024630.9 | AC26: =(AC25+4000)-(0.000833*(AC25+4000)) -> 1062176.4 | AD26: =(AD25+4000)-(0.000833*(AD25+4000)) -> 1099348.2 | AE26: =(AE25+4000)-(0.000833*(AE25+4000)) -> 1136150.3 | AH26: D | AI26: =(AI25+4000)-0 -> 48000 | AJ26: =(AJ25+4000)-0 -> 96000 | AK26: =(AK25+4000)-0 -> 144000 | AL26: =(AL25+4000)-0 -> 192000 | AM26: =(AM25+4000)-0 -> 240000 | AN26: =(AN25+4000)-0 -> 288000 | AO26: =(AO25+4000)-0 -> 336000 | AP26: =(AP25+4000)-0 -> 384000 | ... BJ26: =(BJ25+4000)-0 -> 1344000
AB28: After saving $4K/mo x 25 years you should have (4000x12x25) = 1,200,000 | BG28: After saving $4K/mo x 25 years you should have (4000x12x25) = 1,200,000
AB29: 1.2M - 1,024,631 = $175,369. | BG29: 1.2M - 1,024,631 = $175,369.
AB30: Average = 7,014.76/yr x 25yrs | BG30: Average = 7,014.76/yr x 25yrs
AB31: Let's see what happens if you actually invest your money, get a return, and have an opportunity cost of your advisor's fee being compounded annually | BG31: Let's see what happens if you actually invest your money, get a return, and have an opportunity cost of your advisor's fee being compounded annually
D32: Scenario 2 | AI32: Scenario 2 | AJ32: WITHOUT AN ADVISOR
D33: Assume 4% annual return on investments | AI33: Assume 4% annual return on investments
D34: Assume 4K/mo invested | AI34: Assume 4K/mo invested
D35: Y1 | E35: Y2 | F35: Y3 | G35: Y4 | H35: Y5 | I35: Y6 | J35: Y7 | K35: Y8 | L35: Y9 | M35: Y10 | N35: Y11 | O35: Y12 | P35: Y13 | Q35: Y14 | R35: Y15 | S35: Y16 | T35: Y17 | U35: Y18 | V35: Y19 | W35: Y20 | X35: Y21 | Y35: Y22 | Z35: Y23 | AA35: Y24 | AB35: Y25 | AC35: Y26 | AD35: Y27 | AE35: Y28 | AI35: Y1 | AJ35: Y2 | AK35: Y3 | AL35: Y4 | AM35: Y5 | AN35: Y6 | AO35: Y7 | AP35: Y8 | AQ35: Y9 | AR35: Y10 | AS35: Y11 | AT35: Y12 | AU35: Y13 | AV35: Y14 | AW35: Y15 | AX35: Y16 | AY35: Y17 | AZ35: Y18 | BA35: Y19 | BB35: Y20 | BC35: Y21 | BD35: Y22 | BE35: Y23 | BF35: Y24 | BG35: Y25 | BH35: Y26 | BI35: Y27 | BJ35: Y28
D36: 0 | AI36: 0
D37: =(D36+4000)*1.00328-(0.00146*(D36+4000)) -> 4007.28 | E37: =(D48+4000)*1.00328-(0.00146*(D48+4000)) -> 52667.327 | F37: =(E48+4000)*1.00328-(0.00146*(E48+4000)) -> 102400.81 | G37: =(F48+4000)*1.00328-(0.00146*(F48+4000)) -> 153231.42 | H37: =(G48+4000)*1.00328-(0.00146*(G48+4000)) -> 205183.34 | I37: =(H48+4000)*1.00328-(0.00125*(H48+4000)) -> 258388.77 | J37: =(I48+4000)*1.00328-(0.00125*(I48+4000)) -> 313391.98 | K37: =(J48+4000)*1.00328-(0.00125*(J48+4000)) -> 369750.12 | L37: =(K48+4000)*1.00328-(0.00125*(K48+4000)) -> 427496.58 | M37: =(L48+4000)*1.00328-(0.00125*(L48+4000)) -> 486665.55 | N37: =(M48+4000)*1.00328-(0.00104*(M48+4000)) -> 548402.1 | O37: =(N48+4000)*1.00328-(0.00104*(N48+4000)) -> 612030.77 | P37: =(O48+4000)*1.00328-(0.00104*(O48+4000)) -> 677391.01 | Q37: =(P48+4000)*1.00328-(0.00104*(P48+4000)) -> 744529.95 | R37: =(Q48+4000)*1.00328-(0.00104*(Q48+4000)) -> 813495.97 | S37: =(R48+4000)*1.00328-(0.00104*(R48+4000)) -> 884338.82 | T37: =(S48+4000)*1.00328-(0.00104*(S48+4000)) -> 957109.55 | U37: =(T48+4000)*1.00328-(0.00125*(T48+4000)) -> 1032697.8 | V37: =(U48+4000)*1.00328-(0.00125*(U48+4000)) -> 1106775.2 | W37: =(V48+4000)*1.00328-(0.00125*(V48+4000)) -> 1182677.4 | X37: =(W48+4000)*1.00328-(0.00125*(W48+4000)) -> 1260449.4 | Y37: =(X48+4000)*1.00328-(0.00125*(X48+4000)) -> 1340137.2 | Z37: =(Y48+4000)*1.00328-(0.00125*(Y48+4000)) -> 1421788 | AA37: =(Z48+4000)*1.00328-(0.00125*(Z48+4000)) -> 1505450.1 | AB37: =(AA48+4000)*1.00328-(0.00125*(AA48+4000)) -> 1591173.2 | ... AE37: =(AD48+4000)*1.00328-(0.00125*(AD48+4000)) -> 1861222 | AI37: =(AI36+4000)*1.00328-0 -> 4013.12 | AJ37: =(AI48+4000)*1.00328-0 -> 53209.726 | AK37: =(AJ48+4000)*1.00328-0 -> 104378.03 | AL37: =(AK48+4000)*1.00328-0 -> 157597.05 | AM37: =(AL48+4000)*1.00328-0 -> 212948.97 | AN37: =(AM48+4000)*1.00328-0 -> 270519.28 | AO37: =(AN48+4000)*1.00328-0 -> 330396.89 | AP37: =(AO48+4000)*1.00328-0 -> 392674.26 | AQ37: =(AP48+4000)*1.00328-0 -> 457447.58 | ... BJ37: =(BI48+4000)*1.00328-0 -> 2323058.5
D38: =(D37+4000)*1.00328-(0.00146*(D37+4000)) -> 8021.8532 | E38: =(E37+4000)*1.00328-(0.00146*(E37+4000)) -> 56770.462 | F38: =(F37+4000)*1.00328-(0.00146*(F37+4000)) -> 106594.46 | G38: =(G37+4000)*1.00328-(0.00146*(G37+4000)) -> 157517.58 | H38: =(H37+4000)*1.00328-(0.00146*(H37+4000)) -> 209564.05 | I38: =(I37+4000)*1.00328-(0.00125*(I37+4000)) -> 262921.42 | J38: =(J37+4000)*1.00328-(0.00125*(J37+4000)) -> 318036.28 | K38: =(K37+4000)*1.00328-(0.00125*(K37+4000)) -> 374508.83 | L38: =(L37+4000)*1.00328-(0.00125*(L37+4000)) -> 432372.52 | M38: =(M37+4000)*1.00328-(0.00125*(M37+4000)) -> 491661.6 | N38: =(N37+4000)*1.00328-(0.00104*(N37+4000)) -> 553639.48 | O38: =(O37+4000)*1.00328-(0.00104*(O37+4000)) -> 617410.68 | P38: =(P37+4000)*1.00328-(0.00104*(P37+4000)) -> 682917.33 | Q38: =(Q37+4000)*1.00328-(0.00104*(Q37+4000)) -> 750206.65 | R38: =(R37+4000)*1.00328-(0.00104*(R37+4000)) -> 819327.16 | S38: =(S37+4000)*1.00328-(0.00104*(S37+4000)) -> 890328.7 | T38: =(T37+4000)*1.00328-(0.00104*(T37+4000)) -> 963262.44 | U38: =(U37+4000)*1.00328-(0.00125*(U37+4000)) -> 1038802.3 | V38: =(V37+4000)*1.00328-(0.00125*(V37+4000)) -> 1113030.1 | W38: =(W37+4000)*1.00328-(0.00125*(W37+4000)) -> 1189086.3 | X38: =(X37+4000)*1.00328-(0.00125*(X37+4000)) -> 1267016.2 | Y38: =(Y37+4000)*1.00328-(0.00125*(Y37+4000)) -> 1346865.8 | Z38: =(Z37+4000)*1.00328-(0.00125*(Z37+4000)) -> 1428682.3 | AA38: =(AA37+4000)*1.00328-(0.00125*(AA37+4000)) -> 1512514.3 | AB38: =(AB37+4000)*1.00328-(0.00125*(AB37+4000)) -> 1598411.4 | ... AE38: =(AE37+4000)*1.00328-(0.00125*(AE37+4000)) -> 1869008.4 | AI38: =(AI37+4000)*1.00328-0 -> 8039.403 | AJ38: =(AJ37+4000)*1.00328-0 -> 57397.374 | AK38: =(AK37+4000)*1.00328-0 -> 108733.51 | AL38: =(AL37+4000)*1.00328-0 -> 162127.09 | AM38: =(AM37+4000)*1.00328-0 -> 217660.56 | AN38: =(AN37+4000)*1.00328-0 -> 275419.71 | AO38: =(AO37+4000)*1.00328-0 -> 335493.71 | AP38: =(AP37+4000)*1.00328-0 -> 397975.36 | ... BJ38: =(BJ37+4000)*1.00328-0 -> 2334691.3
A39: =0.0175/12 -> 0.0014583333 | B39: 1.75 | D39: =(D38+4000)*1.00328-(0.00146*(D38+4000)) -> 12043.733 | E39: =(E38+4000)*1.00328-(0.00146*(E38+4000)) -> 60881.064 | F39: =(F38+4000)*1.00328-(0.00146*(F38+4000)) -> 110795.74 | G39: =(G38+4000)*1.00328-(0.00146*(G38+4000)) -> 161811.54 | H39: =(H38+4000)*1.00328-(0.00146*(H38+4000)) -> 213952.74 | I39: =(I38+4000)*1.00328-(0.00125*(I38+4000)) -> 267463.27 | J39: =(J38+4000)*1.00328-(0.00125*(J38+4000)) -> 322690.02 | K39: =(K38+4000)*1.00328-(0.00125*(K38+4000)) -> 379277.2 | L39: =(L38+4000)*1.00328-(0.00125*(L38+4000)) -> 437258.35 | M39: =(M38+4000)*1.00328-(0.00125*(M38+4000)) -> 496667.8 | N39: =(N38+4000)*1.00328-(0.00104*(N38+4000)) -> 558888.59 | O39: =(O38+4000)*1.00328-(0.00104*(O38+4000)) -> 622802.64 | P39: =(P38+4000)*1.00328-(0.00104*(P38+4000)) -> 688456.02 | Q39: =(Q38+4000)*1.00328-(0.00104*(Q38+4000)) -> 755896.08 | R39: =(R38+4000)*1.00328-(0.00104*(R38+4000)) -> 825171.42 | S39: =(S38+4000)*1.00328-(0.00104*(S38+4000)) -> 896331.99 | T39: =(T38+4000)*1.00328-(0.00104*(T38+4000)) -> 969429.11 | U39: =(U38+4000)*1.00328-(0.00125*(U38+4000)) -> 1044919.2 | V39: =(V38+4000)*1.00328-(0.00125*(V38+4000)) -> 1119297.6 | W39: =(W38+4000)*1.00328-(0.00125*(W38+4000)) -> 1195508.3 | X39: =(X38+4000)*1.00328-(0.00125*(X38+4000)) -> 1273596.4 | Y39: =(Y38+4000)*1.00328-(0.00125*(Y38+4000)) -> 1353608 | Z39: =(Z38+4000)*1.00328-(0.00125*(Z38+4000)) -> 1435590.7 | AA39: =(AA38+4000)*1.00328-(0.00125*(AA38+4000)) -> 1519592.8 | AB39: =(AB38+4000)*1.00328-(0.00125*(AB38+4000)) -> 1605664.3 | ... AE39: =(AE38+4000)*1.00328-(0.00125*(AE38+4000)) -> 1876810.6 | AI39: =(AI38+4000)*1.00328-0 -> 12078.892 | AJ39: =(AJ38+4000)*1.00328-0 -> 61598.758 | AK39: =(AK38+4000)*1.00328-0 -> 113103.27 | AL39: =(AL38+4000)*1.00328-0 -> 166671.98 | AM39: =(AM38+4000)*1.00328-0 -> 222387.61 | AN39: =(AN38+4000)*1.00328-0 -> 280336.2 | AO39: =(AO38+4000)*1.00328-0 -> 340607.25 | AP39: =(AP38+4000)*1.00328-0 -> 403293.83 | ... BJ39: =(BJ38+4000)*1.00328-0 -> 2346362.2
A40: =0.015/12 -> 0.00125 | B40: 1.5 | D40: =(D39+4000)*1.00328-(0.00146*(D39+4000)) -> 16072.933 | E40: =(E39+4000)*1.00328-(0.00146*(E39+4000)) -> 64999.147 | F40: =(F39+4000)*1.00328-(0.00146*(F39+4000)) -> 115004.67 | G40: =(G39+4000)*1.00328-(0.00146*(G39+4000)) -> 166113.32 | H40: =(H39+4000)*1.00328-(0.00146*(H39+4000)) -> 218349.41 | I40: =(I39+4000)*1.00328-(0.00125*(I39+4000)) -> 272014.34 | J40: =(J39+4000)*1.00328-(0.00125*(J39+4000)) -> 327353.2 | K40: =(K39+4000)*1.00328-(0.00125*(K39+4000)) -> 384055.26 | L40: =(L39+4000)*1.00328-(0.00125*(L39+4000)) -> 442154.11 | M40: =(M39+4000)*1.00328-(0.00104*(M39+4000)) -> 501789.29 | N40: =(N39+4000)*1.00328-(0.00104*(N39+4000)) -> 564149.46 | O40: =(O39+4000)*1.00328-(0.00104*(O39+4000)) -> 628206.68 | P40: =(P39+4000)*1.00328-(0.00104*(P39+4000)) -> 694007.13 | Q40: =(Q39+4000)*1.00328-(0.00104*(Q39+4000)) -> 761598.24 | R40: =(R39+4000)*1.00328-(0.00104*(R39+4000)) -> 831028.76 | S40: =(S39+4000)*1.00328-(0.00104*(S39+4000)) -> 902348.74 | T40: =(T39+4000)*1.00328-(0.00104*(T39+4000)) -> 975609.59 | U40: =(U39+4000)*1.00328-(0.00125*(U39+4000)) -> 1051048.5 | V40: =(V39+4000)*1.00328-(0.00125*(V39+4000)) -> 1125577.9 | W40: =(W39+4000)*1.00328-(0.00125*(W39+4000)) -> 1201943.3 | X40: =(X39+4000)*1.00328-(0.00125*(X39+4000)) -> 1280189.9 | Y40: =(Y39+4000)*1.00328-(0.00125*(Y39+4000)) -> 1360364 | Z40: =(Z39+4000)*1.00328-(0.00125*(Z39+4000)) -> 1442513 | AA40: =(AA39+4000)*1.00328-(0.00125*(AA39+4000)) -> 1526685.7 | AB40: =(AB39+4000)*1.00328-(0.00125*(AB39+4000)) -> 1612932 | ... AE40: =(AE39+4000)*1.00328-(0.00125*(AE39+4000)) -> 1884628.7 | AI40: =(AI39+4000)*1.00328-0 -> 16131.631 | AJ40: =(AJ39+4000)*1.00328-0 -> 65813.922 | AK40: =(AK39+4000)*1.00328-0 -> 117487.37 | AL40: =(AL39+4000)*1.00328-0 -> 171231.79 | AM40: =(AM39+4000)*1.00328-0 -> 227130.16 | AN40: =(AN39+4000)*1.00328-0 -> 285268.83 | AO40: =(AO39+4000)*1.00328-0 -> 345737.56 | AP40: =(AP39+4000)*1.00328-0 -> 408629.76 | ... BJ40: =(BJ39+4000)*1.00328-0 -> 2358071.4
A41: =0.0125/12 -> 0.0010416667 | B41: 1.25 | D41: =(D40+4000)*1.00328-(0.00146*(D40+4000)) -> 20109.465 | E41: =(E40+4000)*1.00328-(0.00146*(E40+4000)) -> 69124.726 | F41: =(F40+4000)*1.00328-(0.00146*(F40+4000)) -> 119221.26 | G41: =(G40+4000)*1.00328-(0.00146*(G40+4000)) -> 170422.92 | H41: =(H40+4000)*1.00328-(0.00146*(H40+4000)) -> 222754.09 | I41: =(I40+4000)*1.00328-(0.00125*(I40+4000)) -> 276574.65 | J41: =(J40+4000)*1.00328-(0.00125*(J40+4000)) -> 332025.84 | K41: =(K40+4000)*1.00328-(0.00125*(K40+4000)) -> 388843.01 | L41: =(L40+4000)*1.00328-(0.00125*(L40+4000)) -> 447059.8 | M41: =(M40+4000)*1.00328-(0.00104*(M40+4000)) -> 506922.26 | N41: =(N40+4000)*1.00328-(0.00104*(N40+4000)) -> 569422.12 | O41: =(O40+4000)*1.00328-(0.00104*(O40+4000)) -> 633622.82 | P41: =(P40+4000)*1.00328-(0.00104*(P40+4000)) -> 699570.66 | Q41: =(Q40+4000)*1.00328-(0.00104*(Q40+4000)) -> 767313.18 | R41: =(R40+4000)*1.00328-(0.00104*(R40+4000)) -> 836899.23 | S41: =(S40+4000)*1.00328-(0.00104*(S40+4000)) -> 908378.96 | T41: =(T40+4000)*1.00328-(0.00104*(T40+4000)) -> 981803.91 | U41: =(U40+4000)*1.00328-(0.00125*(U40+4000)) -> 1057190.2 | V41: =(V40+4000)*1.00328-(0.00125*(V40+4000)) -> 1131871 | W41: =(W40+4000)*1.00328-(0.00125*(W40+4000)) -> 1208391.4 | X41: =(X40+4000)*1.00328-(0.00125*(X40+4000)) -> 1286796.8 | Y41: =(Y40+4000)*1.00328-(0.00125*(Y40+4000)) -> 1367133.6 | Z41: =(Z40+4000)*1.00328-(0.00125*(Z40+4000)) -> 1449449.4 | AA41: =(AA40+4000)*1.00328-(0.00125*(AA40+4000)) -> 1533793 | AB41: =(AB40+4000)*1.00328-(0.00125*(AB40+4000)) -> 1620214.3 | ... AE41: =(AE40+4000)*1.00328-(0.00125*(AE40+4000)) -> 1892462.6 | AI41: =(AI40+4000)*1.00328-0 -> 20197.663 | AJ41: =(AJ40+4000)*1.00328-0 -> 70042.911 | AK41: =(AK40+4000)*1.00328-0 -> 121885.85 | AL41: =(AL40+4000)*1.00328-0 -> 175806.55 | AM41: =(AM40+4000)*1.00328-0 -> 231888.27 | AN41: =(AN40+4000)*1.00328-0 -> 290217.63 | AO41: =(AO40+4000)*1.00328-0 -> 350884.7 | AP41: =(AP40+4000)*1.00328-0 -> 413983.18 | ... BJ41: =(BJ40+4000)*1.00328-0 -> 2369819
A42: =0.01/12 -> 0.00083333333 | B42: 1 | D42: =(D41+4000)*1.00328-(0.00146*(D41+4000)) -> 24153.345 | E42: =(E41+4000)*1.00328-(0.00146*(E41+4000)) -> 73257.813 | F42: =(F41+4000)*1.00328-(0.00146*(F41+4000)) -> 123445.52 | G42: =(G41+4000)*1.00328-(0.00146*(G41+4000)) -> 174740.37 | H42: =(H41+4000)*1.00328-(0.00146*(H41+4000)) -> 227166.78 | I42: =(I41+4000)*1.00328-(0.00125*(I41+4000)) -> 281144.22 | J42: =(J41+4000)*1.00328-(0.00125*(J41+4000)) -> 336707.98 | K42: =(K41+4000)*1.00328-(0.00125*(K41+4000)) -> 393640.48 | L42: =(L41+4000)*1.00328-(0.00125*(L41+4000)) -> 451975.45 | M42: =(M41+4000)*1.00328-(0.00104*(M41+4000)) -> 512066.73 | N42: =(N41+4000)*1.00328-(0.00104*(N41+4000)) -> 574706.58 | O42: =(O41+4000)*1.00328-(0.00104*(O41+4000)) -> 639051.1 | P42: =(P41+4000)*1.00328-(0.00104*(P41+4000)) -> 705146.66 | Q42: =(Q41+4000)*1.00328-(0.00104*(Q41+4000)) -> 773040.92 | R42: =(R41+4000)*1.00328-(0.00104*(R41+4000)) -> 842782.84 | S42: =(S41+4000)*1.00328-(0.00104*(S41+4000)) -> 914422.69 | T42: =(T41+4000)*1.00328-(0.00104*(T41+4000)) -> 988012.12 | U42: =(U41+4000)*1.00328-(0.00125*(U41+4000)) -> 1063344.4 | V42: =(V41+4000)*1.00328-(0.00125*(V41+4000)) -> 1138176.8 | W42: =(W41+4000)*1.00328-(0.00125*(W41+4000)) -> 1214852.5 | X42: =(X41+4000)*1.00328-(0.00125*(X41+4000)) -> 1293417.1 | Y42: =(Y41+4000)*1.00328-(0.00125*(Y41+4000)) -> 1373917 | Z42: =(Z41+4000)*1.00328-(0.00125*(Z41+4000)) -> 1456399.9 | AA42: =(AA41+4000)*1.00328-(0.00125*(AA41+4000)) -> 1540914.8 | AB42: =(AB41+4000)*1.00328-(0.00125*(AB41+4000)) -> 1627511.5 | ... AE42: =(AE41+4000)*1.00328-(0.00125*(AE41+4000)) -> 1900312.4 | AI42: =(AI41+4000)*1.00328-0 -> 24277.031 | AJ42: =(AJ41+4000)*1.00328-0 -> 74285.772 | AK42: =(AK41+4000)*1.00328-0 -> 126298.76 | AL42: =(AL41+4000)*1.00328-0 -> 180396.31 | AM42: =(AM41+4000)*1.00328-0 -> 236661.98 | AN42: =(AN41+4000)*1.00328-0 -> 295182.66 | AO42: =(AO41+4000)*1.00328-0 -> 356048.72 | AP42: =(AP41+4000)*1.00328-0 -> 419354.17 | ... BJ42: =(BJ41+4000)*1.00328-0 -> 2381605.1
D43: =(D42+4000)*1.00328-(0.00146*(D42+4000)) -> 28204.584 | E43: =(E42+4000)*1.00328-(0.00146*(E42+4000)) -> 77398.422 | F43: =(F42+4000)*1.00328-(0.00146*(F42+4000)) -> 127677.47 | G43: =(G42+4000)*1.00328-(0.00146*(G42+4000)) -> 179065.68 | H43: =(H42+4000)*1.00328-(0.00146*(H42+4000)) -> 231587.51 | I43: =(I42+4000)*1.00328-(0.00125*(I42+4000)) -> 285723.06 | J43: =(J42+4000)*1.00328-(0.00125*(J42+4000)) -> 341399.61 | K43: =(K42+4000)*1.00328-(0.00125*(K42+4000)) -> 398447.69 | L43: =(L42+4000)*1.00328-(0.00125*(L42+4000)) -> 456901.08 | M43: =(M42+4000)*1.00328-(0.00104*(M42+4000)) -> 517222.72 | N43: =(N42+4000)*1.00328-(0.00104*(N42+4000)) -> 580002.89 | O43: =(O42+4000)*1.00328-(0.00104*(O42+4000)) -> 644491.53 | P43: =(P42+4000)*1.00328-(0.00104*(P42+4000)) -> 710735.15 | Q43: =(Q42+4000)*1.00328-(0.00104*(Q42+4000)) -> 778781.5 | R43: =(R42+4000)*1.00328-(0.00104*(R42+4000)) -> 848679.63 | S43: =(S42+4000)*1.00328-(0.00104*(S42+4000)) -> 920479.95 | T43: =(T42+4000)*1.00328-(0.00104*(T42+4000)) -> 994234.22 | U43: =(U42+4000)*1.00328-(0.00125*(U42+4000)) -> 1069511.2 | V43: =(V42+4000)*1.00328-(0.00125*(V42+4000)) -> 1144495.4 | W43: =(W42+4000)*1.00328-(0.00125*(W42+4000)) -> 1221326.8 | X43: =(X42+4000)*1.00328-(0.00125*(X42+4000)) -> 1300050.9 | Y43: =(Y42+4000)*1.00328-(0.00125*(Y42+4000)) -> 1380714.2 | Z43: =(Z42+4000)*1.00328-(0.00125*(Z42+4000)) -> 1463364.6 | AA43: =(AA42+4000)*1.00328-(0.00125*(AA42+4000)) -> 1548050.9 | AB43: =(AB42+4000)*1.00328-(0.00125*(AB42+4000)) -> 1634823.4 | ... AE43: =(AE42+4000)*1.00328-(0.00125*(AE42+4000)) -> 1908178.2 | AI43: =(AI42+4000)*1.00328-0 -> 28369.78 | AJ43: =(AJ42+4000)*1.00328-0 -> 78542.549 | AK43: =(AK42+4000)*1.00328-0 -> 130726.14 | AL43: =(AL42+4000)*1.00328-0 -> 185001.13 | AM43: =(AM42+4000)*1.00328-0 -> 241451.35 | AN43: =(AN42+4000)*1.00328-0 -> 300163.98 | AO43: =(AO42+4000)*1.00328-0 -> 361229.68 | AP43: =(AP42+4000)*1.00328-0 -> 424742.77 | ... BJ43: =(BJ42+4000)*1.00328-0 -> 2393429.9
D44: =(D43+4000)*1.00328-(0.00146*(D43+4000)) -> 32263.196 | E44: =(E43+4000)*1.00328-(0.00146*(E43+4000)) -> 81546.567 | F44: =(F43+4000)*1.00328-(0.00146*(F43+4000)) -> 131917.13 | G44: =(G43+4000)*1.00328-(0.00146*(G43+4000)) -> 183398.86 | H44: =(H43+4000)*1.00328-(0.00146*(H43+4000)) -> 236016.28 | I44: =(I43+4000)*1.00328-(0.00125*(I43+4000)) -> 290311.2 | J44: =(J43+4000)*1.00328-(0.00125*(J43+4000)) -> 346100.77 | K44: =(K43+4000)*1.00328-(0.00125*(K43+4000)) -> 403264.66 | L44: =(L43+4000)*1.00328-(0.00125*(L43+4000)) -> 461836.71 | M44: =(M43+4000)*1.00328-(0.00104*(M43+4000)) -> 522390.26 | N44: =(N43+4000)*1.00328-(0.00104*(N43+4000)) -> 585311.05 | O44: =(O43+4000)*1.00328-(0.00104*(O43+4000)) -> 649944.15 | P44: =(P43+4000)*1.00328-(0.00104*(P43+4000)) -> 716336.16 | Q44: =(Q43+4000)*1.00328-(0.00104*(Q43+4000)) -> 784534.93 | R44: =(R43+4000)*1.00328-(0.00104*(R43+4000)) -> 854589.64 | S44: =(S43+4000)*1.00328-(0.00104*(S43+4000)) -> 926550.79 | T44: =(T43+4000)*1.00328-(0.000833*(T43+4000)) -> 1000676.9 | U44: =(U43+4000)*1.00328-(0.00125*(U43+4000)) -> 1075690.4 | V44: =(V43+4000)*1.00328-(0.00125*(V43+4000)) -> 1150826.8 | W44: =(W43+4000)*1.00328-(0.00125*(W43+4000)) -> 1227814.2 | X44: =(X43+4000)*1.00328-(0.00125*(X43+4000)) -> 1306698.1 | Y44: =(Y43+4000)*1.00328-(0.00125*(Y43+4000)) -> 1387525.2 | Z44: =(Z43+4000)*1.00328-(0.00125*(Z43+4000)) -> 1470343.3 | AA44: =(AA43+4000)*1.00328-(0.00125*(AA43+4000)) -> 1555201.6 | AB44: =(AB43+4000)*1.00328-(0.00125*(AB43+4000)) -> 1642150.3 | ... AE44: =(AE43+4000)*1.00328-(0.00125*(AE43+4000)) -> 1916059.9 | AI44: =(AI43+4000)*1.00328-0 -> 32475.953 | AJ44: =(AJ43+4000)*1.00328-0 -> 82813.289 | AK44: =(AK43+4000)*1.00328-0 -> 135168.04 | AL44: =(AL43+4000)*1.00328-0 -> 189621.06 | AM44: =(AM43+4000)*1.00328-0 -> 246256.43 | AN44: =(AN43+4000)*1.00328-0 -> 305161.64 | AO44: =(AO43+4000)*1.00328-0 -> 366427.64 | AP44: =(AP43+4000)*1.00328-0 -> 430149.05 | ... BJ44: =(BJ43+4000)*1.00328-0 -> 2405293.5
D45: =(D44+4000)*1.00328-(0.00146*(D44+4000)) -> 36329.195 | E45: =(E44+4000)*1.00328-(0.00146*(E44+4000)) -> 85702.262 | F45: =(F44+4000)*1.00328-(0.00146*(F44+4000)) -> 136164.5 | G45: =(G44+4000)*1.00328-(0.00146*(G44+4000)) -> 187739.92 | H45: =(H44+4000)*1.00328-(0.00146*(H44+4000)) -> 240453.1 | I45: =(I44+4000)*1.00328-(0.00125*(I44+4000)) -> 294908.65 | J45: =(J44+4000)*1.00328-(0.00125*(J44+4000)) -> 350811.48 | K45: =(K44+4000)*1.00328-(0.00125*(K44+4000)) -> 408091.41 | L45: =(L44+4000)*1.00328-(0.00125*(L44+4000)) -> 466782.36 | M45: =(M44+4000)*1.00328-(0.00104*(M44+4000)) -> 527569.37 | N45: =(N44+4000)*1.00328-(0.00104*(N44+4000)) -> 590631.11 | O45: =(O44+4000)*1.00328-(0.00104*(O44+4000)) -> 655408.99 | P45: =(P44+4000)*1.00328-(0.00104*(P44+4000)) -> 721949.71 | Q45: =(Q44+4000)*1.00328-(0.00104*(Q44+4000)) -> 790301.25 | R45: =(R44+4000)*1.00328-(0.00104*(R44+4000)) -> 860512.88 | S45: =(S44+4000)*1.00328-(0.00104*(S44+4000)) -> 932635.22 | T45: =(T44+4000)*1.00328-(0.000833*(T44+4000)) -> 1007135.3 | U45: =(U44+4000)*1.00328-(0.00125*(U44+4000)) -> 1081882.2 | V45: =(V44+4000)*1.00328-(0.00125*(V44+4000)) -> 1157171.1 | W45: =(W44+4000)*1.00328-(0.00125*(W44+4000)) -> 1234314.8 | X45: =(X44+4000)*1.00328-(0.00125*(X44+4000)) -> 1313358.8 | Y45: =(Y44+4000)*1.00328-(0.00125*(Y44+4000)) -> 1394350 | Z45: =(Z44+4000)*1.00328-(0.00125*(Z44+4000)) -> 1477336.2 | AA45: =(AA44+4000)*1.00328-(0.00125*(AA44+4000)) -> 1562366.8 | AB45: =(AB44+4000)*1.00328-(0.00125*(AB44+4000)) -> 1649491.9 | ... AE45: =(AE44+4000)*1.00328-(0.00125*(AE44+4000)) -> 1923957.6 | AI45: =(AI44+4000)*1.00328-0 -> 36595.594 | AJ45: =(AJ44+4000)*1.00328-0 -> 87098.037 | AK45: =(AK44+4000)*1.00328-0 -> 139624.51 | AL45: =(AL44+4000)*1.00328-0 -> 194256.13 | AM45: =(AM44+4000)*1.00328-0 -> 251077.27 | AN45: =(AN44+4000)*1.00328-0 -> 310175.69 | AO45: =(AO44+4000)*1.00328-0 -> 371642.64 | AP45: =(AP44+4000)*1.00328-0 -> 435573.06 | ... BJ45: =(BJ44+4000)*1.00328-0 -> 2417195.9
D46: =(D45+4000)*1.00328-(0.00146*(D45+4000)) -> 40402.594 | E46: =(E45+4000)*1.00328-(0.00146*(E45+4000)) -> 89865.52 | F46: =(F45+4000)*1.00328-(0.00146*(F45+4000)) -> 140419.6 | G46: =(G45+4000)*1.00328-(0.00146*(G45+4000)) -> 192088.89 | H46: =(H45+4000)*1.00328-(0.00146*(H45+4000)) -> 244898.01 | I46: =(I45+4000)*1.00328-(0.00125*(I45+4000)) -> 299515.44 | J46: =(J45+4000)*1.00328-(0.00125*(J45+4000)) -> 355531.75 | K46: =(K45+4000)*1.00328-(0.00125*(K45+4000)) -> 412927.95 | L46: =(L45+4000)*1.00328-(0.00125*(L45+4000)) -> 471738.05 | M46: =(M45+4000)*1.00328-(0.00104*(M45+4000)) -> 532760.09 | N46: =(N45+4000)*1.00328-(0.00104*(N45+4000)) -> 595963.08 | O46: =(O45+4000)*1.00328-(0.00104*(O45+4000)) -> 660886.06 | P46: =(P45+4000)*1.00328-(0.00104*(P45+4000)) -> 727575.84 | Q46: =(Q45+4000)*1.00328-(0.00104*(Q45+4000)) -> 796080.48 | R46: =(R45+4000)*1.00328-(0.00104*(R45+4000)) -> 866449.39 | S46: =(S45+4000)*1.00328-(0.00104*(S45+4000)) -> 938733.29 | T46: =(T45+4000)*1.00328-(0.000833*(T45+4000)) -> 1013609.6 | U46: =(U45+4000)*1.00328-(0.00125*(U45+4000)) -> 1088086.5 | V46: =(V45+4000)*1.00328-(0.00125*(V45+4000)) -> 1163528.3 | W46: =(W45+4000)*1.00328-(0.00125*(W45+4000)) -> 1240828.6 | X46: =(X45+4000)*1.00328-(0.00125*(X45+4000)) -> 1320033 | Y46: =(Y45+4000)*1.00328-(0.00125*(Y45+4000)) -> 1401188.6 | Z46: =(Z45+4000)*1.00328-(0.00125*(Z45+4000)) -> 1484343.3 | AA46: =(AA45+4000)*1.00328-(0.00125*(AA45+4000)) -> 1569546.5 | AB46: =(AB45+4000)*1.00328-(0.00125*(AB45+4000)) -> 1656848.5 | ... AE46: =(AE45+4000)*1.00328-(0.00125*(AE45+4000)) -> 1931871.4 | AI46: =(AI45+4000)*1.00328-0 -> 40728.747 | AJ46: =(AJ45+4000)*1.00328-0 -> 91396.838 | AK46: =(AK45+4000)*1.00328-0 -> 144095.6 | AL46: =(AL45+4000)*1.00328-0 -> 198906.41 | AM46: =(AM45+4000)*1.00328-0 -> 255913.93 | AN46: =(AN45+4000)*1.00328-0 -> 315206.18 | AO46: =(AO45+4000)*1.00328-0 -> 376874.75 | AP46: =(AP45+4000)*1.00328-0 -> 441014.86 | ... BJ46: =(BJ45+4000)*1.00328-0 -> 2429137.5
D47: =(D46+4000)*1.00328-(0.00146*(D46+4000)) -> 44483.407 | E47: =(E46+4000)*1.00328-(0.00146*(E46+4000)) -> 94036.355 | F47: =(F46+4000)*1.00328-(0.00146*(F46+4000)) -> 144682.44 | G47: =(G46+4000)*1.00328-(0.00146*(G46+4000)) -> 196445.77 | H47: =(H46+4000)*1.00328-(0.00146*(H46+4000)) -> 249351 | I47: =(I46+4000)*1.00328-(0.00125*(I46+4000)) -> 304131.57 | J47: =(J46+4000)*1.00328-(0.00125*(J46+4000)) -> 360261.6 | K47: =(K46+4000)*1.00328-(0.00125*(K46+4000)) -> 417774.32 | L47: =(L46+4000)*1.00328-(0.00125*(L46+4000)) -> 476703.8 | M47: =(M46+4000)*1.00328-(0.00104*(M46+4000)) -> 537962.43 | N47: =(N46+4000)*1.00328-(0.00104*(N46+4000)) -> 601307 | O47: =(O46+4000)*1.00328-(0.00104*(O46+4000)) -> 666375.41 | P47: =(P46+4000)*1.00328-(0.00104*(P46+4000)) -> 733214.57 | Q47: =(Q46+4000)*1.00328-(0.00104*(Q46+4000)) -> 801872.66 | R47: =(R46+4000)*1.00328-(0.00104*(R46+4000)) -> 872399.19 | S47: =(S46+4000)*1.00328-(0.00104*(S46+4000)) -> 944845.01 | T47: =(T46+4000)*1.00328-(0.000833*(T46+4000)) -> 1020099.7 | U47: =(U46+4000)*1.00328-(0.00125*(U46+4000)) -> 1094303.4 | V47: =(V46+4000)*1.00328-(0.00125*(V46+4000)) -> 1169898.4 | W47: =(W46+4000)*1.00328-(0.00125*(W46+4000)) -> 1247355.6 | X47: =(X46+4000)*1.00328-(0.00125*(X46+4000)) -> 1326720.8 | Y47: =(Y46+4000)*1.00328-(0.00125*(Y46+4000)) -> 1408041.1 | Z47: =(Z46+4000)*1.00328-(0.00125*(Z46+4000)) -> 1491364.7 | AA47: =(AA46+4000)*1.00328-(0.00125*(AA46+4000)) -> 1576740.8 | AB47: =(AB46+4000)*1.00328-(0.00125*(AB46+4000)) -> 1664220.1 | ... AE47: =(AE46+4000)*1.00328-(0.00125*(AE46+4000)) -> 1939801.2 | AI47: =(AI46+4000)*1.00328-0 -> 44875.458 | AJ47: =(AJ46+4000)*1.00328-0 -> 95709.74 | AK47: =(AK46+4000)*1.00328-0 -> 148581.35 | AL47: =(AL46+4000)*1.00328-0 -> 203571.95 | AM47: =(AM46+4000)*1.00328-0 -> 260766.45 | AN47: =(AN46+4000)*1.00328-0 -> 320253.18 | AO47: =(AO46+4000)*1.00328-0 -> 382124.02 | AP47: =(AP46+4000)*1.00328-0 -> 446474.5 | ... BJ47: =(BJ46+4000)*1.00328-0 -> 2441118.2
D48: =(D47+4000)*1.00328-(0.00146*(D47+4000)) -> 48571.647 | E48: =(E47+4000)*1.00328-(0.00146*(E47+4000)) -> 98214.781 | F48: =(F47+4000)*1.00328-(0.00146*(F47+4000)) -> 148953.04 | G48: =(G47+4000)*1.00328-(0.00146*(G47+4000)) -> 200810.58 | H48: =(H47+4000)*1.00328-(0.00125*(H47+4000)) -> 253865.31 | I48: =(I47+4000)*1.00328-(0.00125*(I47+4000)) -> 308757.08 | J48: =(J47+4000)*1.00328-(0.00125*(J47+4000)) -> 365001.05 | K48: =(K47+4000)*1.00328-(0.00125*(K47+4000)) -> 422630.52 | L48: =(L47+4000)*1.00328-(0.00125*(L47+4000)) -> 481679.62 | M48: =(M47+4000)*1.00328-(0.00104*(M47+4000)) -> 543176.42 | N48: =(N47+4000)*1.00328-(0.00104*(N47+4000)) -> 606662.89 | O48: =(O47+4000)*1.00328-(0.00104*(O47+4000)) -> 671877.05 | P48: =(P47+4000)*1.00328-(0.00104*(P47+4000)) -> 738865.93 | Q48: =(Q47+4000)*1.00328-(0.00104*(Q47+4000)) -> 807677.82 | R48: =(R47+4000)*1.00328-(0.00104*(R47+4000)) -> 878362.33 | S48: =(S47+4000)*1.00328-(0.00104*(S47+4000)) -> 950970.42 | T48: =(T47+4000)*1.00328-(0.000833*(T47+4000)) -> 1026605.7 | U48: =(U47+4000)*1.00328-(0.00125*(U47+4000)) -> 1100533 | V48: =(V47+4000)*1.00328-(0.00125*(V47+4000)) -> 1176281.4 | W48: =(W47+4000)*1.00328-(0.00125*(W47+4000)) -> 1253895.8 | X48: =(X47+4000)*1.00328-(0.00125*(X47+4000)) -> 1333422.2 | Y48: =(Y47+4000)*1.00328-(0.00125*(Y47+4000)) -> 1414907.6 | Z48: =(Z47+4000)*1.00328-(0.00125*(Z47+4000)) -> 1498400.3 | AA48: =(AA47+4000)*1.00328-(0.00125*(AA47+4000)) -> 1583949.7 | AB48: =(AB47+4000)*1.00328-(0.00125*(AB47+4000)) -> 1671606.5 | ... AE48: =(AE47+4000)*1.00328-(0.00125*(AE47+4000)) -> 1947747.1 | AI48: =(AI47+4000)*1.00328-0 -> 49035.769 | AJ48: =(AJ47+4000)*1.00328-0 -> 100036.79 | AK48: =(AK47+4000)*1.00328-0 -> 153081.82 | AL48: =(AL47+4000)*1.00328-0 -> 208252.78 | AM48: =(AM47+4000)*1.00328-0 -> 265634.88 | AN48: =(AN47+4000)*1.00328-0 -> 325316.73 | AO48: =(AO47+4000)*1.00328-0 -> 387390.5 | AP48: =(AP47+4000)*1.00328-0 -> 451952.06 | ... BJ48: =(BJ47+4000)*1.00328-0 -> 2453138.1
D51: Scenario 3 | AI51: Scenario 3 | AJ51: WITHOUT AN ADVISOR
D52: Assume 5% annual return on investments | AI52: Assume 5% annual return on investments
D53: Assume 4K/mo invested | AI53: Assume 4K/mo invested
D54: Y1 | E54: Y2 | F54: Y3 | G54: Y4 | H54: Y5 | I54: Y6 | J54: Y7 | K54: Y8 | L54: Y9 | M54: Y10 | N54: Y11 | O54: Y12 | P54: Y13 | Q54: Y14 | R54: Y15 | S54: Y16 | T54: Y17 | U54: Y18 | V54: Y19 | W54: Y20 | X54: Y21 | Y54: Y22 | Z54: Y23 | AA54: Y24 | AB54: Y25 | AC54: Y26 | AD54: Y27 | AE54: Y28 | AI54: Y1 | AJ54: Y2 | AK54: Y3 | AL54: Y4 | AM54: Y5 | AN54: Y6 | AO54: Y7 | AP54: Y8 | AQ54: Y9 | AR54: Y10 | AS54: Y11 | AT54: Y12 | AU54: Y13 | AV54: Y14 | AW54: Y15 | AX54: Y16 | AY54: Y17 | AZ54: Y18 | BA54: Y19 | BB54: Y20 | BC54: Y21 | BD54: Y22 | BE54: Y23 | BF54: Y24 | BG54: Y25 | BH54: Y26 | BI54: Y27 | BJ54: Y28
D55: 0 | AI55: 0
D56: =(D55+4000)*1.00407-(0.00146*(D55+4000)) -> 4010.44 | E56: =(D67+4000)*1.00407-(0.00146*(D67+4000)) -> 52960.03 | F56: =(E67+4000)*1.00407-(0.00146*(E67+4000)) -> 103464.92 | G56: =(F67+4000)*1.00407-(0.00146*(F67+4000)) -> 155574.53 | H56: =(G67+4000)*1.00407-(0.00146*(G67+4000)) -> 209339.85 | I56: =(H67+4000)*1.00407-(0.00125*(H67+4000)) -> 265030.36 | J56: =(I67+4000)*1.00407-(0.00125*(I67+4000)) -> 323028.41 | K56: =(J67+4000)*1.00407-(0.00125*(J67+4000)) -> 383019.84 | L56: =(K67+4000)*1.00407-(0.00125*(K67+4000)) -> 445073.17 | M56: =(L67+4000)*1.00407-(0.00104*(L67+4000)) -> 509471.73 | N56: =(M67+4000)*1.00407-(0.00104*(M67+4000)) -> 577263.91 | O56: =(N67+4000)*1.00407-(0.00104*(N67+4000)) -> 647562.51 | P56: =(O67+4000)*1.00407-(0.00104*(O67+4000)) -> 720460.2 | Q56: =(P67+4000)*1.00407-(0.00104*(P67+4000)) -> 796053.07 | R56: =(Q67+4000)*1.00407-(0.00104*(Q67+4000)) -> 874440.77 | S56: =(R67+4000)*1.00407-(0.00104*(R67+4000)) -> 955726.63 | T56: =(S67+4000)*1.00407-(0.000833*(S67+4000)) -> 1041293.8 | U56: =(T67+4000)*1.00407-(0.00125*(T67+4000)) -> 1131021.5 | V56: =(U67+4000)*1.00407-(0.00125*(U67+4000)) -> 1218783.5 | W56: =(V67+4000)*1.00407-(0.00125*(V67+4000)) -> 1309561.8 | X56: =(W67+4000)*1.00407-(0.00125*(W67+4000)) -> 1403460.2 | Y56: =(X67+4000)*1.00407-(0.00125*(X67+4000)) -> 1500585.9 | Z56: =(Y67+4000)*1.00407-(0.00125*(Y67+4000)) -> 1601049.8 | AA56: =(Z67+4000)*1.00407-(0.00125*(Z67+4000)) -> 1704966.6 | AB56: =(AA67+4000)*1.00407-(0.00125*(AA67+4000)) -> 1812455 | ... AE56: =(AD67+4000)*1.00407-(0.00125*(AD67+4000)) -> 2157598.6 | AI56: =(AI55+4000)*1.00407-0 -> 4016.28 | AJ56: =(AI67+4000)*1.00407-0 -> 53505.871 | AK56: =(AJ67+4000)*1.00407-0 -> 105467.38 | AL56: =(AK67+4000)*1.00407-0 -> 160024.28 | AM56: =(AL67+4000)*1.00407-0 -> 217306.19 | AN56: =(AM67+4000)*1.00407-0 -> 277449.24 | AO56: =(AN67+4000)*1.00407-0 -> 340596.33 | AP56: =(AO67+4000)*1.00407-0 -> 406897.51 | AQ56: =(AP67+4000)*1.00407-0 -> 476510.31 | ... BJ56: =(BI67+4000)*1.00407-0 -> 2707452.8
D57: =(D56+4000)*1.00407-(0.00146*(D56+4000)) -> 8031.3472 | E57: =(E56+4000)*1.00407-(0.00146*(E56+4000)) -> 57108.696 | F57: =(F56+4000)*1.00407-(0.00146*(F56+4000)) -> 107745.4 | G57: =(G56+4000)*1.00407-(0.00146*(G56+4000)) -> 159991.02 | H57: =(H56+4000)*1.00407-(0.00146*(H56+4000)) -> 213896.67 | I57: =(I56+4000)*1.00407-(0.00125*(I56+4000)) -> 269789.03 | J57: =(J56+4000)*1.00407-(0.00125*(J56+4000)) -> 327950.63 | K57: =(K56+4000)*1.00407-(0.00125*(K56+4000)) -> 388111.24 | L57: =(L56+4000)*1.00407-(0.00125*(L56+4000)) -> 450339.55 | M57: =(M56+4000)*1.00407-(0.00104*(M56+4000)) -> 515027.55 | N57: =(N56+4000)*1.00407-(0.00104*(N56+4000)) -> 583025.14 | O57: =(O56+4000)*1.00407-(0.00104*(O56+4000)) -> 653536.75 | P57: =(P56+4000)*1.00407-(0.00104*(P56+4000)) -> 726655.32 | Q57: =(Q56+4000)*1.00407-(0.00104*(Q56+4000)) -> 802477.23 | R57: =(R56+4000)*1.00407-(0.00104*(R56+4000)) -> 881102.45 | S57: =(S56+4000)*1.00407-(0.00104*(S56+4000)) -> 962634.6 | T57: =(T56+4000)*1.00407-(0.000833*(T56+4000)) -> 1048677.4 | U57: =(U56+4000)*1.00407-(0.00125*(U56+4000)) -> 1138222.2 | V57: =(V56+4000)*1.00407-(0.00125*(V56+4000)) -> 1226231.7 | W57: =(W56+4000)*1.00407-(0.00125*(W56+4000)) -> 1317266.1 | X57: =(X56+4000)*1.00407-(0.00125*(X56+4000)) -> 1411429.3 | Y57: =(Y56+4000)*1.00407-(0.00125*(Y56+4000)) -> 1508828.9 | Z57: =(Z56+4000)*1.00407-(0.00125*(Z56+4000)) -> 1609576 | AA57: =(AA56+4000)*1.00407-(0.00125*(AA56+4000)) -> 1713785.9 | AB57: =(AB56+4000)*1.00407-(0.00125*(AB56+4000)) -> 1821577.4 | ... AE57: =(AE56+4000)*1.00407-(0.00125*(AE56+4000)) -> 2167694.3 | AI57: =(AI56+4000)*1.00407-0 -> 8048.9063 | AJ57: =(AJ56+4000)*1.00407-0 -> 57739.92 | AK57: =(AK56+4000)*1.00407-0 -> 109912.91 | AL57: =(AL56+4000)*1.00407-0 -> 164691.85 | AM57: =(AM56+4000)*1.00407-0 -> 222206.91 | AN57: =(AN56+4000)*1.00407-0 -> 282594.74 | AO57: =(AO56+4000)*1.00407-0 -> 345998.84 | AP57: =(AP56+4000)*1.00407-0 -> 412569.86 | ... BJ57: =(BJ56+4000)*1.00407-0 -> 2722488.4
A58: =0.0175/12 -> 0.0014583333 | B58: 1.75 | D58: =(D57+4000)*1.00407-(0.00146*(D57+4000)) -> 12062.749 | E58: =(E57+4000)*1.00407-(0.00146*(E57+4000)) -> 61268.189 | F58: =(F57+4000)*1.00407-(0.00146*(F57+4000)) -> 112037.06 | G58: =(G57+4000)*1.00407-(0.00146*(G57+4000)) -> 164419.04 | H58: =(H57+4000)*1.00407-(0.00146*(H57+4000)) -> 218465.38 | I58: =(I57+4000)*1.00407-(0.00125*(I57+4000)) -> 274561.11 | J58: =(J57+4000)*1.00407-(0.00125*(J57+4000)) -> 332886.73 | K58: =(K57+4000)*1.00407-(0.00125*(K57+4000)) -> 393216.99 | L58: =(L57+4000)*1.00407-(0.00125*(L57+4000)) -> 455620.79 | M58: =(M57+4000)*1.00407-(0.00104*(M57+4000)) -> 520600.2 | N58: =(N57+4000)*1.00407-(0.00104*(N57+4000)) -> 588803.83 | O58: =(O57+4000)*1.00407-(0.00104*(O57+4000)) -> 659529.08 | P58: =(P57+4000)*1.00407-(0.00104*(P57+4000)) -> 732869.2 | Q58: =(Q57+4000)*1.00407-(0.00104*(Q57+4000)) -> 808920.86 | R58: =(R57+4000)*1.00407-(0.00104*(R57+4000)) -> 887784.31 | S58: =(S57+4000)*1.00407-(0.00104*(S57+4000)) -> 969563.5 | T58: =(T57+4000)*1.00407-(0.000833*(T57+4000)) -> 1056084.9 | U58: =(U57+4000)*1.00407-(0.00125*(U57+4000)) -> 1145443.3 | V58: =(V57+4000)*1.00407-(0.00125*(V57+4000)) -> 1233701 | W58: =(W57+4000)*1.00407-(0.00125*(W57+4000)) -> 1324992.1 | X58: =(X57+4000)*1.00407-(0.00125*(X57+4000)) -> 1419420.8 | Y58: =(Y57+4000)*1.00407-(0.00125*(Y57+4000)) -> 1517095 | Z58: =(Z57+4000)*1.00407-(0.00125*(Z57+4000)) -> 1618126.3 | AA58: =(AA57+4000)*1.00407-(0.00125*(AA57+4000)) -> 1722630.1 | AB58: =(AB57+4000)*1.00407-(0.00125*(AB57+4000)) -> 1830725.5 | ... AE58: =(AE57+4000)*1.00407-(0.00125*(AE57+4000)) -> 2177818.5 | AI58: =(AI57+4000)*1.00407-0 -> 12097.945 | AJ58: =(AJ57+4000)*1.00407-0 -> 61991.201 | AK58: =(AK57+4000)*1.00407-0 -> 114376.54 | AL58: =(AL57+4000)*1.00407-0 -> 169378.43 | AM58: =(AM57+4000)*1.00407-0 -> 227127.57 | AN58: =(AN57+4000)*1.00407-0 -> 287761.18 | AO58: =(AO57+4000)*1.00407-0 -> 351423.33 | AP58: =(AP57+4000)*1.00407-0 -> 418265.3 | ... BJ58: =(BJ57+4000)*1.00407-0 -> 2737585.2
A59: =0.015/12 -> 0.00125 | B59: 1.5 | D59: =(D58+4000)*1.00407-(0.00146*(D58+4000)) -> 16104.673 | E59: =(E58+4000)*1.00407-(0.00146*(E58+4000)) -> 65438.539 | F59: =(F58+4000)*1.00407-(0.00146*(F58+4000)) -> 116339.92 | G59: =(G58+4000)*1.00407-(0.00146*(G58+4000)) -> 168858.61 | H59: =(H58+4000)*1.00407-(0.00146*(H58+4000)) -> 223046.01 | I59: =(I58+4000)*1.00407-(0.00125*(I58+4000)) -> 279346.65 | J59: =(J58+4000)*1.00407-(0.00125*(J58+4000)) -> 337836.75 | K59: =(K58+4000)*1.00407-(0.00125*(K58+4000)) -> 398337.14 | L59: =(L58+4000)*1.00407-(0.00125*(L58+4000)) -> 460916.92 | M59: =(M58+4000)*1.00407-(0.00104*(M58+4000)) -> 526189.74 | N59: =(N58+4000)*1.00407-(0.00104*(N58+4000)) -> 594600.02 | O59: =(O58+4000)*1.00407-(0.00104*(O58+4000)) -> 665539.58 | P59: =(P58+4000)*1.00407-(0.00104*(P58+4000)) -> 739101.92 | Q59: =(Q58+4000)*1.00407-(0.00104*(Q58+4000)) -> 815384.01 | R59: =(R58+4000)*1.00407-(0.00104*(R58+4000)) -> 894486.41 | S59: =(S58+4000)*1.00407-(0.00104*(S58+4000)) -> 976513.4 | T59: =(T58+4000)*1.00407-(0.000833*(T58+4000)) -> 1063516.4 | U59: =(U58+4000)*1.00407-(0.00125*(U58+4000)) -> 1152684.7 | V59: =(V58+4000)*1.00407-(0.00125*(V58+4000)) -> 1241191.3 | W59: =(W58+4000)*1.00407-(0.00125*(W58+4000)) -> 1332739.8 | X59: =(X58+4000)*1.00407-(0.00125*(X58+4000)) -> 1427434.8 | Y59: =(Y58+4000)*1.00407-(0.00125*(Y58+4000)) -> 1525384.5 | Z59: =(Z58+4000)*1.00407-(0.00125*(Z58+4000)) -> 1626700.7 | AA59: =(AA58+4000)*1.00407-(0.00125*(AA58+4000)) -> 1731499.1 | AB59: =(AB58+4000)*1.00407-(0.00125*(AB58+4000)) -> 1839899.5 | ... AE59: =(AE58+4000)*1.00407-(0.00125*(AE58+4000)) -> 2187971.2 | AI59: =(AI58+4000)*1.00407-0 -> 16163.464 | AJ59: =(AJ58+4000)*1.00407-0 -> 66259.785 | AK59: =(AK58+4000)*1.00407-0 -> 118858.33 | AL59: =(AL58+4000)*1.00407-0 -> 174084.08 | AM59: =(AM58+4000)*1.00407-0 -> 232068.26 | AN59: =(AN58+4000)*1.00407-0 -> 292948.65 | AO59: =(AO58+4000)*1.00407-0 -> 356869.91 | AP59: =(AP58+4000)*1.00407-0 -> 423983.92 | ... BJ59: =(BJ58+4000)*1.00407-0 -> 2752743.5
A60: =0.0125/12 -> 0.0010416667 | B60: 1.25 | D60: =(D59+4000)*1.00407-(0.00146*(D59+4000)) -> 20157.146 | E60: =(E59+4000)*1.00407-(0.00146*(E59+4000)) -> 69619.774 | F60: =(F59+4000)*1.00407-(0.00146*(F59+4000)) -> 120654 | G60: =(G59+4000)*1.00407-(0.00146*(G59+4000)) -> 173309.77 | H60: =(H59+4000)*1.00407-(0.00146*(H59+4000)) -> 227638.6 | I60: =(I59+4000)*1.00407-(0.00125*(I59+4000)) -> 284145.69 | J60: =(J59+4000)*1.00407-(0.00125*(J59+4000)) -> 342800.73 | K60: =(K59+4000)*1.00407-(0.00125*(K59+4000)) -> 403471.73 | L60: =(L59+4000)*1.00407-(0.00125*(L59+4000)) -> 466227.99 | M60: =(M59+4000)*1.00407-(0.00104*(M59+4000)) -> 531796.21 | N60: =(N59+4000)*1.00407-(0.00104*(N59+4000)) -> 600413.78 | O60: =(O59+4000)*1.00407-(0.00104*(O59+4000)) -> 671568.28 | P60: =(P59+4000)*1.00407-(0.00104*(P59+4000)) -> 745353.51 | Q60: =(Q59+4000)*1.00407-(0.00104*(Q59+4000)) -> 821866.74 | R60: =(R59+4000)*1.00407-(0.00104*(R59+4000)) -> 901208.83 | S60: =(S59+4000)*1.00407-(0.00104*(S59+4000)) -> 983484.35 | T60: =(T59+4000)*1.00407-(0.000833*(T59+4000)) -> 1070972 | U60: =(U59+4000)*1.00407-(0.00125*(U59+4000)) -> 1159946.6 | V60: =(V59+4000)*1.00407-(0.00125*(V59+4000)) -> 1248702.7 | W60: =(W59+4000)*1.00407-(0.00125*(W59+4000)) -> 1340509.4 | X60: =(X59+4000)*1.00407-(0.00125*(X59+4000)) -> 1435471.5 | Y60: =(Y59+4000)*1.00407-(0.00125*(Y59+4000)) -> 1533697.4 | Z60: =(Z59+4000)*1.00407-(0.00125*(Z59+4000)) -> 1635299.3 | AA60: =(AA59+4000)*1.00407-(0.00125*(AA59+4000)) -> 1740393.3 | AB60: =(AB59+4000)*1.00407-(0.00125*(AB59+4000)) -> 1849099.3 | ... AE60: =(AE59+4000)*1.00407-(0.00125*(AE59+4000)) -> 2198152.6 | AI60: =(AI59+4000)*1.00407-0 -> 20245.529 | AJ60: =(AJ59+4000)*1.00407-0 -> 70545.743 | AK60: =(AK59+4000)*1.00407-0 -> 123358.36 | AL60: =(AL59+4000)*1.00407-0 -> 178808.88 | AM60: =(AM59+4000)*1.00407-0 -> 237029.06 | AN60: =(AN59+4000)*1.00407-0 -> 298157.23 | AO60: =(AO59+4000)*1.00407-0 -> 362338.65 | AP60: =(AP59+4000)*1.00407-0 -> 429725.81 | ... BJ60: =(BJ59+4000)*1.00407-0 -> 2767963.4
A61: =0.01/12 -> 0.00083333333 | B61: 1 | D61: =(D60+4000)*1.00407-(0.00146*(D60+4000)) -> 24220.196 | E61: =(E60+4000)*1.00407-(0.00146*(E60+4000)) -> 73811.922 | F61: =(F60+4000)*1.00407-(0.00146*(F60+4000)) -> 124979.35 | G61: =(G60+4000)*1.00407-(0.00146*(G60+4000)) -> 177772.55 | H61: =(H60+4000)*1.00407-(0.00146*(H60+4000)) -> 232243.18 | I61: =(I60+4000)*1.00407-(0.00125*(I60+4000)) -> 288958.26 | J61: =(J60+4000)*1.00407-(0.00125*(J60+4000)) -> 347778.71 | K61: =(K60+4000)*1.00407-(0.00125*(K60+4000)) -> 408620.8 | L61: =(L60+4000)*1.00407-(0.00125*(L60+4000)) -> 471554.03 | M61: =(M60+4000)*1.00407-(0.00104*(M60+4000)) -> 537419.68 | N61: =(N60+4000)*1.00407-(0.00104*(N60+4000)) -> 606245.15 | O61: =(O60+4000)*1.00407-(0.00104*(O60+4000)) -> 677615.25 | P61: =(P60+4000)*1.00407-(0.00104*(P60+4000)) -> 751624.06 | Q61: =(Q60+4000)*1.00407-(0.00104*(Q60+4000)) -> 828369.12 | R61: =(R60+4000)*1.00407-(0.00104*(R60+4000)) -> 907951.61 | S61: =(S60+4000)*1.00407-(0.00104*(S60+4000)) -> 990476.43 | T61: =(T60+4000)*1.00407-(0.000833*(T60+4000)) -> 1078451.6 | U61: =(U60+4000)*1.00407-(0.00125*(U60+4000)) -> 1167228.9 | V61: =(V60+4000)*1.00407-(0.00125*(V60+4000)) -> 1256235.3 | W61: =(W60+4000)*1.00407-(0.00125*(W60+4000)) -> 1348300.9 | X61: =(X60+4000)*1.00407-(0.00125*(X60+4000)) -> 1443530.8 | Y61: =(Y60+4000)*1.00407-(0.00125*(Y60+4000)) -> 1542033.7 | Z61: =(Z60+4000)*1.00407-(0.00125*(Z60+4000)) -> 1643922.1 | AA61: =(AA60+4000)*1.00407-(0.00125*(AA60+4000)) -> 1749312.4 | AB61: =(AB60+4000)*1.00407-(0.00125*(AB60+4000)) -> 1858325 | ... AE61: =(AE60+4000)*1.00407-(0.00125*(AE60+4000)) -> 2208362.7 | AI61: =(AI60+4000)*1.00407-0 -> 24344.209 | AJ61: =(AJ60+4000)*1.00407-0 -> 74849.144 | AK61: =(AK60+4000)*1.00407-0 -> 127876.71 | AL61: =(AL60+4000)*1.00407-0 -> 183552.91 | AM61: =(AM60+4000)*1.00407-0 -> 242010.05 | AN61: =(AN60+4000)*1.00407-0 -> 303387.01 | AO61: =(AO60+4000)*1.00407-0 -> 367829.65 | AP61: =(AP60+4000)*1.00407-0 -> 435491.08 | ... BJ61: =(BJ60+4000)*1.00407-0 -> 2783245.3
D62: =(D61+4000)*1.00407-(0.00146*(D61+4000)) -> 28293.851 | E62: =(E61+4000)*1.00407-(0.00146*(E61+4000)) -> 78015.011 | F62: =(F61+4000)*1.00407-(0.00146*(F61+4000)) -> 129315.99 | G62: =(G61+4000)*1.00407-(0.00146*(G61+4000)) -> 182246.98 | H62: =(H61+4000)*1.00407-(0.00146*(H61+4000)) -> 236859.77 | I62: =(I61+4000)*1.00407-(0.00125*(I61+4000)) -> 293784.41 | J62: =(J61+4000)*1.00407-(0.00125*(J61+4000)) -> 352770.73 | K62: =(K61+4000)*1.00407-(0.00125*(K61+4000)) -> 413784.4 | L62: =(L61+4000)*1.00407-(0.00125*(L61+4000)) -> 476895.09 | M62: =(M61+4000)*1.00407-(0.00104*(M61+4000)) -> 543060.18 | N62: =(N61+4000)*1.00407-(0.00104*(N61+4000)) -> 612094.2 | O62: =(O61+4000)*1.00407-(0.00104*(O61+4000)) -> 683680.55 | P62: =(P61+4000)*1.00407-(0.00104*(P61+4000)) -> 757913.6 | Q62: =(Q61+4000)*1.00407-(0.00104*(Q61+4000)) -> 834891.2 | R62: =(R61+4000)*1.00407-(0.00104*(R61+4000)) -> 914714.82 | S62: =(S61+4000)*1.00407-(0.00104*(S61+4000)) -> 997489.69 | T62: =(T61+4000)*1.00407-(0.000833*(T61+4000)) -> 1085955.5 | U62: =(U61+4000)*1.00407-(0.00125*(U61+4000)) -> 1174531.8 | V62: =(V61+4000)*1.00407-(0.00125*(V61+4000)) -> 1263789.2 | W62: =(W61+4000)*1.00407-(0.00125*(W61+4000)) -> 1356114.4 | X62: =(X61+4000)*1.00407-(0.00125*(X61+4000)) -> 1451612.8 | Y62: =(Y61+4000)*1.00407-(0.00125*(Y61+4000)) -> 1550393.5 | Z62: =(Z61+4000)*1.00407-(0.00125*(Z61+4000)) -> 1652569.3 | AA62: =(AA61+4000)*1.00407-(0.00125*(AA61+4000)) -> 1758256.8 | AB62: =(AB61+4000)*1.00407-(0.00125*(AB61+4000)) -> 1867576.8 | ... AE62: =(AE61+4000)*1.00407-(0.00125*(AE61+4000)) -> 2218601.5 | AI62: =(AI61+4000)*1.00407-0 -> 28459.569 | AJ62: =(AJ61+4000)*1.00407-0 -> 79170.06 | AK62: =(AK61+4000)*1.00407-0 -> 132413.45 | AL62: =(AL61+4000)*1.00407-0 -> 188316.26 | AM62: =(AM61+4000)*1.00407-0 -> 247011.31 | AN62: =(AN61+4000)*1.00407-0 -> 308638.08 | AO62: =(AO61+4000)*1.00407-0 -> 373342.99 | AP62: =(AP61+4000)*1.00407-0 -> 441279.81 | ... BJ62: =(BJ61+4000)*1.00407-0 -> 2798589.4
D63: =(D62+4000)*1.00407-(0.00146*(D62+4000)) -> 32378.138 | E63: =(E62+4000)*1.00407-(0.00146*(E62+4000)) -> 82229.07 | F63: =(F62+4000)*1.00407-(0.00146*(F62+4000)) -> 133663.94 | G63: =(G62+4000)*1.00407-(0.00146*(G62+4000)) -> 186733.08 | H63: =(H62+4000)*1.00407-(0.00146*(H62+4000)) -> 241488.42 | I63: =(I62+4000)*1.00407-(0.00125*(I62+4000)) -> 298624.16 | J63: =(J62+4000)*1.00407-(0.00125*(J62+4000)) -> 357776.82 | K63: =(K62+4000)*1.00407-(0.00125*(K62+4000)) -> 418962.55 | L63: =(L62+4000)*1.00407-(0.00125*(L62+4000)) -> 482251.22 | M63: =(M62+4000)*1.00407-(0.00104*(M62+4000)) -> 548717.77 | N63: =(N62+4000)*1.00407-(0.00104*(N62+4000)) -> 617960.96 | O63: =(O62+4000)*1.00407-(0.00104*(O62+4000)) -> 689764.22 | P63: =(P62+4000)*1.00407-(0.00104*(P62+4000)) -> 764222.19 | Q63: =(Q62+4000)*1.00407-(0.00104*(Q62+4000)) -> 841433.04 | R63: =(R62+4000)*1.00407-(0.00104*(R62+4000)) -> 921498.53 | S63: =(S62+4000)*1.00407-(0.000833*(S62+4000)) -> 1004731.5 | T63: =(T62+4000)*1.00407-(0.000833*(T62+4000)) -> 1093483.7 | U63: =(U62+4000)*1.00407-(0.00125*(U62+4000)) -> 1181855.2 | V63: =(V62+4000)*1.00407-(0.00125*(V62+4000)) -> 1271364.4 | W63: =(W62+4000)*1.00407-(0.00125*(W62+4000)) -> 1363949.9 | X63: =(X62+4000)*1.00407-(0.00125*(X62+4000)) -> 1459717.7 | Y63: =(Y62+4000)*1.00407-(0.00125*(Y62+4000)) -> 1558776.9 | Z63: =(Z62+4000)*1.00407-(0.00125*(Z62+4000)) -> 1661240.8 | AA63: =(AA62+4000)*1.00407-(0.00125*(AA62+4000)) -> 1767226.3 | AB63: =(AB62+4000)*1.00407-(0.00125*(AB62+4000)) -> 1876854.6 | ... AE63: =(AE62+4000)*1.00407-(0.00125*(AE62+4000)) -> 2228869.3 | AI63: =(AI62+4000)*1.00407-0 -> 32591.68 | AJ63: =(AJ62+4000)*1.00407-0 -> 83508.562 | AK63: =(AK62+4000)*1.00407-0 -> 136968.65 | AL63: =(AL62+4000)*1.00407-0 -> 193098.98 | AM63: =(AM62+4000)*1.00407-0 -> 252032.92 | AN63: =(AN62+4000)*1.00407-0 -> 313910.51 | AO63: =(AO62+4000)*1.00407-0 -> 378878.78 | AP63: =(AP62+4000)*1.00407-0 -> 447092.1 | ... BJ63: =(BJ62+4000)*1.00407-0 -> 2813996
D64: =(D63+4000)*1.00407-(0.00146*(D63+4000)) -> 36473.085 | E64: =(E63+4000)*1.00407-(0.00146*(E63+4000)) -> 86454.128 | F64: =(F63+4000)*1.00407-(0.00146*(F63+4000)) -> 138023.24 | G64: =(G63+4000)*1.00407-(0.00146*(G63+4000)) -> 191230.9 | H64: =(H63+4000)*1.00407-(0.00146*(H63+4000)) -> 246129.14 | I64: =(I63+4000)*1.00407-(0.00125*(I63+4000)) -> 303477.56 | J64: =(J63+4000)*1.00407-(0.00125*(J63+4000)) -> 362797.03 | K64: =(K63+4000)*1.00407-(0.00125*(K63+4000)) -> 424155.3 | L64: =(L63+4000)*1.00407-(0.00125*(L63+4000)) -> 487622.45 | M64: =(M63+4000)*1.00407-(0.00104*(M63+4000)) -> 554392.5 | N64: =(N63+4000)*1.00407-(0.00104*(N63+4000)) -> 623845.5 | O64: =(O63+4000)*1.00407-(0.00104*(O63+4000)) -> 695866.32 | P64: =(P63+4000)*1.00407-(0.00104*(P63+4000)) -> 770549.91 | Q64: =(Q63+4000)*1.00407-(0.00104*(Q63+4000)) -> 847994.7 | R64: =(R63+4000)*1.00407-(0.00104*(R63+4000)) -> 928302.79 | S64: =(S63+4000)*1.00407-(0.000833*(S63+4000)) -> 1011996.8 | T64: =(T63+4000)*1.00407-(0.000833*(T63+4000)) -> 1101036.3 | U64: =(U63+4000)*1.00407-(0.00125*(U63+4000)) -> 1189199.3 | V64: =(V63+4000)*1.00407-(0.00125*(V63+4000)) -> 1278960.9 | W64: =(W63+4000)*1.00407-(0.00125*(W63+4000)) -> 1371807.6 | X64: =(X63+4000)*1.00407-(0.00125*(X63+4000)) -> 1467845.3 | Y64: =(Y63+4000)*1.00407-(0.00125*(Y63+4000)) -> 1567183.9 | Z64: =(Z63+4000)*1.00407-(0.00125*(Z63+4000)) -> 1669936.8 | AA64: =(AA63+4000)*1.00407-(0.00125*(AA63+4000)) -> 1776221.2 | AB64: =(AB63+4000)*1.00407-(0.00125*(AB63+4000)) -> 1886158.6 | ... AE64: =(AE63+4000)*1.00407-(0.00125*(AE63+4000)) -> 2239166 | AI64: =(AI63+4000)*1.00407-0 -> 36740.608 | AJ64: =(AJ63+4000)*1.00407-0 -> 87864.722 | AK64: =(AK63+4000)*1.00407-0 -> 141542.4 | AL64: =(AL63+4000)*1.00407-0 -> 197901.18 | AM64: =(AM63+4000)*1.00407-0 -> 257074.98 | AN64: =(AN63+4000)*1.00407-0 -> 319204.41 | AO64: =(AO63+4000)*1.00407-0 -> 384437.09 | AP64: =(AP63+4000)*1.00407-0 -> 452928.04 | ... BJ64: =(BJ63+4000)*1.00407-0 -> 2829465.2
D65: =(D64+4000)*1.00407-(0.00146*(D64+4000)) -> 40578.72 | E65: =(E64+4000)*1.00407-(0.00146*(E64+4000)) -> 90690.213 | F65: =(F64+4000)*1.00407-(0.00146*(F64+4000)) -> 142393.93 | G65: =(G64+4000)*1.00407-(0.00146*(G64+4000)) -> 195740.45 | H65: =(H64+4000)*1.00407-(0.00125*(H64+4000)) -> 250834.5 | I65: =(I64+4000)*1.00407-(0.00125*(I64+4000)) -> 308344.64 | J65: =(J64+4000)*1.00407-(0.00125*(J64+4000)) -> 367831.4 | K65: =(K64+4000)*1.00407-(0.00125*(K64+4000)) -> 429362.7 | L65: =(L64+4000)*1.00407-(0.00125*(L64+4000)) -> 493008.82 | M65: =(M64+4000)*1.00407-(0.00104*(M64+4000)) -> 560084.43 | N65: =(N64+4000)*1.00407-(0.00104*(N64+4000)) -> 629747.87 | O65: =(O64+4000)*1.00407-(0.00104*(O64+4000)) -> 701986.92 | P65: =(P64+4000)*1.00407-(0.00104*(P64+4000)) -> 776896.79 | Q65: =(Q64+4000)*1.00407-(0.00104*(Q64+4000)) -> 854576.24 | R65: =(R64+4000)*1.00407-(0.00104*(R64+4000)) -> 935127.67 | S65: =(S64+4000)*1.00407-(0.000833*(S64+4000)) -> 1019285.6 | T65: =(T64+4000)*1.00407-(0.000833*(T64+4000)) -> 1108613.3 | U65: =(U64+4000)*1.00407-(0.00125*(U64+4000)) -> 1196564.1 | V65: =(V64+4000)*1.00407-(0.00125*(V64+4000)) -> 1286578.8 | W65: =(W64+4000)*1.00407-(0.00125*(W64+4000)) -> 1379687.3 | X65: =(X64+4000)*1.00407-(0.00125*(X64+4000)) -> 1475996 | Y65: =(Y64+4000)*1.00407-(0.00125*(Y64+4000)) -> 1575614.7 | Z65: =(Z64+4000)*1.00407-(0.00125*(Z64+4000)) -> 1678657.3 | AA65: =(AA64+4000)*1.00407-(0.00125*(AA64+4000)) -> 1785241.4 | AB65: =(AB64+4000)*1.00407-(0.00125*(AB64+4000)) -> 1895488.9 | ... AE65: =(AE64+4000)*1.00407-(0.00125*(AE64+4000)) -> 2249491.7 | AI65: =(AI64+4000)*1.00407-0 -> 40906.422 | AJ65: =(AJ64+4000)*1.00407-0 -> 92238.611 | AK65: =(AK64+4000)*1.00407-0 -> 146134.75 | AL65: =(AL64+4000)*1.00407-0 -> 202722.91 | AM65: =(AM64+4000)*1.00407-0 -> 262137.55 | AN65: =(AN64+4000)*1.00407-0 -> 324519.85 | AO65: =(AO64+4000)*1.00407-0 -> 390018.03 | AP65: =(AP64+4000)*1.00407-0 -> 458787.74 | ... BJ65: =(BJ64+4000)*1.00407-0 -> 2844997.4
D66: =(D65+4000)*1.00407-(0.00146*(D65+4000)) -> 44695.07 | E66: =(E65+4000)*1.00407-(0.00146*(E65+4000)) -> 94937.354 | F66: =(F65+4000)*1.00407-(0.00146*(F65+4000)) -> 146776.01 | G66: =(G65+4000)*1.00407-(0.00146*(G65+4000)) -> 200261.77 | H66: =(H65+4000)*1.00407-(0.00125*(H65+4000)) -> 255553.14 | I66: =(I65+4000)*1.00407-(0.00125*(I65+4000)) -> 313225.46 | J66: =(J65+4000)*1.00407-(0.00125*(J65+4000)) -> 372879.96 | K66: =(K65+4000)*1.00407-(0.00125*(K65+4000)) -> 434584.78 | L66: =(L65+4000)*1.00407-(0.00125*(L65+4000)) -> 498410.39 | M66: =(M65+4000)*1.00407-(0.00104*(M65+4000)) -> 565793.61 | N66: =(N65+4000)*1.00407-(0.00104*(N65+4000)) -> 635668.13 | O66: =(O65+4000)*1.00407-(0.00104*(O65+4000)) -> 708126.06 | P66: =(P65+4000)*1.00407-(0.00104*(P65+4000)) -> 783262.91 | Q66: =(Q65+4000)*1.00407-(0.00104*(Q65+4000)) -> 861177.73 | R66: =(R65+4000)*1.00407-(0.00104*(R65+4000)) -> 941973.22 | S66: =(S65+4000)*1.00407-(0.000833*(S65+4000)) -> 1026597.9 | T66: =(T65+4000)*1.00407-(0.000833*(T65+4000)) -> 1116214.8 | U66: =(U65+4000)*1.00407-(0.00125*(U65+4000)) -> 1203949.7 | V66: =(V65+4000)*1.00407-(0.00125*(V65+4000)) -> 1294218.3 | W66: =(W65+4000)*1.00407-(0.00125*(W65+4000)) -> 1387589.3 | X66: =(X65+4000)*1.00407-(0.00125*(X65+4000)) -> 1484169.5 | Y66: =(Y65+4000)*1.00407-(0.00125*(Y65+4000)) -> 1584069.2 | Z66: =(Z65+4000)*1.00407-(0.00125*(Z65+4000)) -> 1687402.4 | AA66: =(AA65+4000)*1.00407-(0.00125*(AA65+4000)) -> 1794287.1 | AB66: =(AB65+4000)*1.00407-(0.00125*(AB65+4000)) -> 1904845.4 | ... AE66: =(AE65+4000)*1.00407-(0.00125*(AE65+4000)) -> 2259846.5 | AI66: =(AI65+4000)*1.00407-0 -> 45089.191 | AJ66: =(AJ65+4000)*1.00407-0 -> 96630.302 | AK66: =(AK65+4000)*1.00407-0 -> 150745.8 | AL66: =(AL65+4000)*1.00407-0 -> 207564.28 | AM66: =(AM65+4000)*1.00407-0 -> 267220.73 | AN66: =(AN65+4000)*1.00407-0 -> 329856.93 | AO66: =(AO65+4000)*1.00407-0 -> 395621.69 | AP66: =(AP65+4000)*1.00407-0 -> 464671.28 | ... BJ66: =(BJ65+4000)*1.00407-0 -> 2860592.8
D67: =(D66+4000)*1.00407-(0.00146*(D66+4000)) -> 48822.164 | E67: =(E66+4000)*1.00407-(0.00146*(E66+4000)) -> 99195.581 | F67: =(F66+4000)*1.00407-(0.00146*(F66+4000)) -> 151169.54 | G67: =(G66+4000)*1.00407-(0.00146*(G66+4000)) -> 204794.89 | H67: =(H66+4000)*1.00407-(0.00125*(H66+4000)) -> 260285.08 | I67: =(I66+4000)*1.00407-(0.00125*(I66+4000)) -> 318120.03 | J67: =(J66+4000)*1.00407-(0.00125*(J66+4000)) -> 377942.76 | K67: =(K66+4000)*1.00407-(0.00125*(K66+4000)) -> 439821.59 | L67: =(L66+4000)*1.00407-(0.00104*(L66+4000)) -> 503932.69 | M67: =(M66+4000)*1.00407-(0.00104*(M66+4000)) -> 571520.08 | N67: =(N66+4000)*1.00407-(0.00104*(N66+4000)) -> 641606.32 | O67: =(O66+4000)*1.00407-(0.00104*(O66+4000)) -> 714283.8 | P67: =(P66+4000)*1.00407-(0.00104*(P66+4000)) -> 789648.32 | Q67: =(Q66+4000)*1.00407-(0.00104*(Q66+4000)) -> 867799.22 | R67: =(R66+4000)*1.00407-(0.00104*(R66+4000)) -> 948839.52 | S67: =(S66+4000)*1.00407-(0.000833*(S66+4000)) -> 1033934 | T67: =(T66+4000)*1.00407-(0.000833*(T66+4000)) -> 1123840.9 | U67: =(U66+4000)*1.00407-(0.00125*(U66+4000)) -> 1211356.2 | V67: =(V66+4000)*1.00407-(0.00125*(V66+4000)) -> 1301879.3 | W67: =(W66+4000)*1.00407-(0.00125*(W66+4000)) -> 1395513.6 | X67: =(X66+4000)*1.00407-(0.00125*(X66+4000)) -> 1492366.2 | Y67: =(Y66+4000)*1.00407-(0.00125*(Y66+4000)) -> 1592547.5 | Z67: =(Z66+4000)*1.00407-(0.00125*(Z66+4000)) -> 1696172.1 | AA67: =(AA66+4000)*1.00407-(0.00125*(AA66+4000)) -> 1803358.3 | AB67: =(AB66+4000)*1.00407-(0.00125*(AB66+4000)) -> 1914228.4 | ... AE67: =(AE66+4000)*1.00407-(0.00125*(AE66+4000)) -> 2270230.6 | AI67: =(AI66+4000)*1.00407-0 -> 49288.984 | AJ67: =(AJ66+4000)*1.00407-0 -> 101039.87 | AK67: =(AK66+4000)*1.00407-0 -> 155375.62 | AL67: =(AL66+4000)*1.00407-0 -> 212425.34 | AM67: =(AM66+4000)*1.00407-0 -> 272324.6 | AN67: =(AN66+4000)*1.00407-0 -> 335215.72 | AO67: =(AO66+4000)*1.00407-0 -> 401248.15 | AP67: =(AP66+4000)*1.00407-0 -> 470578.78 | ... BJ67: =(BJ66+4000)*1.00407-0 -> 2876251.7
D70: Scenario 4 | AI70: Scenario 4 | AJ70: WITHOUT AN ADVISOR
D71: Assume 6% annual return on investments | AI71: Assume 6% annual return on investments
D72: Assume 4K/mo invested | AI72: Assume 4K/mo invested
D73: Y1 | E73: Y2 | F73: Y3 | G73: Y4 | H73: Y5 | I73: Y6 | J73: Y7 | K73: Y8 | L73: Y9 | M73: Y10 | N73: Y11 | O73: Y12 | P73: Y13 | Q73: Y14 | R73: Y15 | S73: Y16 | T73: Y17 | U73: Y18 | V73: Y19 | W73: Y20 | X73: Y21 | Y73: Y22 | Z73: Y23 | AA73: Y24 | AB73: Y25 | AC73: Y26 | AD73: Y27 | AE73: Y28 | AI73: Y1 | AJ73: Y2 | AK73: Y3 | AL73: Y4 | AM73: Y5 | AN73: Y6 | AO73: Y7 | AP73: Y8 | AQ73: Y9 | AR73: Y10 | AS73: Y11 | AT73: Y12 | AU73: Y13 | AV73: Y14 | AW73: Y15 | AX73: Y16 | AY73: Y17 | AZ73: Y18 | BA73: Y19 | BB73: Y20 | BC73: Y21 | BD73: Y22 | BE73: Y23 | BF73: Y24 | BG73: Y25 | BH73: Y26 | BI73: Y27 | BJ73: Y28
D74: 0 | AI74: 0
D75: =(D74+4000)*1.00487-(0.00146*(D74+4000)) -> 4013.64 | E75: =(D86+4000)*1.00487-(0.00146*(D86+4000)) -> 53258.33 | F75: =(E86+4000)*1.00487-(0.00146*(E86+4000)) -> 104556.34 | G75: =(F86+4000)*1.00487-(0.00146*(F86+4000)) -> 157993.28 | H75: =(G86+4000)*1.00487-(0.00146*(G86+4000)) -> 213658.35 | I75: =(H86+4000)*1.00487-(0.00125*(H86+4000)) -> 271866.86 | J75: =(I86+4000)*1.00487-(0.00125*(I86+4000)) -> 333059.32 | K75: =(J86+4000)*1.00487-(0.00125*(J86+4000)) -> 396963.55 | L75: =(K86+4000)*1.00487-(0.00125*(K86+4000)) -> 463699.72 | M75: =(L86+4000)*1.00487-(0.00104*(L86+4000)) -> 534050.66 | N75: =(M86+4000)*1.00487-(0.00104*(M86+4000)) -> 608331.23 | O75: =(N86+4000)*1.00487-(0.00104*(N86+4000)) -> 686098.57 | P75: =(O86+4000)*1.00487-(0.00104*(O86+4000)) -> 767516.37 | Q75: =(P86+4000)*1.00487-(0.00104*(P86+4000)) -> 852755.96 | R75: =(Q86+4000)*1.00487-(0.00104*(Q86+4000)) -> 941996.75 | S75: =(R86+4000)*1.00487-(0.00104*(R86+4000)) -> 1035426.6 | T75: =(S86+4000)*1.00487-(0.000833*(S86+4000)) -> 1134632.4 | U75: =(T86+4000)*1.00487-(0.00125*(T86+4000)) -> 1239598.8 | V75: =(U86+4000)*1.00487-(0.00125*(U86+4000)) -> 1343676.7 | W75: =(V86+4000)*1.00487-(0.00125*(V86+4000)) -> 1452366.9 | X75: =(W86+4000)*1.00487-(0.00125*(W86+4000)) -> 1565873.7 | Y75: =(X86+4000)*1.00487-(0.00125*(X86+4000)) -> 1684410.6 | Z75: =(Y86+4000)*1.00487-(0.00125*(Y86+4000)) -> 1808200.5 | AA75: =(Z86+4000)*1.00487-(0.00125*(Z86+4000)) -> 1937476.3 | AB75: =(AA86+4000)*1.00487-(0.00125*(AA86+4000)) -> 2072480.9 | ... AE75: =(AD86+4000)*1.00487-(0.00125*(AD86+4000)) -> 2514463.7 | AI75: =(AI74+4000)*1.00487-0 -> 4019.48 | AJ75: =(AI86+4000)*1.00487-0 -> 53807.679 | AK75: =(AJ86+4000)*1.00487-0 -> 106584.71 | AL75: =(AK86+4000)*1.00487-0 -> 162530.01 | AM75: =(AL86+4000)*1.00487-0 -> 221833.75 | AN75: =(AM86+4000)*1.00487-0 -> 284697.56 | AO75: =(AN86+4000)*1.00487-0 -> 351335.15 | AP75: =(AO86+4000)*1.00487-0 -> 421973.05 | AQ75: =(AP86+4000)*1.00487-0 -> 496851.43 | ... BJ75: =(BI86+4000)*1.00487-0 -> 3177336.5
D76: =(D75+4000)*1.00487-(0.00146*(D75+4000)) -> 8040.9665 | E76: =(E75+4000)*1.00487-(0.00146*(E75+4000)) -> 57453.581 | F76: =(F75+4000)*1.00487-(0.00146*(F75+4000)) -> 108926.52 | G76: =(G75+4000)*1.00487-(0.00146*(G75+4000)) -> 162545.68 | H76: =(H75+4000)*1.00487-(0.00146*(H75+4000)) -> 218400.56 | I76: =(I75+4000)*1.00487-(0.00125*(I75+4000)) -> 276865.49 | J76: =(J75+4000)*1.00487-(0.00125*(J75+4000)) -> 338279.47 | K76: =(K75+4000)*1.00487-(0.00125*(K75+4000)) -> 402415.03 | L76: =(L75+4000)*1.00487-(0.00125*(L75+4000)) -> 469392.79 | M76: =(M75+4000)*1.00487-(0.00104*(M75+4000)) -> 540111.39 | N76: =(N75+4000)*1.00487-(0.00104*(N75+4000)) -> 614676.46 | O76: =(O75+4000)*1.00487-(0.00104*(O75+4000)) -> 692741.65 | P76: =(P75+4000)*1.00487-(0.00104*(P75+4000)) -> 774471.27 | Q76: =(Q75+4000)*1.00487-(0.00104*(Q75+4000)) -> 860037.33 | R76: =(R75+4000)*1.00487-(0.00104*(R75+4000)) -> 949619.92 | S76: =(S75+4000)*1.00487-(0.00104*(S75+4000)) -> 1043407.6 | T76: =(T75+4000)*1.00487-(0.000833*(T75+4000)) -> 1143229 | U76: =(U75+4000)*1.00487-(0.00125*(U75+4000)) -> 1248100.7 | V76: =(V75+4000)*1.00487-(0.00125*(V75+4000)) -> 1352555.3 | W76: =(W75+4000)*1.00487-(0.00125*(W75+4000)) -> 1461638.9 | X76: =(X75+4000)*1.00487-(0.00125*(X75+4000)) -> 1575556.6 | Y76: =(Y75+4000)*1.00487-(0.00125*(Y75+4000)) -> 1694522.7 | Z76: =(Z75+4000)*1.00487-(0.00125*(Z75+4000)) -> 1818760.7 | AA76: =(AA75+4000)*1.00487-(0.00125*(AA75+4000)) -> 1948504.4 | AB76: =(AB75+4000)*1.00487-(0.00125*(AB75+4000)) -> 2083997.7 | ... AE76: =(AE75+4000)*1.00487-(0.00125*(AE75+4000)) -> 2527580.6 | AI76: =(AI75+4000)*1.00487-0 -> 8058.5349 | AJ76: =(AJ75+4000)*1.00487-0 -> 58089.202 | AK76: =(AK75+4000)*1.00487-0 -> 111123.26 | AL76: =(AL75+4000)*1.00487-0 -> 167341.01 | AM76: =(AM75+4000)*1.00487-0 -> 226933.56 | AN76: =(AN75+4000)*1.00487-0 -> 290103.52 | AO76: =(AO75+4000)*1.00487-0 -> 357065.63 | AP76: =(AP75+4000)*1.00487-0 -> 428047.54 | ... BJ76: =(BJ75+4000)*1.00487-0 -> 3196829.6
A77: =0.0175/12 -> 0.0014583333 | B77: 1.75 | D77: =(D76+4000)*1.00487-(0.00146*(D76+4000)) -> 12082.026 | E77: =(E76+4000)*1.00487-(0.00146*(E76+4000)) -> 61663.138 | F77: =(F76+4000)*1.00487-(0.00146*(F76+4000)) -> 113311.6 | G77: =(G76+4000)*1.00487-(0.00146*(G76+4000)) -> 167113.6 | H77: =(H76+4000)*1.00487-(0.00146*(H76+4000)) -> 223158.95 | I77: =(I76+4000)*1.00487-(0.00125*(I76+4000)) -> 281882.23 | J77: =(J76+4000)*1.00487-(0.00125*(J76+4000)) -> 343518.52 | K77: =(K76+4000)*1.00487-(0.00125*(K76+4000)) -> 407886.26 | L77: =(L76+4000)*1.00487-(0.00125*(L76+4000)) -> 475106.47 | M77: =(M76+4000)*1.00487-(0.00104*(M76+4000)) -> 546195.34 | N77: =(N76+4000)*1.00487-(0.00104*(N76+4000)) -> 621045.99 | O77: =(O76+4000)*1.00487-(0.00104*(O76+4000)) -> 699410.17 | P77: =(P76+4000)*1.00487-(0.00104*(P76+4000)) -> 781452.82 | Q77: =(Q76+4000)*1.00487-(0.00104*(Q76+4000)) -> 867346.6 | R77: =(R76+4000)*1.00487-(0.00104*(R76+4000)) -> 957272.28 | S77: =(S76+4000)*1.00487-(0.00104*(S76+4000)) -> 1051419.1 | T77: =(T76+4000)*1.00487-(0.000833*(T76+4000)) -> 1151860.4 | U77: =(U76+4000)*1.00487-(0.00125*(U76+4000)) -> 1256633.3 | V77: =(V76+4000)*1.00487-(0.00125*(V76+4000)) -> 1361466.1 | W77: =(W76+4000)*1.00487-(0.00125*(W76+4000)) -> 1470944.6 | X77: =(X76+4000)*1.00487-(0.00125*(X76+4000)) -> 1585274.6 | Y77: =(Y76+4000)*1.00487-(0.00125*(Y76+4000)) -> 1704671.3 | Z77: =(Z76+4000)*1.00487-(0.00125*(Z76+4000)) -> 1829359.1 | AA77: =(AA76+4000)*1.00487-(0.00125*(AA76+4000)) -> 1959572.5 | AB77: =(AB76+4000)*1.00487-(0.00125*(AB76+4000)) -> 2095556.3 | ... AE77: =(AE76+4000)*1.00487-(0.00125*(AE76+4000)) -> 2540744.9 | AI77: =(AI76+4000)*1.00487-0 -> 12117.26 | AJ77: =(AJ76+4000)*1.00487-0 -> 62391.577 | AK77: =(AK76+4000)*1.00487-0 -> 115683.91 | AL77: =(AL76+4000)*1.00487-0 -> 172175.44 | AM77: =(AM76+4000)*1.00487-0 -> 232058.21 | AN77: =(AN76+4000)*1.00487-0 -> 295535.8 | AO77: =(AO76+4000)*1.00487-0 -> 362824.02 | AP77: =(AP76+4000)*1.00487-0 -> 434151.61 | ... BJ77: =(BJ76+4000)*1.00487-0 -> 3216417.7
A78: =0.015/12 -> 0.00125 | B78: 1.5 | D78: =(D77+4000)*1.00487-(0.00146*(D77+4000)) -> 16136.866 | E78: =(E77+4000)*1.00487-(0.00146*(E77+4000)) -> 65887.049 | F78: =(F77+4000)*1.00487-(0.00146*(F77+4000)) -> 117711.63 | G78: =(G77+4000)*1.00487-(0.00146*(G77+4000)) -> 171697.1 | H78: =(H77+4000)*1.00487-(0.00146*(H77+4000)) -> 227933.56 | I78: =(I77+4000)*1.00487-(0.00125*(I77+4000)) -> 286917.12 | J78: =(J77+4000)*1.00487-(0.00125*(J77+4000)) -> 348776.54 | K78: =(K77+4000)*1.00487-(0.00125*(K77+4000)) -> 413377.28 | L78: =(L77+4000)*1.00487-(0.00125*(L77+4000)) -> 480840.84 | M78: =(M77+4000)*1.00487-(0.00104*(M77+4000)) -> 552302.59 | N78: =(N77+4000)*1.00487-(0.00104*(N77+4000)) -> 627439.91 | O78: =(O77+4000)*1.00487-(0.00104*(O77+4000)) -> 706104.23 | P78: =(P77+4000)*1.00487-(0.00104*(P77+4000)) -> 788461.1 | Q78: =(Q77+4000)*1.00487-(0.00104*(Q77+4000)) -> 874683.85 | R78: =(R77+4000)*1.00487-(0.00104*(R77+4000)) -> 964953.96 | S78: =(S77+4000)*1.00487-(0.00104*(S77+4000)) -> 1059461.4 | T78: =(T77+4000)*1.00487-(0.000833*(T77+4000)) -> 1160526.6 | U78: =(U77+4000)*1.00487-(0.00125*(U77+4000)) -> 1265196.8 | V78: =(V77+4000)*1.00487-(0.00125*(V77+4000)) -> 1370409.1 | W78: =(W77+4000)*1.00487-(0.00125*(W77+4000)) -> 1480283.9 | X78: =(X77+4000)*1.00487-(0.00125*(X77+4000)) -> 1595027.8 | Y78: =(Y77+4000)*1.00487-(0.00125*(Y77+4000)) -> 1714856.7 | Z78: =(Z77+4000)*1.00487-(0.00125*(Z77+4000)) -> 1839995.9 | AA78: =(AA77+4000)*1.00487-(0.00125*(AA77+4000)) -> 1970680.6 | AB78: =(AB77+4000)*1.00487-(0.00125*(AB77+4000)) -> 2107156.7 | ... AE78: =(AE77+4000)*1.00487-(0.00125*(AE77+4000)) -> 2553956.9 | AI78: =(AI77+4000)*1.00487-0 -> 16195.751 | AJ78: =(AJ77+4000)*1.00487-0 -> 66714.904 | AK78: =(AK77+4000)*1.00487-0 -> 120266.77 | AL78: =(AL77+4000)*1.00487-0 -> 177033.41 | AM78: =(AM77+4000)*1.00487-0 -> 237207.81 | AN78: =(AN77+4000)*1.00487-0 -> 300994.54 | AO78: =(AO77+4000)*1.00487-0 -> 368610.45 | AP78: =(AP77+4000)*1.00487-0 -> 440285.41 | ... BJ78: =(BJ77+4000)*1.00487-0 -> 3236101.1
A79: =0.0125/12 -> 0.0010416667 | B79: 1.25 | D79: =(D78+4000)*1.00487-(0.00146*(D78+4000)) -> 20205.533 | E79: =(E78+4000)*1.00487-(0.00146*(E78+4000)) -> 70125.364 | F79: =(F78+4000)*1.00487-(0.00146*(F78+4000)) -> 122126.67 | G79: =(G78+4000)*1.00487-(0.00146*(G78+4000)) -> 176296.23 | H79: =(H78+4000)*1.00487-(0.00146*(H78+4000)) -> 232724.45 | I79: =(I78+4000)*1.00487-(0.00125*(I78+4000)) -> 291970.24 | J79: =(J78+4000)*1.00487-(0.00125*(J78+4000)) -> 354053.59 | K79: =(K78+4000)*1.00487-(0.00125*(K78+4000)) -> 418888.19 | L79: =(L78+4000)*1.00487-(0.00125*(L78+4000)) -> 486595.96 | M79: =(M78+4000)*1.00487-(0.00104*(M78+4000)) -> 558433.23 | N79: =(N78+4000)*1.00487-(0.00104*(N78+4000)) -> 633858.33 | O79: =(O78+4000)*1.00487-(0.00104*(O78+4000)) -> 712823.93 | P79: =(P78+4000)*1.00487-(0.00104*(P78+4000)) -> 795496.23 | Q79: =(Q78+4000)*1.00487-(0.00104*(Q78+4000)) -> 882049.21 | R79: =(R78+4000)*1.00487-(0.00104*(R78+4000)) -> 972665.05 | S79: =(S78+4000)*1.00487-(0.00104*(S78+4000)) -> 1067534.4 | T79: =(T78+4000)*1.00487-(0.000833*(T78+4000)) -> 1169227.8 | U79: =(U78+4000)*1.00487-(0.00125*(U78+4000)) -> 1273791.3 | V79: =(V78+4000)*1.00487-(0.00125*(V78+4000)) -> 1379384.4 | W79: =(W78+4000)*1.00487-(0.00125*(W78+4000)) -> 1489657 | X79: =(X78+4000)*1.00487-(0.00125*(X78+4000)) -> 1604816.3 | Y79: =(Y78+4000)*1.00487-(0.00125*(Y78+4000)) -> 1725079 | Z79: =(Z78+4000)*1.00487-(0.00125*(Z78+4000)) -> 1850671.1 | AA79: =(AA78+4000)*1.00487-(0.00125*(AA78+4000)) -> 1981828.9 | AB79: =(AB78+4000)*1.00487-(0.00125*(AB78+4000)) -> 2118799.1 | ... AE79: =(AE78+4000)*1.00487-(0.00125*(AE78+4000)) -> 2567216.7 | AI79: =(AI78+4000)*1.00487-0 -> 20294.104 | AJ79: =(AJ78+4000)*1.00487-0 -> 71059.285 | AK79: =(AK78+4000)*1.00487-0 -> 124871.95 | AL79: =(AL78+4000)*1.00487-0 -> 181915.05 | AM79: =(AM78+4000)*1.00487-0 -> 242382.49 | AN79: =(AN78+4000)*1.00487-0 -> 306479.86 | AO79: =(AO78+4000)*1.00487-0 -> 374425.06 | AP79: =(AP78+4000)*1.00487-0 -> 446449.08 | ... BJ79: =(BJ78+4000)*1.00487-0 -> 3255880.4
A80: =0.01/12 -> 0.00083333333 | B80: 1 | D80: =(D79+4000)*1.00487-(0.00146*(D79+4000)) -> 24288.073 | E80: =(E79+4000)*1.00487-(0.00146*(E79+4000)) -> 74378.132 | F80: =(F79+4000)*1.00487-(0.00146*(F79+4000)) -> 126556.76 | G80: =(G79+4000)*1.00487-(0.00146*(G79+4000)) -> 180911.04 | H80: =(H79+4000)*1.00487-(0.00146*(H79+4000)) -> 237531.68 | I80: =(I79+4000)*1.00487-(0.00125*(I79+4000)) -> 297041.65 | J80: =(J79+4000)*1.00487-(0.00125*(J79+4000)) -> 359349.75 | K80: =(K79+4000)*1.00487-(0.00125*(K79+4000)) -> 424419.05 | L80: =(L79+4000)*1.00487-(0.00125*(L79+4000)) -> 492371.92 | M80: =(M79+4000)*1.00487-(0.00104*(M79+4000)) -> 564587.35 | N80: =(N79+4000)*1.00487-(0.00104*(N79+4000)) -> 640301.33 | O80: =(O79+4000)*1.00487-(0.00104*(O79+4000)) -> 719569.37 | P80: =(P79+4000)*1.00487-(0.00104*(P79+4000)) -> 802558.3 | Q80: =(Q79+4000)*1.00487-(0.00104*(Q79+4000)) -> 889442.78 | R80: =(R79+4000)*1.00487-(0.00104*(R79+4000)) -> 980405.68 | S80: =(S79+4000)*1.00487-(0.00104*(S79+4000)) -> 1075638.4 | T80: =(T79+4000)*1.00487-(0.000833*(T79+4000)) -> 1177964.1 | U80: =(U79+4000)*1.00487-(0.00125*(U79+4000)) -> 1282416.9 | V80: =(V79+4000)*1.00487-(0.00125*(V79+4000)) -> 1388392.3 | W80: =(W79+4000)*1.00487-(0.00125*(W79+4000)) -> 1499064 | X80: =(X79+4000)*1.00487-(0.00125*(X79+4000)) -> 1614640.2 | Y80: =(Y79+4000)*1.00487-(0.00125*(Y79+4000)) -> 1735338.2 | Z80: =(Z79+4000)*1.00487-(0.00125*(Z79+4000)) -> 1861385 | AA80: =(AA79+4000)*1.00487-(0.00125*(AA79+4000)) -> 1993017.6 | AB80: =(AB79+4000)*1.00487-(0.00125*(AB79+4000)) -> 2130483.6 | ... AE80: =(AE79+4000)*1.00487-(0.00125*(AE79+4000)) -> 2580524.5 | AI80: =(AI79+4000)*1.00487-0 -> 24412.417 | AJ80: =(AJ79+4000)*1.00487-0 -> 75424.824 | AK80: =(AK79+4000)*1.00487-0 -> 129499.56 | AL80: =(AL79+4000)*1.00487-0 -> 186820.45 | AM80: =(AM79+4000)*1.00487-0 -> 247582.38 | AN80: =(AN79+4000)*1.00487-0 -> 311991.9 | AO80: =(AO79+4000)*1.00487-0 -> 380267.99 | AP80: =(AP79+4000)*1.00487-0 -> 452642.77 | ... BJ80: =(BJ79+4000)*1.00487-0 -> 3275756
D81: =(D80+4000)*1.00487-(0.00146*(D80+4000)) -> 28384.536 | E81: =(E80+4000)*1.00487-(0.00146*(E80+4000)) -> 78645.401 | F81: =(F80+4000)*1.00487-(0.00146*(F80+4000)) -> 131001.96 | G81: =(G80+4000)*1.00487-(0.00146*(G80+4000)) -> 185541.58 | H81: =(H80+4000)*1.00487-(0.00146*(H80+4000)) -> 242355.31 | I81: =(I80+4000)*1.00487-(0.00125*(I80+4000)) -> 302131.42 | J81: =(J80+4000)*1.00487-(0.00125*(J80+4000)) -> 364665.07 | K81: =(K80+4000)*1.00487-(0.00125*(K80+4000)) -> 429969.92 | L81: =(L80+4000)*1.00487-(0.00125*(L80+4000)) -> 498168.78 | M81: =(M80+4000)*1.00487-(0.00104*(M80+4000)) -> 570765.04 | N81: =(N80+4000)*1.00487-(0.00104*(N80+4000)) -> 646769 | O81: =(O80+4000)*1.00487-(0.00104*(O80+4000)) -> 726340.64 | P81: =(P80+4000)*1.00487-(0.00104*(P80+4000)) -> 809647.42 | Q81: =(Q80+4000)*1.00487-(0.00104*(Q80+4000)) -> 896864.67 | R81: =(R80+4000)*1.00487-(0.00104*(R80+4000)) -> 988175.95 | S81: =(S80+4000)*1.00487-(0.00104*(S80+4000)) -> 1083773.4 | T81: =(T80+4000)*1.00487-(0.000833*(T80+4000)) -> 1186735.7 | U81: =(U80+4000)*1.00487-(0.00125*(U80+4000)) -> 1291073.7 | V81: =(V80+4000)*1.00487-(0.00125*(V80+4000)) -> 1397432.7 | W81: =(W80+4000)*1.00487-(0.00125*(W80+4000)) -> 1508505.1 | X81: =(X80+4000)*1.00487-(0.00125*(X80+4000)) -> 1624499.7 | Y81: =(Y80+4000)*1.00487-(0.00125*(Y80+4000)) -> 1745634.6 | Z81: =(Z80+4000)*1.00487-(0.00125*(Z80+4000)) -> 1872137.7 | AA81: =(AA80+4000)*1.00487-(0.00125*(AA80+4000)) -> 2004246.8 | AB81: =(AB80+4000)*1.00487-(0.00125*(AB80+4000)) -> 2142210.4 | ... AE81: =(AE80+4000)*1.00487-(0.00125*(AE80+4000)) -> 2593880.5 | AI81: =(AI80+4000)*1.00487-0 -> 28550.785 | AJ81: =(AJ80+4000)*1.00487-0 -> 79811.623 | AK81: =(AK80+4000)*1.00487-0 -> 134149.7 | AL81: =(AL80+4000)*1.00487-0 -> 191749.75 | AM81: =(AM80+4000)*1.00487-0 -> 252807.58 | AN81: =(AN80+4000)*1.00487-0 -> 317530.78 | AO81: =(AO80+4000)*1.00487-0 -> 386139.38 | AP81: =(AP80+4000)*1.00487-0 -> 458866.62 | ... BJ81: =(BJ80+4000)*1.00487-0 -> 3295728.4
D82: =(D81+4000)*1.00487-(0.00146*(D81+4000)) -> 32494.967 | E82: =(E81+4000)*1.00487-(0.00146*(E81+4000)) -> 82927.222 | F82: =(F81+4000)*1.00487-(0.00146*(F81+4000)) -> 135462.31 | G82: =(G81+4000)*1.00487-(0.00146*(G81+4000)) -> 190187.92 | H82: =(H81+4000)*1.00487-(0.00146*(H81+4000)) -> 247195.38 | I82: =(I81+4000)*1.00487-(0.00125*(I81+4000)) -> 307239.62 | J82: =(J81+4000)*1.00487-(0.00125*(J81+4000)) -> 369999.64 | K82: =(K81+4000)*1.00487-(0.00125*(K81+4000)) -> 435540.89 | L82: =(L81+4000)*1.00487-(0.00104*(L81+4000)) -> 504092.09 | M82: =(M81+4000)*1.00487-(0.00104*(M81+4000)) -> 576966.39 | N82: =(N81+4000)*1.00487-(0.00104*(N81+4000)) -> 653261.45 | O82: =(O81+4000)*1.00487-(0.00104*(O81+4000)) -> 733137.84 | P82: =(P81+4000)*1.00487-(0.00104*(P81+4000)) -> 816763.69 | Q82: =(Q81+4000)*1.00487-(0.00104*(Q81+4000)) -> 904314.98 | R82: =(R81+4000)*1.00487-(0.00104*(R81+4000)) -> 995975.98 | S82: =(S81+4000)*1.00487-(0.000833*(S81+4000)) -> 1092164.8 | T82: =(T81+4000)*1.00487-(0.000833*(T81+4000)) -> 1195542.7 | U82: =(U81+4000)*1.00487-(0.00125*(U81+4000)) -> 1299761.9 | V82: =(V81+4000)*1.00487-(0.00125*(V81+4000)) -> 1406505.9 | W82: =(W81+4000)*1.00487-(0.00125*(W81+4000)) -> 1517980.4 | X82: =(X81+4000)*1.00487-(0.00125*(X81+4000)) -> 1634394.9 | Y82: =(Y81+4000)*1.00487-(0.00125*(Y81+4000)) -> 1755968.3 | Z82: =(Z81+4000)*1.00487-(0.00125*(Z81+4000)) -> 1882929.3 | AA82: =(AA81+4000)*1.00487-(0.00125*(AA81+4000)) -> 2015516.7 | AB82: =(AB81+4000)*1.00487-(0.00125*(AB81+4000)) -> 2153979.7 | ... AE82: =(AE81+4000)*1.00487-(0.00125*(AE81+4000)) -> 2607284.8 | AI82: =(AI81+4000)*1.00487-0 -> 32709.307 | AJ82: =(AJ81+4000)*1.00487-0 -> 84219.785 | AK82: =(AK81+4000)*1.00487-0 -> 138822.49 | AL82: =(AL81+4000)*1.00487-0 -> 196703.05 | AM82: =(AM81+4000)*1.00487-0 -> 258058.24 | AN82: =(AN81+4000)*1.00487-0 -> 323096.64 | AO82: =(AO81+4000)*1.00487-0 -> 392039.36 | AP82: =(AP81+4000)*1.00487-0 -> 465120.78 | ... BJ82: =(BJ81+4000)*1.00487-0 -> 3315798.1
D83: =(D82+4000)*1.00487-(0.00146*(D82+4000)) -> 36619.415 | E83: =(E82+4000)*1.00487-(0.00146*(E82+4000)) -> 87223.644 | F83: =(F82+4000)*1.00487-(0.00146*(F82+4000)) -> 139937.88 | G83: =(G82+4000)*1.00487-(0.00146*(G82+4000)) -> 194850.1 | H83: =(H82+4000)*1.00487-(0.00146*(H82+4000)) -> 252051.95 | I83: =(I82+4000)*1.00487-(0.00125*(I82+4000)) -> 312366.31 | J83: =(J82+4000)*1.00487-(0.00125*(J82+4000)) -> 375353.52 | K83: =(K82+4000)*1.00487-(0.00125*(K82+4000)) -> 441132.03 | L83: =(L82+4000)*1.00487-(0.00104*(L82+4000)) -> 510038.08 | M83: =(M82+4000)*1.00487-(0.00104*(M82+4000)) -> 583191.49 | N83: =(N82+4000)*1.00487-(0.00104*(N82+4000)) -> 659778.76 | O83: =(O82+4000)*1.00487-(0.00104*(O82+4000)) -> 739961.08 | P83: =(P82+4000)*1.00487-(0.00104*(P82+4000)) -> 823907.21 | Q83: =(Q82+4000)*1.00487-(0.00104*(Q82+4000)) -> 911793.83 | R83: =(R82+4000)*1.00487-(0.00104*(R82+4000)) -> 1003805.9 | S83: =(S82+4000)*1.00487-(0.000833*(S82+4000)) -> 1100590 | T83: =(T82+4000)*1.00487-(0.000833*(T82+4000)) -> 1204385.3 | U83: =(U82+4000)*1.00487-(0.00125*(U82+4000)) -> 1308481.5 | V83: =(V82+4000)*1.00487-(0.00125*(V82+4000)) -> 1415611.9 | W83: =(W82+4000)*1.00487-(0.00125*(W82+4000)) -> 1527489.9 | X83: =(X82+4000)*1.00487-(0.00125*(X82+4000)) -> 1644325.9 | Y83: =(Y82+4000)*1.00487-(0.00125*(Y82+4000)) -> 1766339.4 | Z83: =(Z82+4000)*1.00487-(0.00125*(Z82+4000)) -> 1893760 | AA83: =(AA82+4000)*1.00487-(0.00125*(AA82+4000)) -> 2026827.3 | AB83: =(AB82+4000)*1.00487-(0.00125*(AB82+4000)) -> 2165791.6 | ... AE83: =(AE82+4000)*1.00487-(0.00125*(AE82+4000)) -> 2620737.6 | AI83: =(AI82+4000)*1.00487-0 -> 36888.082 | AJ83: =(AJ82+4000)*1.00487-0 -> 88649.416 | AK83: =(AK82+4000)*1.00487-0 -> 143518.03 | AL83: =(AL82+4000)*1.00487-0 -> 201680.47 | AM83: =(AM82+4000)*1.00487-0 -> 263334.46 | AN83: =(AN82+4000)*1.00487-0 -> 328689.6 | AO83: =(AO82+4000)*1.00487-0 -> 397968.07 | AP83: =(AP82+4000)*1.00487-0 -> 471405.4 | ... BJ83: =(BJ82+4000)*1.00487-0 -> 3335965.5
D84: =(D83+4000)*1.00487-(0.00146*(D83+4000)) -> 40757.927 | E84: =(E83+4000)*1.00487-(0.00146*(E83+4000)) -> 91534.716 | F84: =(F83+4000)*1.00487-(0.00146*(F83+4000)) -> 144428.71 | G84: =(G83+4000)*1.00487-(0.00146*(G83+4000)) -> 199528.18 | H84: =(H83+4000)*1.00487-(0.00125*(H83+4000)) -> 256978.86 | I84: =(I83+4000)*1.00487-(0.00125*(I83+4000)) -> 317511.55 | J84: =(J83+4000)*1.00487-(0.00125*(J83+4000)) -> 380726.78 | K84: =(K83+4000)*1.00487-(0.00125*(K83+4000)) -> 446743.41 | L84: =(L83+4000)*1.00487-(0.00104*(L83+4000)) -> 516006.85 | M84: =(M83+4000)*1.00487-(0.00104*(M83+4000)) -> 589440.43 | N84: =(N83+4000)*1.00487-(0.00104*(N83+4000)) -> 666321.03 | O84: =(O83+4000)*1.00487-(0.00104*(O83+4000)) -> 746810.45 | P84: =(P83+4000)*1.00487-(0.00104*(P83+4000)) -> 831078.1 | Q84: =(Q83+4000)*1.00487-(0.00104*(Q83+4000)) -> 919301.32 | R84: =(R83+4000)*1.00487-(0.00104*(R83+4000)) -> 1011665.8 | S84: =(S83+4000)*1.00487-(0.000833*(S83+4000)) -> 1109049.2 | T84: =(T83+4000)*1.00487-(0.000833*(T83+4000)) -> 1213263.5 | U84: =(U83+4000)*1.00487-(0.00125*(U83+4000)) -> 1317232.7 | V84: =(V83+4000)*1.00487-(0.00125*(V83+4000)) -> 1424750.9 | W84: =(W83+4000)*1.00487-(0.00125*(W83+4000)) -> 1537033.9 | X84: =(X83+4000)*1.00487-(0.00125*(X83+4000)) -> 1654292.8 | Y84: =(Y83+4000)*1.00487-(0.00125*(Y83+4000)) -> 1776748 | Z84: =(Z83+4000)*1.00487-(0.00125*(Z83+4000)) -> 1904629.9 | AA84: =(AA83+4000)*1.00487-(0.00125*(AA83+4000)) -> 2038178.9 | AB84: =(AB83+4000)*1.00487-(0.00125*(AB83+4000)) -> 2177646.2 | ... AE84: =(AE83+4000)*1.00487-(0.00125*(AE83+4000)) -> 2634239.2 | AI84: =(AI83+4000)*1.00487-0 -> 41087.207 | AJ84: =(AJ83+4000)*1.00487-0 -> 93100.618 | AK84: =(AK83+4000)*1.00487-0 -> 148236.45 | AL84: =(AL83+4000)*1.00487-0 -> 206682.14 | AM84: =(AM83+4000)*1.00487-0 -> 268636.38 | AN84: =(AN83+4000)*1.00487-0 -> 334309.8 | AO84: =(AO83+4000)*1.00487-0 -> 403925.65 | AP84: =(AP83+4000)*1.00487-0 -> 477720.62 | ... BJ84: =(BJ83+4000)*1.00487-0 -> 3356231.2
D85: =(D84+4000)*1.00487-(0.00146*(D84+4000)) -> 44910.552 | E85: =(E84+4000)*1.00487-(0.00146*(E84+4000)) -> 95860.49 | F85: =(F84+4000)*1.00487-(0.00146*(F84+4000)) -> 148934.85 | G85: =(G84+4000)*1.00487-(0.00146*(G84+4000)) -> 204222.21 | H85: =(H84+4000)*1.00487-(0.00125*(H84+4000)) -> 261923.61 | I85: =(I84+4000)*1.00487-(0.00125*(I84+4000)) -> 322675.43 | J85: =(J84+4000)*1.00487-(0.00125*(J84+4000)) -> 386119.49 | K85: =(K84+4000)*1.00487-(0.00125*(K84+4000)) -> 452375.1 | L85: =(L84+4000)*1.00487-(0.00104*(L84+4000)) -> 521998.48 | M85: =(M84+4000)*1.00487-(0.00104*(M84+4000)) -> 595713.31 | N85: =(N84+4000)*1.00487-(0.00104*(N84+4000)) -> 672888.36 | O85: =(O84+4000)*1.00487-(0.00104*(O84+4000)) -> 753686.06 | P85: =(P84+4000)*1.00487-(0.00104*(P84+4000)) -> 838276.45 | Q85: =(Q84+4000)*1.00487-(0.00104*(Q84+4000)) -> 926837.56 | R85: =(R84+4000)*1.00487-(0.00104*(R84+4000)) -> 1019555.8 | S85: =(S84+4000)*1.00487-(0.000833*(S84+4000)) -> 1117542.6 | T85: =(T84+4000)*1.00487-(0.000833*(T84+4000)) -> 1222177.6 | U85: =(U84+4000)*1.00487-(0.00125*(U84+4000)) -> 1326015.5 | V85: =(V84+4000)*1.00487-(0.00125*(V84+4000)) -> 1433923 | W85: =(W84+4000)*1.00487-(0.00125*(W84+4000)) -> 1546612.5 | X85: =(X84+4000)*1.00487-(0.00125*(X84+4000)) -> 1664295.8 | Y85: =(Y84+4000)*1.00487-(0.00125*(Y84+4000)) -> 1787194.3 | Z85: =(Z84+4000)*1.00487-(0.00125*(Z84+4000)) -> 1915539.2 | AA85: =(AA84+4000)*1.00487-(0.00125*(AA84+4000)) -> 2049571.6 | AB85: =(AB84+4000)*1.00487-(0.00125*(AB84+4000)) -> 2189543.8 | ... AE85: =(AE84+4000)*1.00487-(0.00125*(AE84+4000)) -> 2647789.6 | AI85: =(AI84+4000)*1.00487-0 -> 45306.781 | AJ85: =(AJ84+4000)*1.00487-0 -> 97573.498 | AK85: =(AK84+4000)*1.00487-0 -> 152977.84 | AL85: =(AL84+4000)*1.00487-0 -> 211708.16 | AM85: =(AM84+4000)*1.00487-0 -> 273964.12 | AN85: =(AN84+4000)*1.00487-0 -> 339957.36 | AO85: =(AO84+4000)*1.00487-0 -> 409912.25 | AP85: =(AP84+4000)*1.00487-0 -> 484066.6 | ... BJ85: =(BJ84+4000)*1.00487-0 -> 3376595.5
D86: =(D85+4000)*1.00487-(0.00146*(D85+4000)) -> 49077.337 | E86: =(E85+4000)*1.00487-(0.00146*(E85+4000)) -> 100201.01 | F86: =(F85+4000)*1.00487-(0.00146*(F85+4000)) -> 153456.36 | G86: =(G85+4000)*1.00487-(0.00146*(G85+4000)) -> 208932.25 | H86: =(H85+4000)*1.00487-(0.00125*(H85+4000)) -> 266886.25 | I86: =(I85+4000)*1.00487-(0.00125*(I85+4000)) -> 327857.99 | J86: =(J85+4000)*1.00487-(0.00125*(J85+4000)) -> 391531.72 | K86: =(K85+4000)*1.00487-(0.00125*(K85+4000)) -> 458027.18 | L86: =(L85+4000)*1.00487-(0.00104*(L85+4000)) -> 528013.05 | M86: =(M85+4000)*1.00487-(0.00104*(M85+4000)) -> 602010.21 | N86: =(N85+4000)*1.00487-(0.00104*(N85+4000)) -> 679480.84 | O86: =(O85+4000)*1.00487-(0.00104*(O85+4000)) -> 760587.99 | P86: =(P85+4000)*1.00487-(0.00104*(P85+4000)) -> 845502.36 | Q86: =(Q85+4000)*1.00487-(0.00104*(Q85+4000)) -> 934402.67 | R86: =(R85+4000)*1.00487-(0.00104*(R85+4000)) -> 1027476 | S86: =(S85+4000)*1.00487-(0.000833*(S85+4000)) -> 1126070.3 | T86: =(T85+4000)*1.00487-(0.000833*(T85+4000)) -> 1231127.7 | U86: =(U85+4000)*1.00487-(0.00125*(U85+4000)) -> 1334830.2 | V86: =(V85+4000)*1.00487-(0.00125*(V85+4000)) -> 1443128.3 | W86: =(W85+4000)*1.00487-(0.00125*(W85+4000)) -> 1556225.7 | X86: =(X85+4000)*1.00487-(0.00125*(X85+4000)) -> 1674335 | Y86: =(Y85+4000)*1.00487-(0.00125*(Y85+4000)) -> 1797678.5 | Z86: =(Z85+4000)*1.00487-(0.00125*(Z85+4000)) -> 1926487.9 | AA86: =(AA85+4000)*1.00487-(0.00125*(AA85+4000)) -> 2061005.6 | AB86: =(AB85+4000)*1.00487-(0.00125*(AB85+4000)) -> 2201484.4 | ... AE86: =(AE85+4000)*1.00487-(0.00125*(AE85+4000)) -> 2661389.1 | AI86: =(AI85+4000)*1.00487-0 -> 49546.905 | AJ86: =(AJ85+4000)*1.00487-0 -> 102068.16 | AK86: =(AK85+4000)*1.00487-0 -> 157742.32 | AL86: =(AL85+4000)*1.00487-0 -> 216758.66 | AM86: =(AM85+4000)*1.00487-0 -> 279317.8 | AN86: =(AN85+4000)*1.00487-0 -> 345632.44 | AO86: =(AO85+4000)*1.00487-0 -> 415928.01 | AP86: =(AP85+4000)*1.00487-0 -> 490443.49 | ... BJ86: =(BJ85+4000)*1.00487-0 -> 3397059
D89: Scenario 5 | AI89: Scenario 5 | AJ89: WITHOUT AN ADVISOR
D90: Assume 7% annual return on investments | AI90: Assume 7% annual return on investments
D91: Assume 4K/mo invested | AI91: Assume 4K/mo invested
D92: Y1 | E92: Y2 | F92: Y3 | G92: Y4 | H92: Y5 | I92: Y6 | J92: Y7 | K92: Y8 | L92: Y9 | M92: Y10 | N92: Y11 | O92: Y12 | P92: Y13 | Q92: Y14 | R92: Y15 | S92: Y16 | T92: Y17 | U92: Y18 | V92: Y19 | W92: Y20 | X92: Y21 | Y92: Y22 | Z92: Y23 | AA92: Y24 | AB92: Y25 | AC92: Y26 | AD92: Y27 | AE92: Y28 | AI92: Y1 | AJ92: Y2 | AK92: Y3 | AL92: Y4 | AM92: Y5 | AN92: Y6 | AO92: Y7 | AP92: Y8 | AQ92: Y9 | AR92: Y10 | AS92: Y11 | AT92: Y12 | AU92: Y13 | AV92: Y14 | AW92: Y15 | AX92: Y16 | AY92: Y17 | AZ92: Y18 | BA92: Y19 | BB92: Y20 | BC92: Y21 | BD92: Y22 | BE92: Y23 | BF92: Y24 | BG92: Y25 | BH92: Y26 | BI92: Y27 | BJ92: Y28
D93: 0 | AI93: 0
D94: =(D93+4000)*1.00566-(0.00146*(D93+4000)) -> 4016.8 | E94: =(D105+4000)*1.00566-(0.00146*(D105+4000)) -> 53554.783 | F94: =(E105+4000)*1.00566-(0.00146*(E105+4000)) -> 105647.97 | G94: =(F105+4000)*1.00566-(0.00146*(F105+4000)) -> 160428.16 | H94: =(G105+4000)*1.00566-(0.00146*(G105+4000)) -> 218033.95 | I94: =(H105+4000)*1.00566-(0.00125*(H105+4000)) -> 278948.17 | J94: =(I105+4000)*1.00566-(0.00125*(I105+4000)) -> 343471.89 | K94: =(J105+4000)*1.00566-(0.00125*(J105+4000)) -> 411494.25 | L94: =(K105+4000)*1.00566-(0.00125*(K105+4000)) -> 483204.97 | M94: =(L105+4000)*1.00566-(0.00104*(L105+4000)) -> 559935.17 | N94: =(M105+4000)*1.00566-(0.00104*(M105+4000)) -> 641245.19 | O94: =(N105+4000)*1.00566-(0.00104*(N105+4000)) -> 727179.36 | P94: =(O105+4000)*1.00566-(0.00104*(O105+4000)) -> 818000.67 | Q94: =(P105+4000)*1.00566-(0.00104*(P105+4000)) -> 913987.05 | R94: =(Q105+4000)*1.00566-(0.000833*(Q105+4000)) -> 1015849.9 | S94: =(R105+4000)*1.00566-(0.000833*(R105+4000)) -> 1125812.6 | T94: =(S105+4000)*1.00566-(0.000833*(S105+4000)) -> 1242316.6 | U94: =(T105+4000)*1.00566-(0.00125*(T105+4000)) -> 1365184.2 | V94: =(U105+4000)*1.00566-(0.00125*(U105+4000)) -> 1488606.5 | W94: =(V105+4000)*1.00566-(0.00125*(V105+4000)) -> 1618721.1 | X94: =(W105+4000)*1.00566-(0.00125*(W105+4000)) -> 1755890.9 | Y94: =(X105+4000)*1.00566-(0.00125*(X105+4000)) -> 1900498.3 | Z94: =(Y105+4000)*1.00566-(0.00125*(Y105+4000)) -> 2052946.7 | AA94: =(Z105+4000)*1.00566-(0.00125*(Z105+4000)) -> 2213661.3 | AB94: =(AA105+4000)*1.00566-(0.00125*(AA105+4000)) -> 2383090.3 | ... AE94: =(AD105+4000)*1.00566-(0.00125*(AD105+4000)) -> 2948518 | AI94: =(AI93+4000)*1.00566-0 -> 4022.64 | AJ94: =(AI105+4000)*1.00566-0 -> 54107.618 | AK94: =(AJ105+4000)*1.00566-0 -> 107702.29 | AL94: =(AK105+4000)*1.00566-0 -> 165052.59 | AM94: =(AL105+4000)*1.00566-0 -> 226421.7 | AN94: =(AM105+4000)*1.00566-0 -> 292091.24 | AO94: =(AN105+4000)*1.00566-0 -> 362362.56 | AP94: =(AO105+4000)*1.00566-0 -> 437558.12 | AQ94: =(AP105+4000)*1.00566-0 -> 518022.99 | ... BJ94: =(BI105+4000)*1.00566-0 -> 3738948.9
D95: =(D94+4000)*1.00566-(0.00146*(D94+4000)) -> 8050.4706 | E95: =(E94+4000)*1.00566-(0.00146*(E94+4000)) -> 57796.513 | F95: =(F94+4000)*1.00566-(0.00146*(F94+4000)) -> 110108.49 | G95: =(G94+4000)*1.00566-(0.00146*(G94+4000)) -> 165118.76 | H95: =(H94+4000)*1.00566-(0.00146*(H94+4000)) -> 222966.49 | I95: =(I94+4000)*1.00566-(0.00125*(I94+4000)) -> 284195.97 | J95: =(J94+4000)*1.00566-(0.00125*(J94+4000)) -> 349004.24 | K95: =(K94+4000)*1.00566-(0.00125*(K94+4000)) -> 417326.58 | L95: =(L94+4000)*1.00566-(0.00125*(L94+4000)) -> 489353.54 | M95: =(M94+4000)*1.00566-(0.00104*(M94+4000)) -> 566540.55 | N95: =(N94+4000)*1.00566-(0.00104*(N94+4000)) -> 648226.22 | O95: =(O94+4000)*1.00566-(0.00104*(O94+4000)) -> 734557.41 | P95: =(P94+4000)*1.00566-(0.00104*(P94+4000)) -> 825798.31 | Q95: =(Q94+4000)*1.00566-(0.00104*(Q94+4000)) -> 922228.15 | R95: =(R94+4000)*1.00566-(0.000833*(R94+4000)) -> 1024772.7 | S95: =(S94+4000)*1.00566-(0.000833*(S94+4000)) -> 1135266.2 | T95: =(T94+4000)*1.00566-(0.000833*(T94+4000)) -> 1252332.5 | U95: =(U94+4000)*1.00566-(0.00125*(U94+4000)) -> 1375222.3 | V95: =(V94+4000)*1.00566-(0.00125*(V94+4000)) -> 1499188.9 | W95: =(W94+4000)*1.00566-(0.00125*(W94+4000)) -> 1629877.3 | X95: =(X94+4000)*1.00566-(0.00125*(X94+4000)) -> 1767652 | Y95: =(Y94+4000)*1.00566-(0.00125*(Y94+4000)) -> 1912897.1 | Z95: =(Z94+4000)*1.00566-(0.00125*(Z94+4000)) -> 2066017.9 | AA95: =(AA94+4000)*1.00566-(0.00125*(AA94+4000)) -> 2227441.2 | AB95: =(AB94+4000)*1.00566-(0.00125*(AB94+4000)) -> 2397617.3 | ... AE95: =(AE94+4000)*1.00566-(0.00125*(AE94+4000)) -> 2965538.6 | AI95: =(AI94+4000)*1.00566-0 -> 8068.0481 | AJ95: =(AJ94+4000)*1.00566-0 -> 58436.507 | AK95: =(AK94+4000)*1.00566-0 -> 112334.52 | AL95: =(AL94+4000)*1.00566-0 -> 170009.43 | AM95: =(AM94+4000)*1.00566-0 -> 231725.89 | AN95: =(AN94+4000)*1.00566-0 -> 297767.12 | AO95: =(AO94+4000)*1.00566-0 -> 368436.17 | AP95: =(AP94+4000)*1.00566-0 -> 444057.34 | ... BJ95: =(BJ94+4000)*1.00566-0 -> 3764134
A96: =0.0175/12 -> 0.0014583333 | B96: 1.75 | D96: =(D95+4000)*1.00566-(0.00146*(D95+4000)) -> 12101.083 | E96: =(E95+4000)*1.00566-(0.00146*(E95+4000)) -> 62056.058 | F96: =(F95+4000)*1.00566-(0.00146*(F95+4000)) -> 114587.75 | G96: =(G95+4000)*1.00566-(0.00146*(G95+4000)) -> 169829.06 | H96: =(H95+4000)*1.00566-(0.00146*(H95+4000)) -> 227919.75 | I96: =(I95+4000)*1.00566-(0.00125*(I95+4000)) -> 289466.91 | J96: =(J95+4000)*1.00566-(0.00125*(J95+4000)) -> 354560.99 | K96: =(K95+4000)*1.00566-(0.00125*(K95+4000)) -> 423184.63 | L96: =(L95+4000)*1.00566-(0.00125*(L95+4000)) -> 495529.23 | M96: =(M95+4000)*1.00566-(0.00104*(M95+4000)) -> 573176.45 | N96: =(N95+4000)*1.00566-(0.00104*(N95+4000)) -> 655239.51 | O96: =(O95+4000)*1.00566-(0.00104*(O95+4000)) -> 741969.55 | P96: =(P95+4000)*1.00566-(0.00104*(P95+4000)) -> 833631.98 | Q96: =(Q95+4000)*1.00566-(0.00104*(Q95+4000)) -> 930507.32 | R96: =(R95+4000)*1.00566-(0.000833*(R95+4000)) -> 1033738.6 | S96: =(S95+4000)*1.00566-(0.000833*(S95+4000)) -> 1144765.4 | T96: =(T95+4000)*1.00566-(0.000833*(T95+4000)) -> 1262396.9 | U96: =(U95+4000)*1.00566-(0.00125*(U95+4000)) -> 1385304.7 | V96: =(V95+4000)*1.00566-(0.00125*(V95+4000)) -> 1509818 | W96: =(W95+4000)*1.00566-(0.00125*(W95+4000)) -> 1641082.7 | X96: =(X95+4000)*1.00566-(0.00125*(X95+4000)) -> 1779465 | Y96: =(Y95+4000)*1.00566-(0.00125*(Y95+4000)) -> 1925350.6 | Z96: =(Z95+4000)*1.00566-(0.00125*(Z95+4000)) -> 2079146.6 | AA96: =(AA95+4000)*1.00566-(0.00125*(AA95+4000)) -> 2241281.9 | AB96: =(AB95+4000)*1.00566-(0.00125*(AB95+4000)) -> 2412208.5 | ... AE96: =(AE95+4000)*1.00566-(0.00125*(AE95+4000)) -> 2982634.3 | AI96: =(AI95+4000)*1.00566-0 -> 12136.353 | AJ96: =(AJ95+4000)*1.00566-0 -> 62789.898 | AK96: =(AK95+4000)*1.00566-0 -> 116992.98 | AL96: =(AL95+4000)*1.00566-0 -> 174994.32 | AM96: =(AM95+4000)*1.00566-0 -> 237060.1 | AN96: =(AN95+4000)*1.00566-0 -> 303475.12 | AO96: =(AO95+4000)*1.00566-0 -> 374544.16 | AP96: =(AP95+4000)*1.00566-0 -> 450593.34 | ... BJ96: =(BJ95+4000)*1.00566-0 -> 3789461.6
A97: =0.015/12 -> 0.00125 | B97: 1.5 | D97: =(D96+4000)*1.00566-(0.00146*(D96+4000)) -> 16168.707 | E97: =(E96+4000)*1.00566-(0.00146*(E96+4000)) -> 66333.494 | F97: =(F96+4000)*1.00566-(0.00146*(F96+4000)) -> 119085.82 | G97: =(G96+4000)*1.00566-(0.00146*(G96+4000)) -> 174559.14 | H97: =(H96+4000)*1.00566-(0.00146*(H96+4000)) -> 232893.81 | I97: =(I96+4000)*1.00566-(0.00125*(I96+4000)) -> 294761.1 | J97: =(J96+4000)*1.00566-(0.00125*(J96+4000)) -> 360142.24 | K97: =(K96+4000)*1.00566-(0.00125*(K96+4000)) -> 429068.52 | L97: =(L96+4000)*1.00566-(0.00104*(L96+4000)) -> 501837.06 | M97: =(M96+4000)*1.00566-(0.00104*(M96+4000)) -> 579843 | N97: =(N96+4000)*1.00566-(0.00104*(N96+4000)) -> 662285.19 | O97: =(O96+4000)*1.00566-(0.00104*(O96+4000)) -> 749415.93 | P97: =(P96+4000)*1.00566-(0.00104*(P96+4000)) -> 841501.84 | Q97: =(Q96+4000)*1.00566-(0.00104*(Q96+4000)) -> 938824.74 | R97: =(R96+4000)*1.00566-(0.000833*(R96+4000)) -> 1042747.8 | S97: =(S96+4000)*1.00566-(0.000833*(S96+4000)) -> 1154310.5 | T97: =(T96+4000)*1.00566-(0.000833*(T96+4000)) -> 1272509.8 | U97: =(U96+4000)*1.00566-(0.00125*(U96+4000)) -> 1395431.5 | V97: =(V96+4000)*1.00566-(0.00125*(V96+4000)) -> 1520493.9 | W97: =(W96+4000)*1.00566-(0.00125*(W96+4000)) -> 1652337.5 | X97: =(X96+4000)*1.00566-(0.00125*(X96+4000)) -> 1791330 | Y97: =(Y96+4000)*1.00566-(0.00125*(Y96+4000)) -> 1937859.1 | Z97: =(Z96+4000)*1.00566-(0.00125*(Z96+4000)) -> 2092333.3 | AA97: =(AA96+4000)*1.00566-(0.00125*(AA96+4000)) -> 2255183.6 | AB97: =(AB96+4000)*1.00566-(0.00125*(AB96+4000)) -> 2426864 | ... AE97: =(AE96+4000)*1.00566-(0.00125*(AE96+4000)) -> 2999805.3 | AI97: =(AI96+4000)*1.00566-0 -> 16227.685 | AJ97: =(AJ96+4000)*1.00566-0 -> 67167.929 | AK97: =(AK96+4000)*1.00566-0 -> 121677.8 | AL97: =(AL96+4000)*1.00566-0 -> 180007.43 | AM97: =(AM96+4000)*1.00566-0 -> 242424.5 | AN97: =(AN96+4000)*1.00566-0 -> 309215.43 | AO97: =(AO96+4000)*1.00566-0 -> 380686.72 | AP97: =(AP96+4000)*1.00566-0 -> 457166.34 | ... BJ97: =(BJ96+4000)*1.00566-0 -> 3814932.6
A98: =0.0125/12 -> 0.0010416667 | B98: 1.25 | D98: =(D97+4000)*1.00566-(0.00146*(D97+4000)) -> 20253.416 | E98: =(E97+4000)*1.00566-(0.00146*(E97+4000)) -> 70628.895 | F98: =(F97+4000)*1.00566-(0.00146*(F97+4000)) -> 123602.78 | G98: =(G97+4000)*1.00566-(0.00146*(G97+4000)) -> 179309.09 | H98: =(H97+4000)*1.00566-(0.00146*(H97+4000)) -> 237888.77 | I98: =(I97+4000)*1.00566-(0.00125*(I97+4000)) -> 300078.64 | J98: =(J97+4000)*1.00566-(0.00125*(J97+4000)) -> 365748.11 | K98: =(K97+4000)*1.00566-(0.00125*(K97+4000)) -> 434978.35 | L98: =(L97+4000)*1.00566-(0.00104*(L97+4000)) -> 508174.03 | M98: =(M97+4000)*1.00566-(0.00104*(M97+4000)) -> 586540.36 | N98: =(N97+4000)*1.00566-(0.00104*(N97+4000)) -> 669363.43 | O98: =(O97+4000)*1.00566-(0.00104*(O97+4000)) -> 756896.71 | P98: =(P97+4000)*1.00566-(0.00104*(P97+4000)) -> 849408.06 | Q98: =(Q97+4000)*1.00566-(0.00104*(Q97+4000)) -> 947180.59 | R98: =(R97+4000)*1.00566-(0.000833*(R97+4000)) -> 1051800.4 | S98: =(S97+4000)*1.00566-(0.000833*(S97+4000)) -> 1163901.7 | T98: =(T97+4000)*1.00566-(0.000833*(T97+4000)) -> 1282671.5 | U98: =(U97+4000)*1.00566-(0.00125*(U97+4000)) -> 1405603 | V98: =(V97+4000)*1.00566-(0.00125*(V97+4000)) -> 1531217 | W98: =(W97+4000)*1.00566-(0.00125*(W97+4000)) -> 1663642 | X98: =(X97+4000)*1.00566-(0.00125*(X97+4000)) -> 1803247.4 | Y98: =(Y97+4000)*1.00566-(0.00125*(Y97+4000)) -> 1950422.7 | Z98: =(Z97+4000)*1.00566-(0.00125*(Z97+4000)) -> 2105578.1 | AA98: =(AA97+4000)*1.00566-(0.00125*(AA97+4000)) -> 2269146.6 | AB98: =(AB97+4000)*1.00566-(0.00125*(AB97+4000)) -> 2441584.1 | ... AE98: =(AE97+4000)*1.00566-(0.00125*(AE97+4000)) -> 3017052.1 | AI98: =(AI97+4000)*1.00566-0 -> 20342.174 | AJ98: =(AJ97+4000)*1.00566-0 -> 71570.739 | AK98: =(AK97+4000)*1.00566-0 -> 126389.13 | AL98: =(AL97+4000)*1.00566-0 -> 185048.91 | AM98: =(AM97+4000)*1.00566-0 -> 247819.26 | AN98: =(AN97+4000)*1.00566-0 -> 314988.23 | AO98: =(AO97+4000)*1.00566-0 -> 386864.04 | AP98: =(AP97+4000)*1.00566-0 -> 463776.54 | ... BJ98: =(BJ97+4000)*1.00566-0 -> 3840547.8
A99: =0.01/12 -> 0.00083333333 | B99: 1 | D99: =(D98+4000)*1.00566-(0.00146*(D98+4000)) -> 24355.28 | E99: =(E98+4000)*1.00566-(0.00146*(E98+4000)) -> 74942.336 | F99: =(F98+4000)*1.00566-(0.00146*(F98+4000)) -> 128138.71 | G99: =(G98+4000)*1.00566-(0.00146*(G98+4000)) -> 184078.98 | H99: =(H98+4000)*1.00566-(0.00146*(H98+4000)) -> 242904.7 | I99: =(I98+4000)*1.00566-(0.00125*(I98+4000)) -> 305419.63 | J99: =(J98+4000)*1.00566-(0.00125*(J98+4000)) -> 371378.7 | K99: =(K98+4000)*1.00566-(0.00125*(K98+4000)) -> 440914.24 | L99: =(L98+4000)*1.00566-(0.00104*(L98+4000)) -> 514540.27 | M99: =(M98+4000)*1.00566-(0.00104*(M98+4000)) -> 593268.65 | N99: =(N98+4000)*1.00566-(0.00104*(N98+4000)) -> 676474.37 | O99: =(O98+4000)*1.00566-(0.00104*(O98+4000)) -> 764412.05 | P99: =(P98+4000)*1.00566-(0.00104*(P98+4000)) -> 857350.81 | Q99: =(Q98+4000)*1.00566-(0.00104*(Q98+4000)) -> 955575.05 | R99: =(R98+4000)*1.00566-(0.000833*(R98+4000)) -> 1060896.8 | S99: =(S98+4000)*1.00566-(0.000833*(S98+4000)) -> 1173539.1 | T99: =(T98+4000)*1.00566-(0.000833*(T98+4000)) -> 1292882.2 | U99: =(U98+4000)*1.00566-(0.00125*(U98+4000)) -> 1415819.4 | V99: =(V98+4000)*1.00566-(0.00125*(V98+4000)) -> 1541987.3 | W99: =(W98+4000)*1.00566-(0.00125*(W98+4000)) -> 1674996.3 | X99: =(X98+4000)*1.00566-(0.00125*(X98+4000)) -> 1815217.4 | Y99: =(Y98+4000)*1.00566-(0.00125*(Y98+4000)) -> 1963041.7 | Z99: =(Z98+4000)*1.00566-(0.00125*(Z98+4000)) -> 2118881.4 | AA99: =(AA98+4000)*1.00566-(0.00125*(AA98+4000)) -> 2283171.1 | AB99: =(AB98+4000)*1.00566-(0.00125*(AB98+4000)) -> 2456369.1 | ... AE99: =(AE98+4000)*1.00566-(0.00125*(AE98+4000)) -> 3034375 | AI99: =(AI98+4000)*1.00566-0 -> 24479.95 | AJ99: =(AJ98+4000)*1.00566-0 -> 75998.47 | AK99: =(AK98+4000)*1.00566-0 -> 131127.14 | AL99: =(AL98+4000)*1.00566-0 -> 190118.93 | AM99: =(AM98+4000)*1.00566-0 -> 253244.56 | AN99: =(AN98+4000)*1.00566-0 -> 320793.7 | AO99: =(AO98+4000)*1.00566-0 -> 393076.33 | AP99: =(AP98+4000)*1.00566-0 -> 470424.15 | ... BJ99: =(BJ98+4000)*1.00566-0 -> 3866307.9
D100: =(D99+4000)*1.00566-(0.00146*(D99+4000)) -> 28474.372 | E100: =(E99+4000)*1.00566-(0.00146*(E99+4000)) -> 79273.894 | F100: =(F99+4000)*1.00566-(0.00146*(F99+4000)) -> 132693.69 | G100: =(G99+4000)*1.00566-(0.00146*(G99+4000)) -> 188868.92 | H100: =(H99+4000)*1.00566-(0.00146*(H99+4000)) -> 247941.7 | I100: =(I99+4000)*1.00566-(0.00125*(I99+4000)) -> 310784.17 | J100: =(J99+4000)*1.00566-(0.00125*(J99+4000)) -> 377034.12 | K100: =(K99+4000)*1.00566-(0.00125*(K99+4000)) -> 446876.32 | L100: =(L99+4000)*1.00566-(0.00104*(L99+4000)) -> 520935.93 | M100: =(M99+4000)*1.00566-(0.00104*(M99+4000)) -> 600028.03 | N100: =(N99+4000)*1.00566-(0.00104*(N99+4000)) -> 683618.16 | O100: =(O99+4000)*1.00566-(0.00104*(O99+4000)) -> 771962.12 | P100: =(P99+4000)*1.00566-(0.00104*(P99+4000)) -> 865330.25 | Q100: =(Q99+4000)*1.00566-(0.00104*(Q99+4000)) -> 964008.28 | R100: =(R99+4000)*1.00566-(0.000833*(R99+4000)) -> 1070037 | S100: =(S99+4000)*1.00566-(0.000833*(S99+4000)) -> 1183223.1 | T100: =(T99+4000)*1.00566-(0.000833*(T99+4000)) -> 1303142.3 | U100: =(U99+4000)*1.00566-(0.00125*(U99+4000)) -> 1426080.8 | V100: =(V99+4000)*1.00566-(0.00125*(V99+4000)) -> 1552805.1 | W100: =(W99+4000)*1.00566-(0.00125*(W99+4000)) -> 1686400.7 | X100: =(X99+4000)*1.00566-(0.00125*(X99+4000)) -> 1827240.2 | Y100: =(Y99+4000)*1.00566-(0.00125*(Y99+4000)) -> 1975716.3 | Z100: =(Z99+4000)*1.00566-(0.00125*(Z99+4000)) -> 2132243.3 | AA100: =(AA99+4000)*1.00566-(0.00125*(AA99+4000)) -> 2297257.6 | AB100: =(AB99+4000)*1.00566-(0.00125*(AB99+4000)) -> 2471219.3 | ... AE100: =(AE99+4000)*1.00566-(0.00125*(AE99+4000)) -> 3051774.2 | AI100: =(AI99+4000)*1.00566-0 -> 28641.147 | AJ100: =(AJ99+4000)*1.00566-0 -> 80451.261 | AK100: =(AK99+4000)*1.00566-0 -> 135891.96 | AL100: =(AL99+4000)*1.00566-0 -> 195217.64 | AM100: =(AM99+4000)*1.00566-0 -> 258700.56 | AN100: =(AN99+4000)*1.00566-0 -> 326632.04 | AO100: =(AO99+4000)*1.00566-0 -> 399323.79 | AP100: =(AP99+4000)*1.00566-0 -> 477109.4 | ... BJ100: =(BJ99+4000)*1.00566-0 -> 3892213.8
D101: =(D100+4000)*1.00566-(0.00146*(D100+4000)) -> 32610.765 | E101: =(E100+4000)*1.00566-(0.00146*(E100+4000)) -> 83623.644 | F101: =(F100+4000)*1.00566-(0.00146*(F100+4000)) -> 137267.8 | G101: =(G100+4000)*1.00566-(0.00146*(G100+4000)) -> 193678.97 | H101: =(H100+4000)*1.00566-(0.00125*(H100+4000)) -> 253052.76 | I101: =(I100+4000)*1.00566-(0.00125*(I100+4000)) -> 316172.37 | J101: =(J100+4000)*1.00566-(0.00125*(J100+4000)) -> 382714.48 | K101: =(K100+4000)*1.00566-(0.00125*(K100+4000)) -> 452864.68 | L101: =(L100+4000)*1.00566-(0.00104*(L100+4000)) -> 527361.13 | M101: =(M100+4000)*1.00566-(0.00104*(M100+4000)) -> 606818.64 | N101: =(N100+4000)*1.00566-(0.00104*(N100+4000)) -> 690794.96 | O101: =(O100+4000)*1.00566-(0.00104*(O100+4000)) -> 779547.06 | P101: =(P100+4000)*1.00566-(0.00104*(P100+4000)) -> 873346.55 | Q101: =(Q100+4000)*1.00566-(0.00104*(Q100+4000)) -> 972480.48 | R101: =(R100+4000)*1.00566-(0.000833*(R100+4000)) -> 1079221.4 | S101: =(S100+4000)*1.00566-(0.000833*(S100+4000)) -> 1192953.8 | T101: =(T100+4000)*1.00566-(0.000833*(T100+4000)) -> 1313451.9 | U101: =(U100+4000)*1.00566-(0.00125*(U100+4000)) -> 1436387.5 | V101: =(V100+4000)*1.00566-(0.00125*(V100+4000)) -> 1563670.6 | W101: =(W100+4000)*1.00566-(0.00125*(W100+4000)) -> 1697855.3 | X101: =(X100+4000)*1.00566-(0.00125*(X100+4000)) -> 1839315.9 | Y101: =(Y100+4000)*1.00566-(0.00125*(Y100+4000)) -> 1988446.9 | Z101: =(Z100+4000)*1.00566-(0.00125*(Z100+4000)) -> 2145664.1 | AA101: =(AA100+4000)*1.00566-(0.00125*(AA100+4000)) -> 2311406.1 | AB101: =(AB100+4000)*1.00566-(0.00125*(AB100+4000)) -> 2486135 | ... AE101: =(AE100+4000)*1.00566-(0.00125*(AE100+4000)) -> 3069250.2 | AI101: =(AI100+4000)*1.00566-0 -> 32825.896 | AJ101: =(AJ100+4000)*1.00566-0 -> 84929.255 | AK101: =(AK100+4000)*1.00566-0 -> 140683.74 | AL101: =(AL100+4000)*1.00566-0 -> 200345.22 | AM101: =(AM100+4000)*1.00566-0 -> 264187.45 | AN101: =(AN100+4000)*1.00566-0 -> 332503.41 | AO101: =(AO100+4000)*1.00566-0 -> 405606.6 | AP101: =(AP100+4000)*1.00566-0 -> 483832.47 | ... BJ101: =(BJ100+4000)*1.00566-0 -> 3918266.4
D102: =(D101+4000)*1.00566-(0.00146*(D101+4000)) -> 36764.53 | E102: =(E101+4000)*1.00566-(0.00146*(E101+4000)) -> 87991.663 | F102: =(F101+4000)*1.00566-(0.00146*(F101+4000)) -> 141861.13 | G102: =(G101+4000)*1.00566-(0.00146*(G101+4000)) -> 198509.22 | H102: =(H101+4000)*1.00566-(0.00125*(H101+4000)) -> 258186.37 | I102: =(I101+4000)*1.00566-(0.00125*(I101+4000)) -> 321584.33 | J102: =(J101+4000)*1.00566-(0.00125*(J101+4000)) -> 388419.89 | K102: =(K101+4000)*1.00566-(0.00125*(K101+4000)) -> 458879.45 | L102: =(L101+4000)*1.00566-(0.00104*(L101+4000)) -> 533816.02 | M102: =(M101+4000)*1.00566-(0.00104*(M101+4000)) -> 613640.63 | N102: =(N101+4000)*1.00566-(0.00104*(N101+4000)) -> 698004.91 | O102: =(O101+4000)*1.00566-(0.00104*(O101+4000)) -> 787167.05 | P102: =(P101+4000)*1.00566-(0.00104*(P101+4000)) -> 881399.89 | Q102: =(Q101+4000)*1.00566-(0.00104*(Q101+4000)) -> 980991.82 | R102: =(R101+4000)*1.00566-(0.000833*(R101+4000)) -> 1088450.1 | S102: =(S101+4000)*1.00566-(0.000833*(S101+4000)) -> 1202731.5 | T102: =(T101+4000)*1.00566-(0.000833*(T101+4000)) -> 1323811.2 | U102: =(U101+4000)*1.00566-(0.00125*(U101+4000)) -> 1446739.6 | V102: =(V101+4000)*1.00566-(0.00125*(V101+4000)) -> 1574584 | W102: =(W101+4000)*1.00566-(0.00125*(W101+4000)) -> 1709360.5 | X102: =(X101+4000)*1.00566-(0.00125*(X101+4000)) -> 1851444.9 | Y102: =(Y101+4000)*1.00566-(0.00125*(Y101+4000)) -> 2001233.6 | Z102: =(Z101+4000)*1.00566-(0.00125*(Z101+4000)) -> 2159144.1 | AA102: =(AA101+4000)*1.00566-(0.00125*(AA101+4000)) -> 2325617 | AB102: =(AB101+4000)*1.00566-(0.00125*(AB101+4000)) -> 2501116.5 | ... AE102: =(AE101+4000)*1.00566-(0.00125*(AE101+4000)) -> 3086803.2 | AI102: =(AI101+4000)*1.00566-0 -> 37034.33 | AJ102: =(AJ101+4000)*1.00566-0 -> 89432.595 | AK102: =(AK101+4000)*1.00566-0 -> 145502.65 | AL102: =(AL101+4000)*1.00566-0 -> 205501.81 | AM102: =(AM101+4000)*1.00566-0 -> 269705.39 | AN102: =(AN101+4000)*1.00566-0 -> 338408.02 | AO102: =(AO101+4000)*1.00566-0 -> 411924.97 | AP102: =(AP101+4000)*1.00566-0 -> 490593.61 | ... BJ102: =(BJ101+4000)*1.00566-0 -> 3944466.4
D103: =(D102+4000)*1.00566-(0.00146*(D102+4000)) -> 40935.741 | E103: =(E102+4000)*1.00566-(0.00146*(E102+4000)) -> 92378.028 | F103: =(F102+4000)*1.00566-(0.00146*(F102+4000)) -> 146473.74 | G103: =(G102+4000)*1.00566-(0.00146*(G102+4000)) -> 203359.76 | H103: =(H102+4000)*1.00566-(0.00125*(H102+4000)) -> 263342.61 | I103: =(I102+4000)*1.00566-(0.00125*(I102+4000)) -> 327020.15 | J103: =(J102+4000)*1.00566-(0.00125*(J102+4000)) -> 394150.46 | K103: =(K102+4000)*1.00566-(0.00125*(K102+4000)) -> 464920.75 | L103: =(L102+4000)*1.00566-(0.00104*(L102+4000)) -> 540300.73 | M103: =(M102+4000)*1.00566-(0.00104*(M102+4000)) -> 620494.13 | N103: =(N102+4000)*1.00566-(0.00104*(N102+4000)) -> 705248.17 | O103: =(O102+4000)*1.00566-(0.00104*(O102+4000)) -> 794822.24 | P103: =(P102+4000)*1.00566-(0.00104*(P102+4000)) -> 889490.44 | Q103: =(Q102+4000)*1.00566-(0.00104*(Q102+4000)) -> 989542.48 | R103: =(R102+4000)*1.00566-(0.000833*(R102+4000)) -> 1097723.4 | S103: =(S102+4000)*1.00566-(0.000833*(S102+4000)) -> 1212556.4 | T103: =(T102+4000)*1.00566-(0.000833*(T102+4000)) -> 1334220.5 | U103: =(U102+4000)*1.00566-(0.00125*(U102+4000)) -> 1457137.3 | V103: =(V102+4000)*1.00566-(0.00125*(V102+4000)) -> 1585545.6 | W103: =(W102+4000)*1.00566-(0.00125*(W102+4000)) -> 1720916.4 | X103: =(X102+4000)*1.00566-(0.00125*(X102+4000)) -> 1863627.5 | Y103: =(Y102+4000)*1.00566-(0.00125*(Y102+4000)) -> 2014076.7 | Z103: =(Z102+4000)*1.00566-(0.00125*(Z102+4000)) -> 2172683.6 | AA103: =(AA102+4000)*1.00566-(0.00125*(AA102+4000)) -> 2339890.7 | AB103: =(AB102+4000)*1.00566-(0.00125*(AB102+4000)) -> 2516164.1 | ... AE103: =(AE102+4000)*1.00566-(0.00125*(AE102+4000)) -> 3104433.6 | AI103: =(AI102+4000)*1.00566-0 -> 41266.585 | AJ103: =(AJ102+4000)*1.00566-0 -> 93961.423 | AK103: =(AK102+4000)*1.00566-0 -> 150348.84 | AL103: =(AL102+4000)*1.00566-0 -> 210687.59 | AM103: =(AM102+4000)*1.00566-0 -> 275254.56 | AN103: =(AN102+4000)*1.00566-0 -> 344346.05 | AO103: =(AO102+4000)*1.00566-0 -> 418279.11 | AP103: =(AP102+4000)*1.00566-0 -> 497393.01 | ... BJ103: =(BJ102+4000)*1.00566-0 -> 3970814.8
D104: =(D103+4000)*1.00566-(0.00146*(D103+4000)) -> 45124.471 | E104: =(E103+4000)*1.00566-(0.00146*(E103+4000)) -> 96782.816 | F104: =(F103+4000)*1.00566-(0.00146*(F103+4000)) -> 151105.73 | G104: =(G103+4000)*1.00566-(0.00146*(G103+4000)) -> 208230.67 | H104: =(H103+4000)*1.00566-(0.00125*(H103+4000)) -> 268521.59 | I104: =(I103+4000)*1.00566-(0.00125*(I103+4000)) -> 332479.95 | J104: =(J103+4000)*1.00566-(0.00125*(J103+4000)) -> 399906.3 | K104: =(K103+4000)*1.00566-(0.00125*(K103+4000)) -> 470988.69 | L104: =(L103+4000)*1.00566-(0.00104*(L103+4000)) -> 546815.4 | M104: =(M103+4000)*1.00566-(0.00104*(M103+4000)) -> 627379.29 | N104: =(N103+4000)*1.00566-(0.00104*(N103+4000)) -> 712524.9 | O104: =(O103+4000)*1.00566-(0.00104*(O103+4000)) -> 802512.8 | P104: =(P103+4000)*1.00566-(0.00104*(P103+4000)) -> 897618.37 | Q104: =(Q103+4000)*1.00566-(0.00104*(Q103+4000)) -> 998132.65 | R104: =(R103+4000)*1.00566-(0.000833*(R103+4000)) -> 1107041.4 | S104: =(S103+4000)*1.00566-(0.000833*(S103+4000)) -> 1222428.7 | T104: =(T103+4000)*1.00566-(0.000833*(T103+4000)) -> 1344680.1 | U104: =(U103+4000)*1.00566-(0.00125*(U103+4000)) -> 1467580.9 | V104: =(V103+4000)*1.00566-(0.00125*(V103+4000)) -> 1596555.5 | W104: =(W103+4000)*1.00566-(0.00125*(W103+4000)) -> 1732523.3 | X104: =(X103+4000)*1.00566-(0.00125*(X103+4000)) -> 1875863.7 | Y104: =(Y103+4000)*1.00566-(0.00125*(Y103+4000)) -> 2026976.4 | Z104: =(Z103+4000)*1.00566-(0.00125*(Z103+4000)) -> 2186282.8 | AA104: =(AA103+4000)*1.00566-(0.00125*(AA103+4000)) -> 2354227.2 | AB104: =(AB103+4000)*1.00566-(0.00125*(AB103+4000)) -> 2531278 | ... AE104: =(AE103+4000)*1.00566-(0.00125*(AE103+4000)) -> 3122141.8 | AI104: =(AI103+4000)*1.00566-0 -> 45522.794 | AJ104: =(AJ103+4000)*1.00566-0 -> 98515.885 | AK104: =(AK103+4000)*1.00566-0 -> 155222.45 | AL104: =(AL103+4000)*1.00566-0 -> 215902.72 | AM104: =(AM103+4000)*1.00566-0 -> 280835.14 | AN104: =(AN103+4000)*1.00566-0 -> 350317.69 | AO104: =(AO103+4000)*1.00566-0 -> 424669.21 | AP104: =(AP103+4000)*1.00566-0 -> 504230.89 | ... BJ104: =(BJ103+4000)*1.00566-0 -> 3997312.2
D105: =(D104+4000)*1.00566-(0.00146*(D104+4000)) -> 49330.794 | E105: =(E104+4000)*1.00566-(0.00146*(E104+4000)) -> 101206.1 | F105: =(F104+4000)*1.00566-(0.00146*(F104+4000)) -> 155757.18 | G105: =(G104+4000)*1.00566-(0.00146*(G104+4000)) -> 213122.04 | H105: =(H104+4000)*1.00566-(0.00125*(H104+4000)) -> 273723.41 | I105: =(I104+4000)*1.00566-(0.00125*(I104+4000)) -> 337963.83 | J105: =(J104+4000)*1.00566-(0.00125*(J104+4000)) -> 405687.53 | K105: =(K104+4000)*1.00566-(0.00125*(K104+4000)) -> 477083.39 | L105: =(L104+4000)*1.00566-(0.00104*(L104+4000)) -> 553360.17 | M105: =(M104+4000)*1.00566-(0.00104*(M104+4000)) -> 634296.26 | N105: =(N104+4000)*1.00566-(0.00104*(N104+4000)) -> 719835.25 | O105: =(O104+4000)*1.00566-(0.00104*(O104+4000)) -> 810238.89 | P105: =(P104+4000)*1.00566-(0.00104*(P104+4000)) -> 905783.84 | Q105: =(Q104+4000)*1.00566-(0.000833*(Q104+4000)) -> 1006969.9 | R105: =(R104+4000)*1.00566-(0.000833*(R104+4000)) -> 1116404.4 | S105: =(S104+4000)*1.00566-(0.000833*(S104+4000)) -> 1232348.7 | T105: =(T104+4000)*1.00566-(0.000833*(T104+4000)) -> 1355190.2 | U105: =(U104+4000)*1.00566-(0.00125*(U104+4000)) -> 1478070.6 | V105: =(V104+4000)*1.00566-(0.00125*(V104+4000)) -> 1607613.9 | W105: =(W104+4000)*1.00566-(0.00125*(W104+4000)) -> 1744181.4 | X105: =(X104+4000)*1.00566-(0.00125*(X104+4000)) -> 1888153.9 | Y105: =(Y104+4000)*1.00566-(0.00125*(Y104+4000)) -> 2039933 | Z105: =(Z104+4000)*1.00566-(0.00125*(Z104+4000)) -> 2199941.9 | AA105: =(AA104+4000)*1.00566-(0.00125*(AA104+4000)) -> 2368627 | AB105: =(AB104+4000)*1.00566-(0.00125*(AB104+4000)) -> 2546458.6 | ... AE105: =(AE104+4000)*1.00566-(0.00125*(AE104+4000)) -> 3139928.1 | AI105: =(AI104+4000)*1.00566-0 -> 49803.093 | AJ105: =(AJ104+4000)*1.00566-0 -> 103096.12 | AK105: =(AK104+4000)*1.00566-0 -> 160123.65 | AL105: =(AL104+4000)*1.00566-0 -> 221147.37 | AM105: =(AM104+4000)*1.00566-0 -> 286447.31 | AN105: =(AN104+4000)*1.00566-0 -> 356323.13 | AO105: =(AO104+4000)*1.00566-0 -> 431095.48 | AP105: =(AP104+4000)*1.00566-0 -> 511107.48 | ... BJ105: =(BJ104+4000)*1.00566-0 -> 4023959.6
D108: Scenario 6 | AI108: Scenario 6 | AJ108: WITHOUT AN ADVISOR
D109: Assume 8% annual return on investments | AI109: Assume 8% annual return on investments
D110: Assume 4K/mo invested | AI110: Assume 4K/mo invested
...

Sheet 5K
A1: Cost of a Financial Advisor
A3: 0 - 250,000 | B3: 0.0175
A4: 250,000 - 500,000 | B4: 0.015 | D4: They calculate their fee based on the daily closing value of your account, averaged over each month x the monthly portion of your annual rate.
A5: 500,000 - 1,000,000 | B5: 0.0125 | D5: Ex. 1. If daily average closing value of my account is $12,000 and the monthly fee is 0.146% (1.75%/12) then my fee for the month is (12,000 * 0.00146) = $17.52
A6: 1,000,000 - 2,000,000 | B6: 0.01 | D6: Ex. 2. If the following month I have $16,000 in my account, the fee for that month is 16,000 x 0.00146 = 23.36
A7: 2,000,000 - 6,000,000 | B7: 0.01 | D7: Ex. 3. What is the cost of all of this? You might think it is 17.52 + 23.36 = $40.88. You would be wrong! You've also lost out on the interest you would have gained on that 17.52 and 23.36. And the compounded interest on that interest. And the compounded interest on the interest of the interest. You get the idea. So what does that actually look like in real numbers?
A8: 6,000,000+ | B8: 0.0075
D10: Scenario 1 | AI10: Scenario 1 | AJ10: WITHOUT AN ADVISOR
D11: Assume I don't invest anything. It just sits there in a cash account. What would be the raw dollar cost of the financial advisor. (i.e. lost opportunity of compounding not realised) | AI11: Assume I don't invest anything. It just sits there in a cash account. What would be the raw dollar cost of the financial advisor. (i.e. lost opportunity of compounding not realised)
D12: Assume I save $5K/mo | AI12: Assume I save $5K/mo
D13: Y1 | E13: Y2 | F13: Y3 | G13: Y4 | H13: Y5 | I13: Y6 | J13: Y7 | K13: Y8 | L13: Y9 | M13: Y10 | N13: Y11 | O13: Y12 | P13: Y13 | Q13: Y14 | R13: Y15 | S13: Y16 | T13: Y17 | U13: Y18 | V13: Y19 | W13: Y20 | X13: Y21 | Y13: Y22 | Z13: Y23 | AA13: Y24 | AB13: Y25 | AC13: Y26 | AD13: Y27 | AE13: Y28 | AI13: Y1 | AJ13: Y2 | AK13: Y3 | AL13: Y4 | AM13: Y5 | AN13: Y6 | AO13: Y7 | AP13: Y8 | AQ13: Y9 | AR13: Y10 | AS13: Y11 | AT13: Y12 | AU13: Y13 | AV13: Y14 | AW13: Y15 | AX13: Y16 | AY13: Y17 | AZ13: Y18 | BA13: Y19 | BB13: Y20 | BC13: Y21 | BD13: Y22 | BE13: Y23 | BF13: Y24 | BG13: Y25 | BH13: Y26 | BI13: Y27 | BJ13: Y28
D14: 0 | AI14: 0
C15: J | D15: =(D14+5000)-(0.00146*(D14+5000)) -> 4992.7 | E15: =(D26+5000)-(0.00146*(D26+5000)) -> 64339.564 | F15: =(E26+5000)-(0.00146*(E26+5000)) -> 122654.98 | G15: =(F26+5000)-(0.00146*(F26+5000)) -> 179956.87 | H15: =(G26+5000)-(0.00146*(G26+5000)) -> 236262.86 | I15: =(H26+5000)-(0.00125*(H26+5000)) -> 292156.94 | J15: =(I26+5000)-(0.00125*(I26+5000)) -> 347319.31 | K15: =(J26+5000)-(0.00125*(J26+5000)) -> 401659.92 | L15: =(K26+5000)-(0.00125*(K26+5000)) -> 455191 | M15: =(L26+5000)-(0.00104*(L26+5000)) -> 508137.17 | N15: =(M26+5000)-(0.00104*(M26+5000)) -> 561427.71 | O15: =(N26+5000)-(0.00104*(N26+5000)) -> 614056.98 | P15: =(O26+5000)-(0.00104*(O26+5000)) -> 666033.17 | Q15: =(P26+5000)-(0.00104*(P26+5000)) -> 717364.4 | R15: =(Q26+5000)-(0.00104*(Q26+5000)) -> 768058.67 | S15: =(R26+5000)-(0.00104*(R26+5000)) -> 818123.88 | T15: =(S26+5000)-(0.00104*(S26+5000)) -> 867567.83 | ... V15: =(U26+5000)-(0.00104*(U26+5000)) -> 964622.73 | W15: =(V26+5000)-(0.000833*(V26+5000)) -> 1013081.9 | X15: =(W26+5000)-(0.000833*(W26+5000)) -> 1062677.5 | Y15: =(X26+5000)-(0.000833*(X26+5000)) -> 1111779.6 | Z15: =(Y26+5000)-(0.000833*(Y26+5000)) -> 1160393.2 | AA15: =(Z26+5000)-(0.000833*(Z26+5000)) -> 1208523 | AB15: =(AA26+5000)-(0.000833*(AA26+5000)) -> 1256173.9 | AC15: =(AB26+5000)-(0.000833*(AB26+5000)) -> 1303350.7 | AD15: =(AC26+5000)-(0.000833*(AC26+5000)) -> 1350058 | AE15: =(AD26+5000)-(0.000833*(AD26+5000)) -> 1396300.6 | AH15: J | AI15: =(AI14+5000)-0 -> 5000 | AJ15: =(AI26+5000)-0 -> 65000 | AK15: =(AJ26+5000)-0 -> 125000 | AL15: =(AK26+5000)-0 -> 185000 | AM15: =(AL26+5000)-0 -> 245000 | AN15: =(AM26+5000)-0 -> 305000 | AO15: =(AN26+5000)-0 -> 365000 | AP15: =(AO26+5000)-0 -> 425000 | AQ15: =(AP26+5000)-0 -> 485000 | ... BJ15: =(BI26+5000)-0 -> 1625000
A16: =0.0175/12 -> 0.0014583333 | B16: 1.75 | C16: F | D16: =(D15+5000)-(0.00146*(D15+5000)) -> 9978.1107 | E16: =(E15+5000)-(0.00146*(E15+5000)) -> 69238.328 | F16: =(F15+5000)-(0.00146*(F15+5000)) -> 127468.6 | G16: =(G15+5000)-(0.00146*(G15+5000)) -> 184686.84 | H16: =(H15+5000)-(0.00146*(H15+5000)) -> 240910.62 | I16: =(I15+5000)-(0.00125*(I15+5000)) -> 296785.49 | J16: =(J15+5000)-(0.00125*(J15+5000)) -> 351878.91 | K16: =(K15+5000)-(0.00125*(K15+5000)) -> 406151.59 | L16: =(L15+5000)-(0.00125*(L15+5000)) -> 459615.76 | M16: =(M15+5000)-(0.00104*(M15+5000)) -> 512603.51 | N16: =(N15+5000)-(0.00104*(N15+5000)) -> 565838.63 | O16: =(O15+5000)-(0.00104*(O15+5000)) -> 618413.16 | P16: =(P15+5000)-(0.00104*(P15+5000)) -> 670335.3 | Q16: =(Q15+5000)-(0.00104*(Q15+5000)) -> 721613.14 | R16: =(R15+5000)-(0.00104*(R15+5000)) -> 772254.69 | S16: =(S15+5000)-(0.00104*(S15+5000)) -> 822267.83 | T16: =(T15+5000)-(0.00104*(T15+5000)) -> 871660.36 | ... V16: =(V15+5000)-(0.00104*(V15+5000)) -> 968614.32 | W16: =(W15+5000)-(0.000833*(W15+5000)) -> 1017233.8 | X16: =(X15+5000)-(0.000833*(X15+5000)) -> 1066788.1 | Y16: =(Y15+5000)-(0.000833*(Y15+5000)) -> 1115849.3 | Z16: =(Z15+5000)-(0.000833*(Z15+5000)) -> 1164422.4 | AA16: =(AA15+5000)-(0.000833*(AA15+5000)) -> 1212512.1 | AB16: =(AB15+5000)-(0.000833*(AB15+5000)) -> 1260123.4 | AC16: =(AC15+5000)-(0.000833*(AC15+5000)) -> 1307260.8 | AD16: =(AD15+5000)-(0.000833*(AD15+5000)) -> 1353929.3 | AE16: =(AE15+5000)-(0.000833*(AE15+5000)) -> 1400133.3 | AH16: F | AI16: =(AI15+5000)-0 -> 10000 | AJ16: =(AJ15+5000)-0 -> 70000 | AK16: =(AK15+5000)-0 -> 130000 | AL16: =(AL15+5000)-0 -> 190000 | AM16: =(AM15+5000)-0 -> 250000 | AN16: =(AN15+5000)-0 -> 310000 | AO16: =(AO15+5000)-0 -> 370000 | AP16: =(AP15+5000)-0 -> 430000 | ... BJ16: =(BJ15+5000)-0 -> 1630000
A17: =0.015/12 -> 0.00125 | B17: 1.5 | C17: M | D17: =(D16+5000)-(0.00146*(D16+5000)) -> 14956.243 | E17: =(E16+5000)-(0.00146*(E16+5000)) -> 74129.94 | F17: =(F16+5000)-(0.00146*(F16+5000)) -> 132275.2 | G17: =(G16+5000)-(0.00146*(G16+5000)) -> 189409.89 | H17: =(H16+5000)-(0.00146*(H16+5000)) -> 245551.59 | I17: =(I16+5000)-(0.00125*(I16+5000)) -> 301408.26 | J17: =(J16+5000)-(0.00125*(J16+5000)) -> 356432.82 | K17: =(K16+5000)-(0.00125*(K16+5000)) -> 410637.66 | L17: =(L16+5000)-(0.00125*(L16+5000)) -> 464034.99 | M17: =(M16+5000)-(0.00104*(M16+5000)) -> 517065.2 | N17: =(N16+5000)-(0.00104*(N16+5000)) -> 570244.96 | O17: =(O16+5000)-(0.00104*(O16+5000)) -> 622764.81 | P17: =(P16+5000)-(0.00104*(P16+5000)) -> 674632.95 | Q17: =(Q16+5000)-(0.00104*(Q16+5000)) -> 725857.46 | R17: =(R16+5000)-(0.00104*(R16+5000)) -> 776446.34 | S17: =(S16+5000)-(0.00104*(S16+5000)) -> 826407.47 | T17: =(T16+5000)-(0.00104*(T16+5000)) -> 875748.64 | ... V17: =(V16+5000)-(0.00104*(V16+5000)) -> 972601.77 | W17: =(W16+5000)-(0.000833*(W16+5000)) -> 1021382.3 | X17: =(X16+5000)-(0.000833*(X16+5000)) -> 1070895.3 | Y17: =(Y16+5000)-(0.000833*(Y16+5000)) -> 1119915.7 | Z17: =(Z16+5000)-(0.000833*(Z16+5000)) -> 1168448.3 | AA17: =(AA16+5000)-(0.000833*(AA16+5000)) -> 1216497.9 | AB17: =(AB16+5000)-(0.000833*(AB16+5000)) -> 1264069.5 | AC17: =(AC16+5000)-(0.000833*(AC16+5000)) -> 1311167.7 | AD17: =(AD16+5000)-(0.000833*(AD16+5000)) -> 1357797.3 | AE17: =(AE16+5000)-(0.000833*(AE16+5000)) -> 1403962.9 | AH17: M | AI17: =(AI16+5000)-0 -> 15000 | AJ17: =(AJ16+5000)-0 -> 75000 | AK17: =(AK16+5000)-0 -> 135000 | AL17: =(AL16+5000)-0 -> 195000 | AM17: =(AM16+5000)-0 -> 255000 | AN17: =(AN16+5000)-0 -> 315000 | AO17: =(AO16+5000)-0 -> 375000 | AP17: =(AP16+5000)-0 -> 435000 | ... BJ17: =(BJ16+5000)-0 -> 1635000
A18: =0.0125/12 -> 0.0010416667 | B18: 1.25 | C18: A | D18: =(D17+5000)-(0.00146*(D17+5000)) -> 19927.107 | E18: =(E17+5000)-(0.00146*(E17+5000)) -> 79014.411 | F18: =(F17+5000)-(0.00146*(F17+5000)) -> 137074.78 | G18: =(G17+5000)-(0.00146*(G17+5000)) -> 194126.06 | H18: =(H17+5000)-(0.00125*(H17+5000)) -> 250238.4 | I18: =(I17+5000)-(0.00125*(I17+5000)) -> 306025.25 | J18: =(J17+5000)-(0.00125*(J17+5000)) -> 360981.02 | K18: =(K17+5000)-(0.00125*(K17+5000)) -> 415118.11 | L18: =(L17+5000)-(0.00125*(L17+5000)) -> 468448.69 | M18: =(M17+5000)-(0.00104*(M17+5000)) -> 521522.26 | N18: =(N17+5000)-(0.00104*(N17+5000)) -> 574646.7 | O18: =(O17+5000)-(0.00104*(O17+5000)) -> 627111.93 | P18: =(P17+5000)-(0.00104*(P17+5000)) -> 678926.13 | Q18: =(Q17+5000)-(0.00104*(Q17+5000)) -> 730097.37 | R18: =(R17+5000)-(0.00104*(R17+5000)) -> 780633.64 | S18: =(S17+5000)-(0.00104*(S17+5000)) -> 830542.81 | T18: =(T17+5000)-(0.00104*(T17+5000)) -> 879832.66 | ... V18: =(V17+5000)-(0.00104*(V17+5000)) -> 976585.06 | W18: =(W17+5000)-(0.000833*(W17+5000)) -> 1025527.3 | X18: =(X17+5000)-(0.000833*(X17+5000)) -> 1074999.1 | Y18: =(Y17+5000)-(0.000833*(Y17+5000)) -> 1123978.6 | Z18: =(Z17+5000)-(0.000833*(Z17+5000)) -> 1172470.8 | AA18: =(AA17+5000)-(0.000833*(AA17+5000)) -> 1220480.4 | AB18: =(AB17+5000)-(0.000833*(AB17+5000)) -> 1268012.4 | AC18: =(AC17+5000)-(0.000833*(AC17+5000)) -> 1315071.3 | AD18: =(AD17+5000)-(0.000833*(AD17+5000)) -> 1361662.1 | AE18: =(AE17+5000)-(0.000833*(AE17+5000)) -> 1407789.2 | AH18: A | AI18: =(AI17+5000)-0 -> 20000 | AJ18: =(AJ17+5000)-0 -> 80000 | AK18: =(AK17+5000)-0 -> 140000 | AL18: =(AL17+5000)-0 -> 200000 | AM18: =(AM17+5000)-0 -> 260000 | AN18: =(AN17+5000)-0 -> 320000 | AO18: =(AO17+5000)-0 -> 380000 | AP18: =(AP17+5000)-0 -> 440000 | ... BJ18: =(BJ17+5000)-0 -> 1640000
A19: =0.01/12 -> 0.00083333333 | B19: 1 | C19: M | D19: =(D18+5000)-(0.00146*(D18+5000)) -> 24890.713 | E19: =(E18+5000)-(0.00146*(E18+5000)) -> 83891.75 | F19: =(F18+5000)-(0.00146*(F18+5000)) -> 141867.35 | G19: =(G18+5000)-(0.00146*(G18+5000)) -> 198835.33 | H19: =(H18+5000)-(0.00125*(H18+5000)) -> 254919.35 | I19: =(I18+5000)-(0.00125*(I18+5000)) -> 310636.47 | J19: =(J18+5000)-(0.00125*(J18+5000)) -> 365523.55 | K19: =(K18+5000)-(0.00125*(K18+5000)) -> 419592.96 | L19: =(L18+5000)-(0.00125*(L18+5000)) -> 472856.88 | M19: =(M18+5000)-(0.00104*(M18+5000)) -> 525974.67 | N19: =(N18+5000)-(0.00104*(N18+5000)) -> 579043.87 | O19: =(O18+5000)-(0.00104*(O18+5000)) -> 631454.54 | P19: =(P18+5000)-(0.00104*(P18+5000)) -> 683214.85 | Q19: =(Q18+5000)-(0.00104*(Q18+5000)) -> 734332.87 | R19: =(R18+5000)-(0.00104*(R18+5000)) -> 784816.58 | S19: =(S18+5000)-(0.00104*(S18+5000)) -> 834673.84 | T19: =(T18+5000)-(0.00104*(T18+5000)) -> 883912.43 | ... V19: =(V18+5000)-(0.00104*(V18+5000)) -> 980564.21 | W19: =(W18+5000)-(0.000833*(W18+5000)) -> 1029668.9 | X19: =(X18+5000)-(0.000833*(X18+5000)) -> 1079099.5 | Y19: =(Y18+5000)-(0.000833*(Y18+5000)) -> 1128038.2 | Z19: =(Z18+5000)-(0.000833*(Z18+5000)) -> 1176489.9 | AA19: =(AA18+5000)-(0.000833*(AA18+5000)) -> 1224459.6 | AB19: =(AB18+5000)-(0.000833*(AB18+5000)) -> 1271951.9 | AC19: =(AC18+5000)-(0.000833*(AC18+5000)) -> 1318971.7 | AD19: =(AD18+5000)-(0.000833*(AD18+5000)) -> 1365523.6 | AE19: =(AE18+5000)-(0.000833*(AE18+5000)) -> 1411612.4 | AH19: M | AI19: =(AI18+5000)-0 -> 25000 | AJ19: =(AJ18+5000)-0 -> 85000 | AK19: =(AK18+5000)-0 -> 145000 | AL19: =(AL18+5000)-0 -> 205000 | AM19: =(AM18+5000)-0 -> 265000 | AN19: =(AN18+5000)-0 -> 325000 | AO19: =(AO18+5000)-0 -> 385000 | AP19: =(AP18+5000)-0 -> 445000 | ... BJ19: =(BJ18+5000)-0 -> 1645000
C20: J | D20: =(D19+5000)-(0.00146*(D19+5000)) -> 29847.072 | E20: =(E19+5000)-(0.00146*(E19+5000)) -> 88761.968 | F20: =(F19+5000)-(0.00146*(F19+5000)) -> 146652.92 | G20: =(G19+5000)-(0.00146*(G19+5000)) -> 203537.73 | H20: =(H19+5000)-(0.00125*(H19+5000)) -> 259594.45 | I20: =(I19+5000)-(0.00125*(I19+5000)) -> 315241.92 | J20: =(J19+5000)-(0.00125*(J19+5000)) -> 370060.39 | K20: =(K19+5000)-(0.00125*(K19+5000)) -> 424062.22 | L20: =(L19+5000)-(0.00125*(L19+5000)) -> 477259.56 | M20: =(M19+5000)-(0.00104*(M19+5000)) -> 530422.46 | N20: =(N19+5000)-(0.00104*(N19+5000)) -> 583436.46 | O20: =(O19+5000)-(0.00104*(O19+5000)) -> 635792.62 | P20: =(P19+5000)-(0.00104*(P19+5000)) -> 687499.1 | Q20: =(Q19+5000)-(0.00104*(Q19+5000)) -> 738563.97 | R20: =(R19+5000)-(0.00104*(R19+5000)) -> 788995.17 | S20: =(S19+5000)-(0.00104*(S19+5000)) -> 838800.58 | T20: =(T19+5000)-(0.00104*(T19+5000)) -> 887987.96 | ... V20: =(V19+5000)-(0.00104*(V19+5000)) -> 984539.22 | W20: =(W19+5000)-(0.000833*(W19+5000)) -> 1033807 | X20: =(X19+5000)-(0.000833*(X19+5000)) -> 1083196.4 | Y20: =(Y19+5000)-(0.000833*(Y19+5000)) -> 1132094.4 | Z20: =(Z19+5000)-(0.000833*(Z19+5000)) -> 1180505.8 | AA20: =(AA19+5000)-(0.000833*(AA19+5000)) -> 1228435.5 | AB20: =(AB19+5000)-(0.000833*(AB19+5000)) -> 1275888.2 | AC20: =(AC19+5000)-(0.000833*(AC19+5000)) -> 1322868.9 | AD20: =(AD19+5000)-(0.000833*(AD19+5000)) -> 1369382 | AE20: =(AE19+5000)-(0.000833*(AE19+5000)) -> 1415432.3 | AH20: J | AI20: =(AI19+5000)-0 -> 30000 | AJ20: =(AJ19+5000)-0 -> 90000 | AK20: =(AK19+5000)-0 -> 150000 | AL20: =(AL19+5000)-0 -> 210000 | AM20: =(AM19+5000)-0 -> 270000 | AN20: =(AN19+5000)-0 -> 330000 | AO20: =(AO19+5000)-0 -> 390000 | AP20: =(AP19+5000)-0 -> 450000 | ... BJ20: =(BJ19+5000)-0 -> 1650000
C21: J | D21: =(D20+5000)-(0.00146*(D20+5000)) -> 34796.196 | E21: =(E20+5000)-(0.00146*(E20+5000)) -> 93625.075 | F21: =(F20+5000)-(0.00146*(F20+5000)) -> 151431.51 | G21: =(G20+5000)-(0.00146*(G20+5000)) -> 208233.27 | H21: =(H20+5000)-(0.00125*(H20+5000)) -> 264263.71 | I21: =(I20+5000)-(0.00125*(I20+5000)) -> 319841.62 | J21: =(J20+5000)-(0.00125*(J20+5000)) -> 374591.57 | K21: =(K20+5000)-(0.00125*(K20+5000)) -> 428525.89 | L21: =(L20+5000)-(0.00125*(L20+5000)) -> 481656.74 | M21: =(M20+5000)-(0.00104*(M20+5000)) -> 534865.62 | N21: =(N20+5000)-(0.00104*(N20+5000)) -> 587824.49 | O21: =(O20+5000)-(0.00104*(O20+5000)) -> 640126.2 | P21: =(P20+5000)-(0.00104*(P20+5000)) -> 691778.9 | Q21: =(Q20+5000)-(0.00104*(Q20+5000)) -> 742790.66 | R21: =(R20+5000)-(0.00104*(R20+5000)) -> 793169.42 | S21: =(S20+5000)-(0.00104*(S20+5000)) -> 842923.03 | T21: =(T20+5000)-(0.00104*(T20+5000)) -> 892059.26 | ... V21: =(V20+5000)-(0.00104*(V20+5000)) -> 988510.1 | W21: =(W20+5000)-(0.000833*(W20+5000)) -> 1037941.7 | X21: =(X20+5000)-(0.000833*(X20+5000)) -> 1087289.9 | Y21: =(Y20+5000)-(0.000833*(Y20+5000)) -> 1136147.2 | Z21: =(Z20+5000)-(0.000833*(Z20+5000)) -> 1184518.2 | AA21: =(AA20+5000)-(0.000833*(AA20+5000)) -> 1232408 | AB21: =(AB20+5000)-(0.000833*(AB20+5000)) -> 1279821.3 | AC21: =(AC20+5000)-(0.000833*(AC20+5000)) -> 1326762.7 | AD21: =(AD20+5000)-(0.000833*(AD20+5000)) -> 1373237.1 | AE21: =(AE20+5000)-(0.000833*(AE20+5000)) -> 1419249.1 | AH21: J | AI21: =(AI20+5000)-0 -> 35000 | AJ21: =(AJ20+5000)-0 -> 95000 | AK21: =(AK20+5000)-0 -> 155000 | AL21: =(AL20+5000)-0 -> 215000 | AM21: =(AM20+5000)-0 -> 275000 | AN21: =(AN20+5000)-0 -> 335000 | AO21: =(AO20+5000)-0 -> 395000 | AP21: =(AP20+5000)-0 -> 455000 | ... BJ21: =(BJ20+5000)-0 -> 1655000
C22: A | D22: =(D21+5000)-(0.00146*(D21+5000)) -> 39738.093 | E22: =(E21+5000)-(0.00146*(E21+5000)) -> 98481.082 | F22: =(F21+5000)-(0.00146*(F21+5000)) -> 156203.12 | G22: =(G21+5000)-(0.00146*(G21+5000)) -> 212921.95 | H22: =(H21+5000)-(0.00125*(H21+5000)) -> 268927.13 | I22: =(I21+5000)-(0.00125*(I21+5000)) -> 324435.57 | J22: =(J21+5000)-(0.00125*(J21+5000)) -> 379117.08 | K22: =(K21+5000)-(0.00125*(K21+5000)) -> 432983.98 | L22: =(L21+5000)-(0.00125*(L21+5000)) -> 486048.42 | M22: =(M21+5000)-(0.00104*(M21+5000)) -> 539304.16 | N22: =(N21+5000)-(0.00104*(N21+5000)) -> 592207.95 | O22: =(O21+5000)-(0.00104*(O21+5000)) -> 644455.27 | P22: =(P21+5000)-(0.00104*(P21+5000)) -> 696054.25 | Q22: =(Q21+5000)-(0.00104*(Q21+5000)) -> 747012.96 | R22: =(R21+5000)-(0.00104*(R21+5000)) -> 797339.32 | S22: =(S21+5000)-(0.00104*(S21+5000)) -> 847041.19 | T22: =(T21+5000)-(0.00104*(T21+5000)) -> 896126.31 | ... V22: =(V21+5000)-(0.00104*(V21+5000)) -> 992476.85 | W22: =(W21+5000)-(0.000833*(W21+5000)) -> 1042072.9 | X22: =(X21+5000)-(0.000833*(X21+5000)) -> 1091380.1 | Y22: =(Y21+5000)-(0.000833*(Y21+5000)) -> 1140196.6 | Z22: =(Z21+5000)-(0.000833*(Z21+5000)) -> 1188527.4 | AA22: =(AA21+5000)-(0.000833*(AA21+5000)) -> 1236377.3 | AB22: =(AB21+5000)-(0.000833*(AB21+5000)) -> 1283751 | AC22: =(AC21+5000)-(0.000833*(AC21+5000)) -> 1330653.4 | AD22: =(AD21+5000)-(0.000833*(AD21+5000)) -> 1377089.1 | AE22: =(AE21+5000)-(0.000833*(AE21+5000)) -> 1423062.7 | AH22: A | AI22: =(AI21+5000)-0 -> 40000 | AJ22: =(AJ21+5000)-0 -> 100000 | AK22: =(AK21+5000)-0 -> 160000 | AL22: =(AL21+5000)-0 -> 220000 | AM22: =(AM21+5000)-0 -> 280000 | AN22: =(AN21+5000)-0 -> 340000 | AO22: =(AO21+5000)-0 -> 400000 | AP22: =(AP21+5000)-0 -> 460000 | ... BJ22: =(BJ21+5000)-0 -> 1660000
C23: S | D23: =(D22+5000)-(0.00146*(D22+5000)) -> 44672.776 | E23: =(E22+5000)-(0.00146*(E22+5000)) -> 103330 | F23: =(F22+5000)-(0.00146*(F22+5000)) -> 160967.76 | G23: =(G22+5000)-(0.00146*(G22+5000)) -> 217603.78 | H23: =(H22+5000)-(0.00125*(H22+5000)) -> 273584.72 | I23: =(I22+5000)-(0.00125*(I22+5000)) -> 329023.77 | J23: =(J22+5000)-(0.00125*(J22+5000)) -> 383636.93 | K23: =(K22+5000)-(0.00125*(K22+5000)) -> 437436.5 | L23: =(L22+5000)-(0.00125*(L22+5000)) -> 490434.61 | M23: =(M22+5000)-(0.00104*(M22+5000)) -> 543738.08 | N23: =(N22+5000)-(0.00104*(N22+5000)) -> 596586.86 | O23: =(O22+5000)-(0.00104*(O22+5000)) -> 648779.83 | P23: =(P22+5000)-(0.00104*(P22+5000)) -> 700325.16 | Q23: =(Q22+5000)-(0.00104*(Q22+5000)) -> 751230.86 | R23: =(R22+5000)-(0.00104*(R22+5000)) -> 801504.89 | S23: =(S22+5000)-(0.00104*(S22+5000)) -> 851155.07 | T23: =(T22+5000)-(0.00104*(T22+5000)) -> 900189.14 | ... V23: =(V22+5000)-(0.00104*(V22+5000)) -> 996439.48 | W23: =(W22+5000)-(0.000833*(W22+5000)) -> 1046200.7 | X23: =(X22+5000)-(0.000833*(X22+5000)) -> 1095466.8 | Y23: =(Y22+5000)-(0.000833*(Y22+5000)) -> 1144242.6 | Z23: =(Z22+5000)-(0.000833*(Z22+5000)) -> 1192533.2 | AA23: =(AA22+5000)-(0.000833*(AA22+5000)) -> 1240343.2 | AB23: =(AB22+5000)-(0.000833*(AB22+5000)) -> 1287677.5 | AC23: =(AC22+5000)-(0.000833*(AC22+5000)) -> 1334540.8 | AD23: =(AD22+5000)-(0.000833*(AD22+5000)) -> 1380937.8 | AE23: =(AE22+5000)-(0.000833*(AE22+5000)) -> 1426873.1 | AH23: S | AI23: =(AI22+5000)-0 -> 45000 | AJ23: =(AJ22+5000)-0 -> 105000 | AK23: =(AK22+5000)-0 -> 165000 | AL23: =(AL22+5000)-0 -> 225000 | AM23: =(AM22+5000)-0 -> 285000 | AN23: =(AN22+5000)-0 -> 345000 | AO23: =(AO22+5000)-0 -> 405000 | AP23: =(AP22+5000)-0 -> 465000 | ... BJ23: =(BJ22+5000)-0 -> 1665000
C24: O | D24: =(D23+5000)-(0.00146*(D23+5000)) -> 49600.253 | E24: =(E23+5000)-(0.00146*(E23+5000)) -> 108171.84 | F24: =(F23+5000)-(0.00146*(F23+5000)) -> 165725.45 | G24: =(G23+5000)-(0.00146*(G23+5000)) -> 222278.78 | H24: =(H23+5000)-(0.00125*(H23+5000)) -> 278236.49 | I24: =(I23+5000)-(0.00125*(I23+5000)) -> 333606.24 | J24: =(J23+5000)-(0.00125*(J23+5000)) -> 388151.14 | K24: =(K23+5000)-(0.00125*(K23+5000)) -> 441883.46 | L24: =(L23+5000)-(0.00125*(L23+5000)) -> 494815.31 | M24: =(M23+5000)-(0.00104*(M23+5000)) -> 548167.4 | N24: =(N23+5000)-(0.00104*(N23+5000)) -> 600961.2 | O24: =(O23+5000)-(0.00104*(O23+5000)) -> 653099.9 | P24: =(P23+5000)-(0.00104*(P23+5000)) -> 704591.62 | Q24: =(Q23+5000)-(0.00104*(Q23+5000)) -> 755444.38 | R24: =(R23+5000)-(0.00104*(R23+5000)) -> 805666.12 | S24: =(S23+5000)-(0.00104*(S23+5000)) -> 855264.66 | T24: =(T23+5000)-(0.00104*(T23+5000)) -> 904247.75 | U24: =(U23+5000)-(0.00104*(U23+5000)) -> 952623 | V24: =(V23+5000)-(0.000833*(V23+5000)) -> 1000605.3 | W24: =(W23+5000)-(0.000833*(W23+5000)) -> 1050325 | X24: =(X23+5000)-(0.000833*(X23+5000)) -> 1099550.1 | Y24: =(Y23+5000)-(0.000833*(Y23+5000)) -> 1148285.3 | Z24: =(Z23+5000)-(0.000833*(Z23+5000)) -> 1196535.6 | AA24: =(AA23+5000)-(0.000833*(AA23+5000)) -> 1244305.8 | AB24: =(AB23+5000)-(0.000833*(AB23+5000)) -> 1291600.7 | AC24: =(AC23+5000)-(0.000833*(AC23+5000)) -> 1338424.9 | ... AE24: =(AE23+5000)-(0.000833*(AE23+5000)) -> 1430680.4 | AH24: O | AI24: =(AI23+5000)-0 -> 50000 | AJ24: =(AJ23+5000)-0 -> 110000 | AK24: =(AK23+5000)-0 -> 170000 | AL24: =(AL23+5000)-0 -> 230000 | AM24: =(AM23+5000)-0 -> 290000 | AN24: =(AN23+5000)-0 -> 350000 | AO24: =(AO23+5000)-0 -> 410000 | AP24: =(AP23+5000)-0 -> 470000 | ... BJ24: =(BJ23+5000)-0 -> 1670000
C25: N | D25: =(D24+5000)-(0.00146*(D24+5000)) -> 54520.537 | E25: =(E24+5000)-(0.00146*(E24+5000)) -> 113006.61 | F25: =(F24+5000)-(0.00146*(F24+5000)) -> 170476.19 | G25: =(G24+5000)-(0.00146*(G24+5000)) -> 226946.95 | H25: =(H24+5000)-(0.00125*(H24+5000)) -> 282882.44 | I25: =(I24+5000)-(0.00125*(I24+5000)) -> 338182.98 | J25: =(J24+5000)-(0.00125*(J24+5000)) -> 392659.7 | K25: =(K24+5000)-(0.00125*(K24+5000)) -> 446324.85 | L25: =(L24+5000)-(0.00125*(L24+5000)) -> 499190.54 | M25: =(M24+5000)-(0.00104*(M24+5000)) -> 552592.1 | N25: =(N24+5000)-(0.00104*(N24+5000)) -> 605331.01 | O25: =(O24+5000)-(0.00104*(O24+5000)) -> 657415.48 | P25: =(P24+5000)-(0.00104*(P24+5000)) -> 708853.64 | Q25: =(Q24+5000)-(0.00104*(Q24+5000)) -> 759653.52 | R25: =(R24+5000)-(0.00104*(R24+5000)) -> 809823.03 | S25: =(S24+5000)-(0.00104*(S24+5000)) -> 859369.99 | T25: =(T24+5000)-(0.00104*(T24+5000)) -> 908302.13 | U25: =(U24+5000)-(0.00104*(U24+5000)) -> 956627.08 | V25: =(V24+5000)-(0.000833*(V24+5000)) -> 1004767.6 | W25: =(W24+5000)-(0.000833*(W24+5000)) -> 1054446 | X25: =(X24+5000)-(0.000833*(X24+5000)) -> 1103630 | Y25: =(Y24+5000)-(0.000833*(Y24+5000)) -> 1152324.6 | Z25: =(Z24+5000)-(0.000833*(Z24+5000)) -> 1200534.7 | AA25: =(AA24+5000)-(0.000833*(AA24+5000)) -> 1248265.1 | AB25: =(AB24+5000)-(0.000833*(AB24+5000)) -> 1295520.6 | AC25: =(AC24+5000)-(0.000833*(AC24+5000)) -> 1342305.9 | ... AE25: =(AE24+5000)-(0.000833*(AE24+5000)) -> 1434484.4 | AH25: N | AI25: =(AI24+5000)-0 -> 55000 | AJ25: =(AJ24+5000)-0 -> 115000 | AK25: =(AK24+5000)-0 -> 175000 | AL25: =(AL24+5000)-0 -> 235000 | AM25: =(AM24+5000)-0 -> 295000 | AN25: =(AN24+5000)-0 -> 355000 | AO25: =(AO24+5000)-0 -> 415000 | AP25: =(AP24+5000)-0 -> 475000 | ... BJ25: =(BJ24+5000)-0 -> 1675000
C26: D | D26: =(D25+5000)-(0.00146*(D25+5000)) -> 59433.637 | E26: =(E25+5000)-(0.00146*(E25+5000)) -> 117834.32 | F26: =(F25+5000)-(0.00146*(F25+5000)) -> 175219.99 | G26: =(G25+5000)-(0.00146*(G25+5000)) -> 231608.31 | H26: =(H25+5000)-(0.00125*(H25+5000)) -> 287522.59 | I26: =(I25+5000)-(0.00125*(I25+5000)) -> 342754.01 | J26: =(J25+5000)-(0.00125*(J25+5000)) -> 397162.62 | K26: =(K25+5000)-(0.00125*(K25+5000)) -> 450760.7 | L26: =(L25+5000)-(0.00104*(L25+5000)) -> 503666.19 | M26: =(M25+5000)-(0.00104*(M25+5000)) -> 557012.21 | N26: =(N25+5000)-(0.00104*(N25+5000)) -> 609696.26 | O26: =(O25+5000)-(0.00104*(O25+5000)) -> 661726.57 | P26: =(P25+5000)-(0.00104*(P25+5000)) -> 713111.24 | Q26: =(Q25+5000)-(0.00104*(Q25+5000)) -> 763858.28 | R26: =(R25+5000)-(0.00104*(R25+5000)) -> 813975.61 | S26: =(S25+5000)-(0.00104*(S25+5000)) -> 863471.04 | ... U26: =(U25+5000)-(0.00104*(U25+5000)) -> 960626.98 | V26: =(V25+5000)-(0.000833*(V25+5000)) -> 1008926.5 | W26: =(W25+5000)-(0.000833*(W25+5000)) -> 1058563.4 | X26: =(X25+5000)-(0.000833*(X25+5000)) -> 1107706.5 | Y26: =(Y25+5000)-(0.000833*(Y25+5000)) -> 1156360.6 | Z26: =(Z25+5000)-(0.000833*(Z25+5000)) -> 1204530.5 | AA26: =(AA25+5000)-(0.000833*(AA25+5000)) -> 1252221.2 | AB26: =(AB25+5000)-(0.000833*(AB25+5000)) -> 1299437.3 | AC26: =(AC25+5000)-(0.000833*(AC25+5000)) -> 1346183.6 | ... AE26: =(AE25+5000)-(0.000833*(AE25+5000)) -> 1438285.4 | AH26: D | AI26: =(AI25+5000)-0 -> 60000 | AJ26: =(AJ25+5000)-0 -> 120000 | AK26: =(AK25+5000)-0 -> 180000 | AL26: =(AL25+5000)-0 -> 240000 | AM26: =(AM25+5000)-0 -> 300000 | AN26: =(AN25+5000)-0 -> 360000 | AO26: =(AO25+5000)-0 -> 420000 | AP26: =(AP25+5000)-0 -> 480000 | ... BJ26: =(BJ25+5000)-0 -> 1680000
AA28: After saving $5K/mo x 25 yrs you should have: | AB28: =5000*12*25 -> 1500000 | BF28: After saving $5K/mo x 25 yrs you should have: | BG28: =6000*12*25 -> 1800000
AA29: You actually have: | AB29: =AF26 -> 0 | BF29: You actually have: | BG29: =BK26 -> 0
AA30: Your advisor cost you: | AB30: =AB28-AB29 -> 1500000 | BF30: Your advisor cost you: | BG30: =BG28-BG29 -> 1800000
AA31: Avg cost/year: | AB31: =AB30/12 -> 125000 | BF31: Because you are your own advisor! | BG31: =BG30/12 -> 150000
D32: Scenario 2 | AI32: Scenario 2 | AJ32: WITHOUT AN ADVISOR
D33: Assume 4% annual return on investments | AI33: Assume 4% annual return on investments
D34: Assume 5K/mo invested | AI34: Assume 5K/mo invested
D35: Y1 | E35: Y2 | F35: Y3 | G35: Y4 | H35: Y5 | I35: Y6 | J35: Y7 | K35: Y8 | L35: Y9 | M35: Y10 | N35: Y11 | O35: Y12 | P35: Y13 | Q35: Y14 | R35: Y15 | S35: Y16 | T35: Y17 | U35: Y18 | V35: Y19 | W35: Y20 | X35: Y21 | Y35: Y22 | Z35: Y23 | AA35: Y24 | AB35: Y25 | AC35: Y26 | AD35: Y27 | AE35: Y28 | AI35: Y1 | AJ35: Y2 | AK35: Y3 | AL35: Y4 | AM35: Y5 | AN35: Y6 | AO35: Y7 | AP35: Y8 | AQ35: Y9 | AR35: Y10 | AS35: Y11 | AT35: Y12 | AU35: Y13 | AV35: Y14 | AW35: Y15 | AX35: Y16 | AY35: Y17 | AZ35: Y18 | BA35: Y19 | BB35: Y20 | BC35: Y21 | BD35: Y22 | BE35: Y23 | BF35: Y24 | BG35: Y25 | BH35: Y26 | BI35: Y27 | BJ35: Y28
D36: 0 | AI36: 0
D37: =(D36+5000)*1.00328-(0.00146*(D36+5000)) -> 5009.1 | E37: =(D48+5000)*1.00328-(0.00146*(D48+5000)) -> 65834.159 | F37: =(E48+5000)*1.00328-(0.00146*(E48+5000)) -> 128001.02 | G37: =(F48+5000)*1.00328-(0.00146*(F48+5000)) -> 191539.27 | H37: =(G48+5000)*1.00328-(0.00125*(G48+5000)) -> 256585.66 | I37: =(H48+5000)*1.00328-(0.00125*(H48+5000)) -> 323703.97 | J37: =(I48+5000)*1.00328-(0.00125*(I48+5000)) -> 392475.66 | K37: =(J48+5000)*1.00328-(0.00125*(J48+5000)) -> 462941.46 | L37: =(K48+5000)*1.00328-(0.00104*(K48+5000)) -> 535800.57 | M37: =(L48+5000)*1.00328-(0.00125*(L48+5000)) -> 611134.39 | N37: =(M48+5000)*1.00328-(0.00104*(M48+5000)) -> 688380.13 | O37: =(N48+5000)*1.00328-(0.00104*(N48+5000)) -> 767994.28 | P37: =(O48+5000)*1.00328-(0.00104*(O48+5000)) -> 849775.02 | Q37: =(P48+5000)*1.00328-(0.00104*(P48+5000)) -> 933781.32 | R37: =(Q48+5000)*1.00328-(0.000833*(Q48+5000)) -> 1020702.8 | S37: =(R48+5000)*1.00328-(0.000833*(R48+5000)) -> 1112044.3 | T37: =(S48+5000)*1.00328-(0.000833*(S48+5000)) -> 1206104.4 | U37: =(T48+5000)*1.00328-(0.00125*(T48+5000)) -> 1302422 | V37: =(U48+5000)*1.00328-(0.00125*(U48+5000)) -> 1395303.2 | W37: =(V48+5000)*1.00328-(0.00125*(V48+5000)) -> 1490472.5 | X37: =(W48+5000)*1.00328-(0.00125*(W48+5000)) -> 1587986.2 | Y37: =(X48+5000)*1.00328-(0.00125*(X48+5000)) -> 1687902 | Z37: =(Y48+5000)*1.00328-(0.00125*(Y48+5000)) -> 1790279.1 | AA37: =(Z48+5000)*1.00328-(0.00125*(Z48+5000)) -> 1895178.2 | AB37: =(AA48+5000)*1.00328-(0.00125*(AA48+5000)) -> 2002661.3 | ... AE37: =(AD48+5000)*1.00328-(0.00125*(AD48+5000)) -> 2341259.5 | AI37: =(AI36+5000)*1.00328-0 -> 5016.4 | AJ37: =(AI48+5000)*1.00328-0 -> 66512.158 | AK37: =(AJ48+5000)*1.00328-0 -> 130472.54 | AL37: =(AK48+5000)*1.00328-0 -> 196996.31 | AM37: =(AL48+5000)*1.00328-0 -> 266186.21 | AN37: =(AM48+5000)*1.00328-0 -> 338149.1 | AO37: =(AN48+5000)*1.00328-0 -> 412996.11 | AP37: =(AO48+5000)*1.00328-0 -> 490842.83 | AQ37: =(AP48+5000)*1.00328-0 -> 571809.48 | ... BJ37: =(BI48+5000)*1.00328-0 -> 2903823.2
D38: =(D37+5000)*1.00328-(0.00146*(D37+5000)) -> 10027.317 | E38: =(E37+5000)*1.00328-(0.00146*(E37+5000)) -> 70963.077 | F38: =(F37+5000)*1.00328-(0.00146*(F37+5000)) -> 133243.08 | G38: =(G37+5000)*1.00328-(0.00146*(G37+5000)) -> 196896.97 | H38: =(H37+5000)*1.00328-(0.00125*(H37+5000)) -> 262116.68 | I38: =(I37+5000)*1.00328-(0.00125*(I37+5000)) -> 329371.24 | J38: =(J37+5000)*1.00328-(0.00125*(J37+5000)) -> 398282.54 | K38: =(K37+5000)*1.00328-(0.00125*(K37+5000)) -> 468891.38 | L38: =(L37+5000)*1.00328-(0.00104*(L37+5000)) -> 542011.96 | M38: =(M37+5000)*1.00328-(0.00125*(M37+5000)) -> 617385.15 | N38: =(N37+5000)*1.00328-(0.00104*(N37+5000)) -> 694933.31 | O38: =(O37+5000)*1.00328-(0.00104*(O37+5000)) -> 774725.79 | P38: =(P37+5000)*1.00328-(0.00104*(P37+5000)) -> 856689.72 | Q38: =(Q37+5000)*1.00328-(0.00104*(Q37+5000)) -> 940884.19 | R38: =(R37+5000)*1.00328-(0.000833*(R37+5000)) -> 1028212.7 | S38: =(S37+5000)*1.00328-(0.000833*(S37+5000)) -> 1119777.8 | T38: =(T37+5000)*1.00328-(0.000833*(T37+5000)) -> 1214068 | U38: =(U37+5000)*1.00328-(0.00125*(U37+5000)) -> 1310076.1 | V38: =(V37+5000)*1.00328-(0.00125*(V37+5000)) -> 1403145.9 | W38: =(W37+5000)*1.00328-(0.00125*(W37+5000)) -> 1498508.3 | X38: =(X37+5000)*1.00328-(0.00125*(X37+5000)) -> 1596220 | Y38: =(Y37+5000)*1.00328-(0.00125*(Y37+5000)) -> 1696338.6 | Z38: =(Z37+5000)*1.00328-(0.00125*(Z37+5000)) -> 1798923.5 | AA38: =(AA37+5000)*1.00328-(0.00125*(AA37+5000)) -> 1904035.5 | AB38: =(AB37+5000)*1.00328-(0.00125*(AB37+5000)) -> 2011736.8 | ... AE38: =(AE37+5000)*1.00328-(0.00125*(AE37+5000)) -> 2351022.4 | AI38: =(AI37+5000)*1.00328-0 -> 10049.254 | AJ38: =(AJ37+5000)*1.00328-0 -> 71746.718 | AK38: =(AK37+5000)*1.00328-0 -> 135916.89 | AL38: =(AL37+5000)*1.00328-0 -> 202658.86 | AM38: =(AM37+5000)*1.00328-0 -> 272075.7 | AN38: =(AN37+5000)*1.00328-0 -> 344274.63 | AO38: =(AO37+5000)*1.00328-0 -> 419367.14 | AP38: =(AP37+5000)*1.00328-0 -> 497469.19 | ... BJ38: =(BJ37+5000)*1.00328-0 -> 2918364.1
A39: =0.0175/12 -> 0.0014583333 | B39: 1.75 | D39: =(D38+5000)*1.00328-(0.00146*(D38+5000)) -> 15054.666 | E39: =(E38+5000)*1.00328-(0.00146*(E38+5000)) -> 76101.33 | F39: =(F38+5000)*1.00328-(0.00146*(F38+5000)) -> 138494.68 | G39: =(G38+5000)*1.00328-(0.00146*(G38+5000)) -> 202264.42 | H39: =(H38+5000)*1.00328-(0.00125*(H38+5000)) -> 267658.93 | I39: =(I38+5000)*1.00328-(0.00125*(I38+5000)) -> 335050.01 | J39: =(J38+5000)*1.00328-(0.00125*(J38+5000)) -> 404101.2 | K39: =(K38+5000)*1.00328-(0.00125*(K38+5000)) -> 474853.38 | L39: =(L38+5000)*1.00328-(0.00104*(L38+5000)) -> 548237.27 | M39: =(M38+5000)*1.00328-(0.00125*(M38+5000)) -> 623648.59 | N39: =(N38+5000)*1.00328-(0.00104*(N38+5000)) -> 701501.16 | O39: =(O38+5000)*1.00328-(0.00104*(O38+5000)) -> 781472.38 | P39: =(P38+5000)*1.00328-(0.00104*(P38+5000)) -> 863619.91 | Q39: =(Q38+5000)*1.00328-(0.00104*(Q38+5000)) -> 948002.97 | R39: =(R38+5000)*1.00328-(0.000833*(R38+5000)) -> 1035741 | S39: =(S38+5000)*1.00328-(0.000833*(S38+5000)) -> 1127530.1 | T39: =(T38+5000)*1.00328-(0.000833*(T38+5000)) -> 1222051.1 | U39: =(U38+5000)*1.00328-(0.00125*(U38+5000)) -> 1317745.7 | V39: =(V38+5000)*1.00328-(0.00125*(V38+5000)) -> 1411004.4 | W39: =(W38+5000)*1.00328-(0.00125*(W38+5000)) -> 1506560.5 | X39: =(X38+5000)*1.00328-(0.00125*(X38+5000)) -> 1604470.4 | Y39: =(Y38+5000)*1.00328-(0.00125*(Y38+5000)) -> 1704792.3 | Z39: =(Z38+5000)*1.00328-(0.00125*(Z38+5000)) -> 1807585.5 | AA39: =(AA38+5000)*1.00328-(0.00125*(AA38+5000)) -> 1912910.9 | AB39: =(AB38+5000)*1.00328-(0.00125*(AB38+5000)) -> 2020830.8 | ... AE39: =(AE38+5000)*1.00328-(0.00125*(AE38+5000)) -> 2360805.1 | AI39: =(AI38+5000)*1.00328-0 -> 15098.615 | AJ39: =(AJ38+5000)*1.00328-0 -> 76998.447 | AK39: =(AK38+5000)*1.00328-0 -> 141379.09 | AL39: =(AL38+5000)*1.00328-0 -> 208339.98 | AM39: =(AM38+5000)*1.00328-0 -> 277984.51 | AN39: =(AN38+5000)*1.00328-0 -> 350420.25 | AO39: =(AO38+5000)*1.00328-0 -> 425759.06 | AP39: =(AP38+5000)*1.00328-0 -> 504117.29 | ... BJ39: =(BJ38+5000)*1.00328-0 -> 2932952.7
A40: =0.015/12 -> 0.00125 | B40: 1.5 | D40: =(D39+5000)*1.00328-(0.00146*(D39+5000)) -> 20091.166 | E40: =(E39+5000)*1.00328-(0.00146*(E39+5000)) -> 81248.934 | F40: =(F39+5000)*1.00328-(0.00146*(F39+5000)) -> 143755.84 | G40: =(G39+5000)*1.00328-(0.00146*(G39+5000)) -> 207641.65 | H40: =(H39+5000)*1.00328-(0.00125*(H39+5000)) -> 273212.42 | I40: =(I39+5000)*1.00328-(0.00125*(I39+5000)) -> 340740.32 | J40: =(J39+5000)*1.00328-(0.00125*(J39+5000)) -> 409931.68 | K40: =(K39+5000)*1.00328-(0.00125*(K39+5000)) -> 480827.49 | L40: =(L39+5000)*1.00328-(0.00104*(L39+5000)) -> 554476.52 | M40: =(M39+5000)*1.00328-(0.00104*(M39+5000)) -> 630056.76 | N40: =(N39+5000)*1.00328-(0.00104*(N39+5000)) -> 708083.72 | O40: =(O39+5000)*1.00328-(0.00104*(O39+5000)) -> 788234.07 | P40: =(P39+5000)*1.00328-(0.00104*(P39+5000)) -> 870565.61 | Q40: =(Q39+5000)*1.00328-(0.00104*(Q39+5000)) -> 955137.69 | R40: =(R39+5000)*1.00328-(0.000833*(R39+5000)) -> 1043287.7 | S40: =(S39+5000)*1.00328-(0.000833*(S39+5000)) -> 1135301.4 | T40: =(T39+5000)*1.00328-(0.000833*(T39+5000)) -> 1230053.7 | U40: =(U39+5000)*1.00328-(0.00125*(U39+5000)) -> 1325430.8 | V40: =(V39+5000)*1.00328-(0.00125*(V39+5000)) -> 1418878.9 | W40: =(W39+5000)*1.00328-(0.00125*(W39+5000)) -> 1514628.9 | X40: =(X39+5000)*1.00328-(0.00125*(X39+5000)) -> 1612737.7 | Y40: =(Y39+5000)*1.00328-(0.00125*(Y39+5000)) -> 1713263.2 | Z40: =(Z39+5000)*1.00328-(0.00125*(Z39+5000)) -> 1816265 | AA40: =(AA39+5000)*1.00328-(0.00125*(AA39+5000)) -> 1921804.2 | AB40: =(AB39+5000)*1.00328-(0.00125*(AB39+5000)) -> 2029943.2 | ... AE40: =(AE39+5000)*1.00328-(0.00125*(AE39+5000)) -> 2370607.7 | AI40: =(AI39+5000)*1.00328-0 -> 20164.539 | AJ40: =(AJ39+5000)*1.00328-0 -> 82267.402 | AK40: =(AK39+5000)*1.00328-0 -> 146859.22 | AL40: =(AL39+5000)*1.00328-0 -> 214039.73 | AM40: =(AM39+5000)*1.00328-0 -> 283912.7 | AN40: =(AN39+5000)*1.00328-0 -> 356586.03 | AO40: =(AO39+5000)*1.00328-0 -> 432171.95 | AP40: =(AP39+5000)*1.00328-0 -> 510787.2 | ... BJ40: =(BJ39+5000)*1.00328-0 -> 2947589.2
A41: =0.0125/12 -> 0.0010416667 | B41: 1.25 | D41: =(D40+5000)*1.00328-(0.00146*(D40+5000)) -> 25136.832 | E41: =(E40+5000)*1.00328-(0.00146*(E40+5000)) -> 86405.907 | F41: =(F40+5000)*1.00328-(0.00146*(F40+5000)) -> 149026.58 | G41: =(G40+5000)*1.00328-(0.00146*(G40+5000)) -> 213028.65 | H41: =(H40+5000)*1.00328-(0.00125*(H40+5000)) -> 278777.2 | I41: =(I40+5000)*1.00328-(0.00125*(I40+5000)) -> 346442.17 | J41: =(J40+5000)*1.00328-(0.00125*(J40+5000)) -> 415773.99 | K41: =(K40+5000)*1.00328-(0.00125*(K40+5000)) -> 486813.72 | L41: =(L40+5000)*1.00328-(0.00104*(L40+5000)) -> 560729.75 | M41: =(M40+5000)*1.00328-(0.00104*(M40+5000)) -> 636479.29 | N41: =(N40+5000)*1.00328-(0.00104*(N40+5000)) -> 714681.03 | O41: =(O40+5000)*1.00328-(0.00104*(O40+5000)) -> 795010.92 | P41: =(P40+5000)*1.00328-(0.00104*(P40+5000)) -> 877526.88 | Q41: =(Q40+5000)*1.00328-(0.00104*(Q40+5000)) -> 962288.4 | R41: =(R40+5000)*1.00328-(0.000833*(R40+5000)) -> 1050852.8 | S41: =(S40+5000)*1.00328-(0.000833*(S40+5000)) -> 1143091.7 | T41: =(T40+5000)*1.00328-(0.000833*(T40+5000)) -> 1238075.8 | U41: =(U40+5000)*1.00328-(0.00125*(U40+5000)) -> 1333131.6 | V41: =(V40+5000)*1.00328-(0.00125*(V40+5000)) -> 1426769.4 | W41: =(W40+5000)*1.00328-(0.00125*(W40+5000)) -> 1522713.8 | X41: =(X40+5000)*1.00328-(0.00125*(X40+5000)) -> 1621021.7 | Y41: =(Y40+5000)*1.00328-(0.00125*(Y40+5000)) -> 1721751.3 | Z41: =(Z40+5000)*1.00328-(0.00125*(Z40+5000)) -> 1824962.2 | AA41: =(AA40+5000)*1.00328-(0.00125*(AA40+5000)) -> 1930715.6 | AB41: =(AB40+5000)*1.00328-(0.00125*(AB40+5000)) -> 2039074.2 | ... AE41: =(AE40+5000)*1.00328-(0.00125*(AE40+5000)) -> 2380430.2 | AI41: =(AI40+5000)*1.00328-0 -> 25247.078 | AJ41: =(AJ40+5000)*1.00328-0 -> 87553.639 | AK41: =(AK40+5000)*1.00328-0 -> 152357.31 | AL41: =(AL40+5000)*1.00328-0 -> 219758.18 | AM41: =(AM40+5000)*1.00328-0 -> 289860.34 | AN41: =(AN40+5000)*1.00328-0 -> 362772.03 | AO41: =(AO40+5000)*1.00328-0 -> 438605.88 | AP41: =(AP40+5000)*1.00328-0 -> 517478.98 | ... BJ41: =(BJ40+5000)*1.00328-0 -> 2962273.7
A42: =0.01/12 -> 0.00083333333 | B42: 1 | D42: =(D41+5000)*1.00328-(0.00146*(D41+5000)) -> 30191.681 | E42: =(E41+5000)*1.00328-(0.00146*(E41+5000)) -> 91572.266 | F42: =(F41+5000)*1.00328-(0.00146*(F41+5000)) -> 154306.9 | G42: =(G41+5000)*1.00328-(0.00146*(G41+5000)) -> 218425.46 | H42: =(H41+5000)*1.00328-(0.00125*(H41+5000)) -> 284353.26 | I42: =(I41+5000)*1.00328-(0.00125*(I41+5000)) -> 352155.6 | J42: =(J41+5000)*1.00328-(0.00125*(J41+5000)) -> 421628.16 | K42: =(K41+5000)*1.00328-(0.00125*(K41+5000)) -> 492812.1 | L42: =(L41+5000)*1.00328-(0.00104*(L41+5000)) -> 566996.98 | M42: =(M41+5000)*1.00328-(0.00104*(M41+5000)) -> 642916.2 | N42: =(N41+5000)*1.00328-(0.00104*(N41+5000)) -> 721293.11 | O42: =(O41+5000)*1.00328-(0.00104*(O41+5000)) -> 801802.94 | P42: =(P41+5000)*1.00328-(0.00104*(P41+5000)) -> 884503.74 | Q42: =(Q41+5000)*1.00328-(0.00104*(Q41+5000)) -> 969455.13 | R42: =(R41+5000)*1.00328-(0.000833*(R41+5000)) -> 1058436.5 | S42: =(S41+5000)*1.00328-(0.000833*(S41+5000)) -> 1150901.1 | T42: =(T41+5000)*1.00328-(0.000833*(T41+5000)) -> 1246117.7 | U42: =(U41+5000)*1.00328-(0.00125*(U41+5000)) -> 1340848 | V42: =(V41+5000)*1.00328-(0.00125*(V41+5000)) -> 1434675.9 | W42: =(W41+5000)*1.00328-(0.00125*(W41+5000)) -> 1530815 | X42: =(X41+5000)*1.00328-(0.00125*(X41+5000)) -> 1629322.5 | Y42: =(Y41+5000)*1.00328-(0.00125*(Y41+5000)) -> 1730256.6 | Z42: =(Z41+5000)*1.00328-(0.00125*(Z41+5000)) -> 1833677 | AA42: =(AA41+5000)*1.00328-(0.00125*(AA41+5000)) -> 1939645.1 | AB42: =(AB41+5000)*1.00328-(0.00125*(AB41+5000)) -> 2048223.6 | ... AE42: =(AE41+5000)*1.00328-(0.00125*(AE41+5000)) -> 2390272.6 | AI42: =(AI41+5000)*1.00328-0 -> 30346.289 | AJ42: =(AJ41+5000)*1.00328-0 -> 92857.215 | AK42: =(AK41+5000)*1.00328-0 -> 157873.45 | AL42: =(AL41+5000)*1.00328-0 -> 225495.39 | AM42: =(AM41+5000)*1.00328-0 -> 295827.48 | AN42: =(AN41+5000)*1.00328-0 -> 368978.33 | AO42: =(AO41+5000)*1.00328-0 -> 445060.9 | AP42: =(AP41+5000)*1.00328-0 -> 524192.71 | ... BJ42: =(BJ41+5000)*1.00328-0 -> 2977006.4
D43: =(D42+5000)*1.00328-(0.00146*(D42+5000)) -> 35255.73 | E43: =(E42+5000)*1.00328-(0.00146*(E42+5000)) -> 96748.028 | F43: =(F42+5000)*1.00328-(0.00146*(F42+5000)) -> 159596.84 | G43: =(G42+5000)*1.00328-(0.00146*(G42+5000)) -> 223832.1 | H43: =(H42+5000)*1.00328-(0.00125*(H42+5000)) -> 289940.65 | I43: =(I42+5000)*1.00328-(0.00125*(I42+5000)) -> 357880.62 | J43: =(J42+5000)*1.00328-(0.00125*(J42+5000)) -> 427494.21 | K43: =(K42+5000)*1.00328-(0.00125*(K42+5000)) -> 498822.66 | L43: =(L42+5000)*1.00328-(0.00104*(L42+5000)) -> 573278.26 | M43: =(M42+5000)*1.00328-(0.00104*(M42+5000)) -> 649367.53 | N43: =(N42+5000)*1.00328-(0.00104*(N42+5000)) -> 727920.01 | O43: =(O42+5000)*1.00328-(0.00104*(O42+5000)) -> 808610.18 | P43: =(P42+5000)*1.00328-(0.00104*(P42+5000)) -> 891496.23 | Q43: =(Q42+5000)*1.00328-(0.00104*(Q42+5000)) -> 976637.91 | R43: =(R42+5000)*1.00328-(0.000833*(R42+5000)) -> 1066038.7 | S43: =(S42+5000)*1.00328-(0.000833*(S42+5000)) -> 1158729.6 | T43: =(T42+5000)*1.00328-(0.000833*(T42+5000)) -> 1254179.1 | U43: =(U42+5000)*1.00328-(0.00125*(U42+5000)) -> 1348580.1 | V43: =(V42+5000)*1.00328-(0.00125*(V42+5000)) -> 1442598.4 | W43: =(W42+5000)*1.00328-(0.00125*(W42+5000)) -> 1538932.7 | X43: =(X42+5000)*1.00328-(0.00125*(X42+5000)) -> 1637640.2 | Y43: =(Y42+5000)*1.00328-(0.00125*(Y42+5000)) -> 1738779.1 | Z43: =(Z42+5000)*1.00328-(0.00125*(Z42+5000)) -> 1842409.5 | AA43: =(AA42+5000)*1.00328-(0.00125*(AA42+5000)) -> 1948592.8 | AB43: =(AB42+5000)*1.00328-(0.00125*(AB42+5000)) -> 2057391.7 | ... AE43: =(AE42+5000)*1.00328-(0.00125*(AE42+5000)) -> 2400135 | AI43: =(AI42+5000)*1.00328-0 -> 35462.225 | AJ43: =(AJ42+5000)*1.00328-0 -> 98178.187 | AK43: =(AK42+5000)*1.00328-0 -> 163407.67 | AL43: =(AL42+5000)*1.00328-0 -> 231251.41 | AM43: =(AM42+5000)*1.00328-0 -> 301814.19 | AN43: =(AN42+5000)*1.00328-0 -> 375204.97 | AO43: =(AO42+5000)*1.00328-0 -> 451537.1 | AP43: =(AP42+5000)*1.00328-0 -> 530928.46 | ... BJ43: =(BJ42+5000)*1.00328-0 -> 2991787.4
D44: =(D43+5000)*1.00328-(0.00146*(D43+5000)) -> 40328.995 | E44: =(E43+5000)*1.00328-(0.00146*(E43+5000)) -> 101933.21 | F44: =(F43+5000)*1.00328-(0.00146*(F43+5000)) -> 164896.41 | G44: =(G43+5000)*1.00328-(0.00146*(G43+5000)) -> 229248.57 | H44: =(H43+5000)*1.00328-(0.00125*(H43+5000)) -> 295539.38 | I44: =(I43+5000)*1.00328-(0.00125*(I43+5000)) -> 363617.27 | J44: =(J43+5000)*1.00328-(0.00125*(J43+5000)) -> 433372.18 | K44: =(K43+5000)*1.00328-(0.00104*(K43+5000)) -> 504951.22 | L44: =(L43+5000)*1.00328-(0.00104*(L43+5000)) -> 579573.6 | M44: =(M43+5000)*1.00328-(0.00104*(M43+5000)) -> 655833.32 | N44: =(N43+5000)*1.00328-(0.00104*(N43+5000)) -> 734561.75 | O44: =(O43+5000)*1.00328-(0.00104*(O43+5000)) -> 815432.67 | P44: =(P43+5000)*1.00328-(0.00104*(P43+5000)) -> 898504.38 | Q44: =(Q43+5000)*1.00328-(0.00104*(Q43+5000)) -> 983836.78 | R44: =(R43+5000)*1.00328-(0.000833*(R43+5000)) -> 1073659.6 | S44: =(S43+5000)*1.00328-(0.000833*(S43+5000)) -> 1166577.2 | T44: =(T43+5000)*1.00328-(0.000833*(T43+5000)) -> 1262260.3 | U44: =(U43+5000)*1.00328-(0.00125*(U43+5000)) -> 1356327.8 | V44: =(V43+5000)*1.00328-(0.00125*(V43+5000)) -> 1450537 | W44: =(W43+5000)*1.00328-(0.00125*(W43+5000)) -> 1547066.9 | X44: =(X43+5000)*1.00328-(0.00125*(X43+5000)) -> 1645974.7 | Y44: =(Y43+5000)*1.00328-(0.00125*(Y43+5000)) -> 1747319 | Z44: =(Z43+5000)*1.00328-(0.00125*(Z43+5000)) -> 1851159.8 | AA44: =(AA43+5000)*1.00328-(0.00125*(AA43+5000)) -> 1957558.6 | AB44: =(AB43+5000)*1.00328-(0.00125*(AB43+5000)) -> 2066578.3 | ... AE44: =(AE43+5000)*1.00328-(0.00125*(AE43+5000)) -> 2410017.4 | AI44: =(AI43+5000)*1.00328-0 -> 40594.941 | AJ44: =(AJ43+5000)*1.00328-0 -> 103516.61 | AK44: =(AK43+5000)*1.00328-0 -> 168960.05 | AL44: =(AL43+5000)*1.00328-0 -> 237026.32 | AM44: =(AM43+5000)*1.00328-0 -> 307820.54 | AN44: =(AN43+5000)*1.00328-0 -> 381452.05 | AO44: =(AO43+5000)*1.00328-0 -> 458034.55 | AP44: =(AP43+5000)*1.00328-0 -> 537686.31 | ... BJ44: =(BJ43+5000)*1.00328-0 -> 3006616.8
D45: =(D44+5000)*1.00328-(0.00146*(D44+5000)) -> 45411.494 | E45: =(E44+5000)*1.00328-(0.00146*(E44+5000)) -> 107127.83 | F45: =(F44+5000)*1.00328-(0.00146*(F44+5000)) -> 170205.62 | G45: =(G44+5000)*1.00328-(0.00146*(G44+5000)) -> 234674.91 | H45: =(H44+5000)*1.00328-(0.00125*(H44+5000)) -> 301149.48 | I45: =(I44+5000)*1.00328-(0.00125*(I44+5000)) -> 369365.56 | J45: =(J44+5000)*1.00328-(0.00125*(J44+5000)) -> 439262.07 | K45: =(K44+5000)*1.00328-(0.00104*(K44+5000)) -> 511093.51 | L45: =(L44+5000)*1.00328-(0.00104*(L44+5000)) -> 585883.04 | M45: =(M44+5000)*1.00328-(0.00104*(M44+5000)) -> 662313.58 | N45: =(N44+5000)*1.00328-(0.00104*(N44+5000)) -> 741218.37 | O45: =(O44+5000)*1.00328-(0.00104*(O44+5000)) -> 822270.44 | P45: =(P44+5000)*1.00328-(0.00104*(P44+5000)) -> 905528.23 | Q45: =(Q44+5000)*1.00328-(0.00104*(Q44+5000)) -> 991051.77 | R45: =(R44+5000)*1.00328-(0.000833*(R44+5000)) -> 1081299 | S45: =(S44+5000)*1.00328-(0.000833*(S44+5000)) -> 1174444.1 | T45: =(T44+5000)*1.00328-(0.000833*(T44+5000)) -> 1270361.3 | U45: =(U44+5000)*1.00328-(0.00125*(U44+5000)) -> 1364091.3 | V45: =(V44+5000)*1.00328-(0.00125*(V44+5000)) -> 1458491.8 | W45: =(W44+5000)*1.00328-(0.00125*(W44+5000)) -> 1555217.6 | X45: =(X44+5000)*1.00328-(0.00125*(X44+5000)) -> 1654326.2 | Y45: =(Y44+5000)*1.00328-(0.00125*(Y44+5000)) -> 1755876.2 | Z45: =(Z44+5000)*1.00328-(0.00125*(Z44+5000)) -> 1859927.8 | AA45: =(AA44+5000)*1.00328-(0.00125*(AA44+5000)) -> 1966542.6 | AB45: =(AB44+5000)*1.00328-(0.00125*(AB44+5000)) -> 2075783.7 | ... AE45: =(AE44+5000)*1.00328-(0.00125*(AE44+5000)) -> 2419919.9 | AI45: =(AI44+5000)*1.00328-0 -> 45744.492 | AJ45: =(AJ44+5000)*1.00328-0 -> 108872.55 | AK45: =(AK44+5000)*1.00328-0 -> 174530.64 | AL45: =(AL44+5000)*1.00328-0 -> 242820.17 | AM45: =(AM44+5000)*1.00328-0 -> 313846.59 | AN45: =(AN44+5000)*1.00328-0 -> 387719.61 | AO45: =(AO44+5000)*1.00328-0 -> 464553.3 | AP45: =(AP44+5000)*1.00328-0 -> 544466.32 | ... BJ45: =(BJ44+5000)*1.00328-0 -> 3021494.9
D46: =(D45+5000)*1.00328-(0.00146*(D45+5000)) -> 50503.243 | E46: =(E45+5000)*1.00328-(0.00146*(E45+5000)) -> 112331.9 | F46: =(F45+5000)*1.00328-(0.00146*(F45+5000)) -> 175524.49 | G46: =(G45+5000)*1.00328-(0.00146*(G45+5000)) -> 240111.11 | H46: =(H45+5000)*1.00328-(0.00125*(H45+5000)) -> 306770.96 | I46: =(I45+5000)*1.00328-(0.00125*(I45+5000)) -> 375125.52 | J46: =(J45+5000)*1.00328-(0.00125*(J45+5000)) -> 445163.93 | K46: =(K45+5000)*1.00328-(0.00104*(K45+5000)) -> 517249.56 | L46: =(L45+5000)*1.00328-(0.00104*(L45+5000)) -> 592206.62 | M46: =(M45+5000)*1.00328-(0.00104*(M45+5000)) -> 668808.37 | N46: =(N45+5000)*1.00328-(0.00104*(N45+5000)) -> 747889.9 | O46: =(O45+5000)*1.00328-(0.00104*(O45+5000)) -> 829123.52 | P46: =(P45+5000)*1.00328-(0.00104*(P45+5000)) -> 912567.81 | Q46: =(Q45+5000)*1.00328-(0.00104*(Q45+5000)) -> 998282.93 | R46: =(R45+5000)*1.00328-(0.000833*(R45+5000)) -> 1088957.2 | S46: =(S45+5000)*1.00328-(0.000833*(S45+5000)) -> 1182330.2 | T46: =(T45+5000)*1.00328-(0.000833*(T45+5000)) -> 1278482.1 | U46: =(U45+5000)*1.00328-(0.00125*(U45+5000)) -> 1371870.6 | V46: =(V45+5000)*1.00328-(0.00125*(V45+5000)) -> 1466462.6 | W46: =(W45+5000)*1.00328-(0.00125*(W45+5000)) -> 1563384.9 | X46: =(X45+5000)*1.00328-(0.00125*(X45+5000)) -> 1662694.6 | Y46: =(Y45+5000)*1.00328-(0.00125*(Y45+5000)) -> 1764450.8 | Z46: =(Z45+5000)*1.00328-(0.00125*(Z45+5000)) -> 1868713.6 | AA46: =(AA45+5000)*1.00328-(0.00125*(AA45+5000)) -> 1975544.8 | AB46: =(AB45+5000)*1.00328-(0.00125*(AB45+5000)) -> 2085007.6 | ... AE46: =(AE45+5000)*1.00328-(0.00125*(AE45+5000)) -> 2429842.5 | AI46: =(AI45+5000)*1.00328-0 -> 50910.934 | AJ46: =(AJ45+5000)*1.00328-0 -> 114246.05 | AK46: =(AK45+5000)*1.00328-0 -> 180119.5 | AL46: =(AL45+5000)*1.00328-0 -> 248633.02 | AM46: =(AM45+5000)*1.00328-0 -> 319892.41 | AN46: =(AN45+5000)*1.00328-0 -> 394007.73 | AO46: =(AO45+5000)*1.00328-0 -> 471093.43 | AP46: =(AP45+5000)*1.00328-0 -> 551268.57 | ... BJ46: =(BJ45+5000)*1.00328-0 -> 3036421.8
D47: =(D46+5000)*1.00328-(0.00146*(D46+5000)) -> 55604.259 | E47: =(E46+5000)*1.00328-(0.00146*(E46+5000)) -> 117545.44 | F47: =(F46+5000)*1.00328-(0.00146*(F46+5000)) -> 180853.05 | G47: =(G46+5000)*1.00328-(0.00146*(G46+5000)) -> 245557.22 | H47: =(H46+5000)*1.00328-(0.00125*(H46+5000)) -> 312403.85 | I47: =(I46+5000)*1.00328-(0.00125*(I46+5000)) -> 380897.18 | J47: =(J46+5000)*1.00328-(0.00125*(J46+5000)) -> 451077.76 | K47: =(K46+5000)*1.00328-(0.00104*(K46+5000)) -> 523419.4 | L47: =(L46+5000)*1.00328-(0.00104*(L46+5000)) -> 598544.36 | M47: =(M46+5000)*1.00328-(0.00104*(M46+5000)) -> 675317.7 | N47: =(N46+5000)*1.00328-(0.00104*(N46+5000)) -> 754576.37 | O47: =(O46+5000)*1.00328-(0.00104*(O46+5000)) -> 835991.96 | P47: =(P46+5000)*1.00328-(0.00104*(P46+5000)) -> 919623.17 | Q47: =(Q46+5000)*1.00328-(0.000833*(Q46+5000)) -> 1005738 | R47: =(R46+5000)*1.00328-(0.000833*(R46+5000)) -> 1096634.1 | S47: =(S46+5000)*1.00328-(0.000833*(S46+5000)) -> 1190235.6 | T47: =(T46+5000)*1.00328-(0.000833*(T46+5000)) -> 1286622.8 | U47: =(U46+5000)*1.00328-(0.00125*(U46+5000)) -> 1379665.6 | V47: =(V46+5000)*1.00328-(0.00125*(V46+5000)) -> 1474449.7 | W47: =(W46+5000)*1.00328-(0.00125*(W46+5000)) -> 1571568.7 | X47: =(X46+5000)*1.00328-(0.00125*(X46+5000)) -> 1671080.1 | Y47: =(Y46+5000)*1.00328-(0.00125*(Y46+5000)) -> 1773042.8 | Z47: =(Z46+5000)*1.00328-(0.00125*(Z46+5000)) -> 1877517.2 | AA47: =(AA46+5000)*1.00328-(0.00125*(AA46+5000)) -> 1984565.3 | AB47: =(AB46+5000)*1.00328-(0.00125*(AB46+5000)) -> 2094250.4 | ... AE47: =(AE46+5000)*1.00328-(0.00125*(AE46+5000)) -> 2439785.2 | AI47: =(AI46+5000)*1.00328-0 -> 56094.322 | AJ47: =(AJ46+5000)*1.00328-0 -> 119637.17 | AK47: =(AK46+5000)*1.00328-0 -> 185726.69 | AL47: =(AL46+5000)*1.00328-0 -> 254464.93 | AM47: =(AM46+5000)*1.00328-0 -> 325958.06 | AN47: =(AN46+5000)*1.00328-0 -> 400316.48 | AO47: =(AO46+5000)*1.00328-0 -> 477655.02 | AP47: =(AP46+5000)*1.00328-0 -> 558093.13 | ... BJ47: =(BJ46+5000)*1.00328-0 -> 3051397.7
D48: =(D47+5000)*1.00328-(0.00146*(D47+5000)) -> 60714.558 | E48: =(E47+5000)*1.00328-(0.00146*(E47+5000)) -> 122768.48 | F48: =(F47+5000)*1.00328-(0.00146*(F47+5000)) -> 186191.3 | G48: =(G47+5000)*1.00328-(0.00125*(G47+5000)) -> 251065.85 | H48: =(H47+5000)*1.00328-(0.00125*(H47+5000)) -> 318048.18 | I48: =(I47+5000)*1.00328-(0.00125*(I47+5000)) -> 386680.55 | J48: =(J47+5000)*1.00328-(0.00125*(J47+5000)) -> 457003.6 | K48: =(K47+5000)*1.00328-(0.00104*(K47+5000)) -> 529603.06 | L48: =(L47+5000)*1.00328-(0.00104*(L47+5000)) -> 604896.3 | M48: =(M47+5000)*1.00328-(0.00104*(M47+5000)) -> 681841.61 | N48: =(N47+5000)*1.00328-(0.00104*(N47+5000)) -> 761277.82 | O48: =(O47+5000)*1.00328-(0.00104*(O47+5000)) -> 842875.78 | P48: =(P47+5000)*1.00328-(0.00104*(P47+5000)) -> 926694.32 | Q48: =(Q47+5000)*1.00328-(0.000833*(Q47+5000)) -> 1013211.2 | R48: =(R47+5000)*1.00328-(0.000833*(R47+5000)) -> 1104329.8 | S48: =(S47+5000)*1.00328-(0.000833*(S47+5000)) -> 1198160.3 | T48: =(T47+5000)*1.00328-(0.000833*(T47+5000)) -> 1294783.4 | U48: =(U47+5000)*1.00328-(0.00125*(U47+5000)) -> 1387476.5 | V48: =(V47+5000)*1.00328-(0.00125*(V47+5000)) -> 1482453 | W48: =(W47+5000)*1.00328-(0.00125*(W47+5000)) -> 1579769.1 | X48: =(X47+5000)*1.00328-(0.00125*(X47+5000)) -> 1679482.5 | Y48: =(Y47+5000)*1.00328-(0.00125*(Y47+5000)) -> 1781652.2 | Z48: =(Z47+5000)*1.00328-(0.00125*(Z47+5000)) -> 1886338.7 | AA48: =(AA47+5000)*1.00328-(0.00125*(AA47+5000)) -> 1993604.1 | AB48: =(AB47+5000)*1.00328-(0.00125*(AB47+5000)) -> 2103511.8 | ... AE48: =(AE47+5000)*1.00328-(0.00125*(AE47+5000)) -> 2449748.1 | AI48: =(AI47+5000)*1.00328-0 -> 61294.711 | AJ48: =(AJ47+5000)*1.00328-0 -> 125045.98 | AK48: =(AK47+5000)*1.00328-0 -> 191352.27 | AL48: =(AL47+5000)*1.00328-0 -> 260315.98 | AM48: =(AM47+5000)*1.00328-0 -> 332043.6 | AN48: =(AN47+5000)*1.00328-0 -> 406645.91 | AO48: =(AO47+5000)*1.00328-0 -> 484238.13 | AP48: =(AP47+5000)*1.00328-0 -> 564940.08 | ... BJ48: =(BJ47+5000)*1.00328-0 -> 3066422.7
D51: Scenario 3 | AI51: Scenario 3 | AJ51: WITHOUT AN ADVISOR
D52: Assume 5% annual return on investments | AI52: Assume 5% annual return on investments
D53: Assume 5K/mo invested | AI53: Assume 5K/mo invested
D54: Y1 | E54: Y2 | F54: Y3 | G54: Y4 | H54: Y5 | I54: Y6 | J54: Y7 | K54: Y8 | L54: Y9 | M54: Y10 | N54: Y11 | O54: Y12 | P54: Y13 | Q54: Y14 | R54: Y15 | S54: Y16 | T54: Y17 | U54: Y18 | V54: Y19 | W54: Y20 | X54: Y21 | Y54: Y22 | Z54: Y23 | AA54: Y24 | AB54: Y25 | AC54: Y26 | AD54: Y27 | AE54: Y28 | AI54: Y1 | AJ54: Y2 | AK54: Y3 | AL54: Y4 | AM54: Y5 | AN54: Y6 | AO54: Y7 | AP54: Y8 | AQ54: Y9 | AR54: Y10 | AS54: Y11 | AT54: Y12 | AU54: Y13 | AV54: Y14 | AW54: Y15 | AX54: Y16 | AY54: Y17 | AZ54: Y18 | BA54: Y19 | BB54: Y20 | BC54: Y21 | BD54: Y22 | BE54: Y23 | BF54: Y24 | BG54: Y25 | BH54: Y26 | BI54: Y27 | BJ54: Y28
D55: 0 | AI55: 0
D56: =(D55+5000)*1.00407-(0.00146*(D55+5000)) -> 5013.05 | E56: =(D67+5000)*1.00407-(0.00146*(D67+5000)) -> 66200.037 | F56: =(E67+5000)*1.00407-(0.00146*(E67+5000)) -> 129331.15 | G56: =(F67+5000)*1.00407-(0.00146*(F67+5000)) -> 194468.16 | H56: =(G67+5000)*1.00407-(0.00125*(G67+5000)) -> 261836.12 | I56: =(H67+5000)*1.00407-(0.00125*(H67+5000)) -> 331946.63 | J56: =(I67+5000)*1.00407-(0.00125*(I67+5000)) -> 404466.83 | K56: =(J67+5000)*1.00407-(0.00125*(J67+5000)) -> 479479.54 | L56: =(K67+5000)*1.00407-(0.00104*(K67+5000)) -> 558083.1 | M56: =(L67+5000)*1.00407-(0.00104*(L67+5000)) -> 639911.54 | N56: =(M67+5000)*1.00407-(0.00104*(M67+5000)) -> 724765.34 | O56: =(N67+5000)*1.00407-(0.00104*(N67+5000)) -> 812756.37 | P56: =(O67+5000)*1.00407-(0.00104*(O67+5000)) -> 904000.61 | Q56: =(P67+5000)*1.00407-(0.00104*(P67+5000)) -> 998618.34 | R56: =(Q67+5000)*1.00407-(0.000833*(Q67+5000)) -> 1099384.3 | S56: =(R67+5000)*1.00407-(0.000833*(R67+5000)) -> 1204134.9 | T56: =(S67+5000)*1.00407-(0.000833*(S67+5000)) -> 1313027.6 | U56: =(T67+5000)*1.00407-(0.00125*(T67+5000)) -> 1425633.5 | V56: =(U67+5000)*1.00407-(0.00125*(U67+5000)) -> 1535743.5 | W56: =(V67+5000)*1.00407-(0.00125*(V67+5000)) -> 1649638 | X56: =(W67+5000)*1.00407-(0.00125*(W67+5000)) -> 1767447 | Y56: =(X67+5000)*1.00407-(0.00125*(X67+5000)) -> 1889305.1 | Z56: =(Y67+5000)*1.00407-(0.00125*(Y67+5000)) -> 2015351.4 | AA56: =(Z67+5000)*1.00407-(0.00125*(Z67+5000)) -> 2145730 | AB56: =(AA67+5000)*1.00407-(0.00125*(AA67+5000)) -> 2280589.6 | ... AE56: =(AD67+5000)*1.00407-(0.00125*(AD67+5000)) -> 2713621.7 | AI56: =(AI55+5000)*1.00407-0 -> 5020.35 | AJ56: =(AI67+5000)*1.00407-0 -> 66882.338 | AK56: =(AJ67+5000)*1.00407-0 -> 131834.22 | AL56: =(AK67+5000)*1.00407-0 -> 200030.34 | AM56: =(AL67+5000)*1.00407-0 -> 271632.74 | AN56: =(AM67+5000)*1.00407-0 -> 346811.55 | AO56: =(AN67+5000)*1.00407-0 -> 425745.41 | AP56: =(AO67+5000)*1.00407-0 -> 508621.88 | AQ56: =(AP67+5000)*1.00407-0 -> 595637.89 | ... BJ56: =(BI67+5000)*1.00407-0 -> 3384316
D57: =(D56+5000)*1.00407-(0.00146*(D56+5000)) -> 10039.184 | E57: =(E56+5000)*1.00407-(0.00146*(E56+5000)) -> 71385.87 | F57: =(F56+5000)*1.00407-(0.00146*(F56+5000)) -> 134681.76 | G57: =(G56+5000)*1.00407-(0.00146*(G56+5000)) -> 199988.78 | H57: =(H56+5000)*1.00407-(0.00125*(H56+5000)) -> 267588.59 | I57: =(I56+5000)*1.00407-(0.00125*(I56+5000)) -> 337896.82 | J57: =(J56+5000)*1.00407-(0.00125*(J56+5000)) -> 410621.53 | K57: =(K56+5000)*1.00407-(0.00125*(K56+5000)) -> 485845.77 | L57: =(L56+5000)*1.00407-(0.00104*(L56+5000)) -> 564789.24 | M57: =(M56+5000)*1.00407-(0.00104*(M56+5000)) -> 646865.62 | N57: =(N56+5000)*1.00407-(0.00104*(N56+5000)) -> 731976.53 | O57: =(O56+5000)*1.00407-(0.00104*(O56+5000)) -> 820234.17 | P57: =(P56+5000)*1.00407-(0.00104*(P56+5000)) -> 911754.88 | Q57: =(Q56+5000)*1.00407-(0.000833*(Q56+5000)) -> 1006867 | R57: =(R56+5000)*1.00407-(0.000833*(R56+5000)) -> 1107959.2 | S57: =(S56+5000)*1.00407-(0.000833*(S56+5000)) -> 1213048.9 | T57: =(T56+5000)*1.00407-(0.000833*(T56+5000)) -> 1322294.1 | U57: =(U56+5000)*1.00407-(0.00125*(U56+5000)) -> 1434667.9 | V57: =(V56+5000)*1.00407-(0.00125*(V56+5000)) -> 1545088.4 | W57: =(W56+5000)*1.00407-(0.00125*(W56+5000)) -> 1659304.1 | X57: =(X56+5000)*1.00407-(0.00125*(X56+5000)) -> 1777445.3 | Y57: =(Y56+5000)*1.00407-(0.00125*(Y56+5000)) -> 1899647.1 | Z57: =(Z56+5000)*1.00407-(0.00125*(Z56+5000)) -> 2026048.8 | AA57: =(AA56+5000)*1.00407-(0.00125*(AA56+5000)) -> 2156795 | AB57: =(AB56+5000)*1.00407-(0.00125*(AB56+5000)) -> 2292034.9 | ... AE57: =(AE56+5000)*1.00407-(0.00125*(AE56+5000)) -> 2726288.2 | AI57: =(AI56+5000)*1.00407-0 -> 10061.133 | AJ57: =(AJ56+5000)*1.00407-0 -> 72174.899 | AK57: =(AK56+5000)*1.00407-0 -> 137391.14 | AL57: =(AL56+5000)*1.00407-0 -> 205864.82 | AM57: =(AM56+5000)*1.00407-0 -> 277758.64 | AN57: =(AN56+5000)*1.00407-0 -> 353243.43 | AO57: =(AO56+5000)*1.00407-0 -> 432498.55 | AP57: =(AP56+5000)*1.00407-0 -> 515712.33 | ... BJ57: =(BJ56+5000)*1.00407-0 -> 3403110.5
A58: =0.0175/12 -> 0.0014583333 | B58: 1.75 | D58: =(D57+5000)*1.00407-(0.00146*(D57+5000)) -> 15078.436 | E58: =(E57+5000)*1.00407-(0.00146*(E57+5000)) -> 76585.237 | F58: =(F57+5000)*1.00407-(0.00146*(F57+5000)) -> 140046.33 | G58: =(G57+5000)*1.00407-(0.00146*(G57+5000)) -> 205523.8 | H58: =(H57+5000)*1.00407-(0.00125*(H57+5000)) -> 273357.29 | I58: =(I57+5000)*1.00407-(0.00125*(I57+5000)) -> 343863.79 | J58: =(J57+5000)*1.00407-(0.00125*(J57+5000)) -> 416793.58 | K58: =(K57+5000)*1.00407-(0.00125*(K57+5000)) -> 492229.95 | L58: =(L57+5000)*1.00407-(0.00104*(L57+5000)) -> 571515.71 | M58: =(M57+5000)*1.00407-(0.00104*(M57+5000)) -> 653840.77 | N58: =(N57+5000)*1.00407-(0.00104*(N57+5000)) -> 739209.57 | O58: =(O57+5000)*1.00407-(0.00104*(O57+5000)) -> 827734.63 | P58: =(P57+5000)*1.00407-(0.00104*(P57+5000)) -> 919532.64 | Q58: =(Q57+5000)*1.00407-(0.000833*(Q57+5000)) -> 1015142.5 | R58: =(R57+5000)*1.00407-(0.000833*(R57+5000)) -> 1116561.9 | S58: =(S57+5000)*1.00407-(0.000833*(S57+5000)) -> 1221991.7 | T58: =(T57+5000)*1.00407-(0.000833*(T57+5000)) -> 1331590.5 | U58: =(U57+5000)*1.00407-(0.00125*(U57+5000)) -> 1443727.7 | V58: =(V57+5000)*1.00407-(0.00125*(V57+5000)) -> 1554459.7 | W58: =(W57+5000)*1.00407-(0.00125*(W57+5000)) -> 1668997.4 | X58: =(X57+5000)*1.00407-(0.00125*(X57+5000)) -> 1787471.8 | Y58: =(Y57+5000)*1.00407-(0.00125*(Y57+5000)) -> 1910018.2 | Z58: =(Z57+5000)*1.00407-(0.00125*(Z57+5000)) -> 2036776.4 | AA58: =(AA57+5000)*1.00407-(0.00125*(AA57+5000)) -> 2167891.3 | AB58: =(AB57+5000)*1.00407-(0.00125*(AB57+5000)) -> 2303512.6 | ... AE58: =(AE57+5000)*1.00407-(0.00125*(AE57+5000)) -> 2738990.5 | AI58: =(AI57+5000)*1.00407-0 -> 15122.432 | AJ58: =(AJ57+5000)*1.00407-0 -> 77489.001 | AK58: =(AK57+5000)*1.00407-0 -> 142970.67 | AL58: =(AL57+5000)*1.00407-0 -> 211723.04 | AM58: =(AM57+5000)*1.00407-0 -> 283909.46 | AN58: =(AN57+5000)*1.00407-0 -> 359701.48 | AO58: =(AO57+5000)*1.00407-0 -> 439279.17 | AP58: =(AP57+5000)*1.00407-0 -> 522831.62 | ... BJ58: =(BJ57+5000)*1.00407-0 -> 3421981.6
A59: =0.015/12 -> 0.00125 | B59: 1.5 | D59: =(D58+5000)*1.00407-(0.00146*(D58+5000)) -> 20130.841 | E59: =(E58+5000)*1.00407-(0.00146*(E58+5000)) -> 81798.174 | F59: =(F58+5000)*1.00407-(0.00146*(F58+5000)) -> 145424.9 | G59: =(G58+5000)*1.00407-(0.00146*(G58+5000)) -> 211073.26 | H59: =(H58+5000)*1.00407-(0.00125*(H58+5000)) -> 279142.26 | I59: =(I58+5000)*1.00407-(0.00125*(I58+5000)) -> 349847.59 | J59: =(J58+5000)*1.00407-(0.00125*(J58+5000)) -> 422983.04 | K59: =(K58+5000)*1.00407-(0.00125*(K58+5000)) -> 498632.14 | L59: =(L58+5000)*1.00407-(0.00104*(L58+5000)) -> 578262.55 | M59: =(M58+5000)*1.00407-(0.00104*(M58+5000)) -> 660837.06 | N59: =(N58+5000)*1.00407-(0.00104*(N58+5000)) -> 746464.52 | O59: =(O58+5000)*1.00407-(0.00104*(O58+5000)) -> 835257.81 | P59: =(P58+5000)*1.00407-(0.00104*(P58+5000)) -> 927333.98 | Q59: =(Q58+5000)*1.00407-(0.000833*(Q58+5000)) -> 1023444.7 | R59: =(R58+5000)*1.00407-(0.000833*(R58+5000)) -> 1125192.3 | S59: =(S58+5000)*1.00407-(0.000833*(S58+5000)) -> 1230963.5 | T59: =(T58+5000)*1.00407-(0.000833*(T58+5000)) -> 1340917.1 | U59: =(U58+5000)*1.00407-(0.00125*(U58+5000)) -> 1452813.1 | V59: =(V58+5000)*1.00407-(0.00125*(V58+5000)) -> 1563857.3 | W59: =(W58+5000)*1.00407-(0.00125*(W58+5000)) -> 1678718.1 | X59: =(X58+5000)*1.00407-(0.00125*(X58+5000)) -> 1797526.6 | Y59: =(Y58+5000)*1.00407-(0.00125*(Y58+5000)) -> 1920418.5 | Z59: =(Z58+5000)*1.00407-(0.00125*(Z58+5000)) -> 2047534.2 | AA59: =(AA58+5000)*1.00407-(0.00125*(AA58+5000)) -> 2179018.8 | AB59: =(AB58+5000)*1.00407-(0.00125*(AB58+5000)) -> 2315022.6 | ... AE59: =(AE58+5000)*1.00407-(0.00125*(AE58+5000)) -> 2751728.5 | AI59: =(AI58+5000)*1.00407-0 -> 20204.33 | AJ59: =(AJ58+5000)*1.00407-0 -> 82824.732 | AK59: =(AK58+5000)*1.00407-0 -> 148572.91 | AL59: =(AL58+5000)*1.00407-0 -> 217605.1 | AM59: =(AM58+5000)*1.00407-0 -> 290085.33 | AN59: =(AN58+5000)*1.00407-0 -> 366185.81 | AO59: =(AO58+5000)*1.00407-0 -> 446087.38 | AP59: =(AP58+5000)*1.00407-0 -> 529979.9 | ... BJ59: =(BJ58+5000)*1.00407-0 -> 3440929.4
A60: =0.0125/12 -> 0.0010416667 | B60: 1.25 | D60: =(D59+5000)*1.00407-(0.00146*(D59+5000)) -> 25196.433 | E60: =(E59+5000)*1.00407-(0.00146*(E59+5000)) -> 87024.717 | F60: =(F59+5000)*1.00407-(0.00146*(F59+5000)) -> 150817.51 | G60: =(G59+5000)*1.00407-(0.00146*(G59+5000)) -> 216637.22 | H60: =(H59+5000)*1.00407-(0.00125*(H59+5000)) -> 284943.54 | I60: =(I59+5000)*1.00407-(0.00125*(I59+5000)) -> 355848.26 | J60: =(J59+5000)*1.00407-(0.00125*(J59+5000)) -> 429189.95 | K60: =(K59+5000)*1.00407-(0.00104*(K59+5000)) -> 505158.15 | L60: =(L59+5000)*1.00407-(0.00104*(L59+5000)) -> 585029.83 | M60: =(M59+5000)*1.00407-(0.00104*(M59+5000)) -> 667854.55 | N60: =(N59+5000)*1.00407-(0.00104*(N59+5000)) -> 753741.46 | O60: =(O59+5000)*1.00407-(0.00104*(O59+5000)) -> 842803.79 | P60: =(P59+5000)*1.00407-(0.00104*(P59+5000)) -> 935158.95 | Q60: =(Q59+5000)*1.00407-(0.000833*(Q59+5000)) -> 1031773.7 | R60: =(R59+5000)*1.00407-(0.000833*(R59+5000)) -> 1133850.8 | S60: =(S59+5000)*1.00407-(0.000833*(S59+5000)) -> 1239964.3 | T60: =(T59+5000)*1.00407-(0.000833*(T59+5000)) -> 1350273.8 | U60: =(U59+5000)*1.00407-(0.00125*(U59+5000)) -> 1461924.2 | V60: =(V59+5000)*1.00407-(0.00125*(V59+5000)) -> 1573281.5 | W60: =(W59+5000)*1.00407-(0.00125*(W59+5000)) -> 1688466.2 | X60: =(X59+5000)*1.00407-(0.00125*(X59+5000)) -> 1807609.7 | Y60: =(Y59+5000)*1.00407-(0.00125*(Y59+5000)) -> 1930848.2 | Z60: =(Z59+5000)*1.00407-(0.00125*(Z59+5000)) -> 2058322.4 | AA60: =(AA59+5000)*1.00407-(0.00125*(AA59+5000)) -> 2190177.8 | AB60: =(AB59+5000)*1.00407-(0.00125*(AB59+5000)) -> 2326565.1 | ... AE60: =(AE59+5000)*1.00407-(0.00125*(AE59+5000)) -> 2764502.5 | AI60: =(AI59+5000)*1.00407-0 -> 25306.912 | AJ60: =(AJ59+5000)*1.00407-0 -> 88182.178 | AK60: =(AK59+5000)*1.00407-0 -> 154197.95 | AL60: =(AL59+5000)*1.00407-0 -> 223511.1 | AM60: =(AM59+5000)*1.00407-0 -> 296286.32 | AN60: =(AN59+5000)*1.00407-0 -> 372696.54 | AO60: =(AO59+5000)*1.00407-0 -> 452923.31 | AP60: =(AP59+5000)*1.00407-0 -> 537157.27 | ... BJ60: =(BJ59+5000)*1.00407-0 -> 3459954.3
A61: =0.01/12 -> 0.00083333333 | B61: 1 | D61: =(D60+5000)*1.00407-(0.00146*(D60+5000)) -> 30275.245 | E61: =(E60+5000)*1.00407-(0.00146*(E60+5000)) -> 92264.902 | F61: =(F60+5000)*1.00407-(0.00146*(F60+5000)) -> 156224.19 | G61: =(G60+5000)*1.00407-(0.00146*(G60+5000)) -> 222215.69 | H61: =(H60+5000)*1.00407-(0.00125*(H60+5000)) -> 290761.18 | I61: =(I60+5000)*1.00407-(0.00125*(I60+5000)) -> 361865.85 | J61: =(J60+5000)*1.00407-(0.00125*(J60+5000)) -> 435414.37 | K61: =(K60+5000)*1.00407-(0.00104*(K60+5000)) -> 511703.93 | L61: =(L60+5000)*1.00407-(0.00104*(L60+5000)) -> 591817.62 | M61: =(M60+5000)*1.00407-(0.00104*(M60+5000)) -> 674893.29 | N61: =(N60+5000)*1.00407-(0.00104*(N60+5000)) -> 761040.45 | O61: =(O60+5000)*1.00407-(0.00104*(O60+5000)) -> 850372.64 | P61: =(P60+5000)*1.00407-(0.00104*(P60+5000)) -> 943007.63 | Q61: =(Q60+5000)*1.00407-(0.000833*(Q60+5000)) -> 1040129.8 | R61: =(R60+5000)*1.00407-(0.000833*(R60+5000)) -> 1142537.2 | S61: =(S60+5000)*1.00407-(0.000833*(S60+5000)) -> 1248994.2 | T61: =(T60+5000)*1.00407-(0.000833*(T60+5000)) -> 1359660.8 | U61: =(U60+5000)*1.00407-(0.00125*(U60+5000)) -> 1471060.9 | V61: =(V60+5000)*1.00407-(0.00125*(V60+5000)) -> 1582732.3 | W61: =(W60+5000)*1.00407-(0.00125*(W60+5000)) -> 1698241.7 | X61: =(X60+5000)*1.00407-(0.00125*(X60+5000)) -> 1817721.3 | Y61: =(Y60+5000)*1.00407-(0.00125*(Y60+5000)) -> 1941307.3 | Z61: =(Z60+5000)*1.00407-(0.00125*(Z60+5000)) -> 2069140.9 | AA61: =(AA60+5000)*1.00407-(0.00125*(AA60+5000)) -> 2201368.2 | AB61: =(AB60+5000)*1.00407-(0.00125*(AB60+5000)) -> 2338140.1 | ... AE61: =(AE60+5000)*1.00407-(0.00125*(AE60+5000)) -> 2777312.5 | AI61: =(AI60+5000)*1.00407-0 -> 30430.261 | AJ61: =(AJ60+5000)*1.00407-0 -> 93561.43 | AK61: =(AK60+5000)*1.00407-0 -> 159845.89 | AL61: =(AL60+5000)*1.00407-0 -> 229441.14 | AM61: =(AM60+5000)*1.00407-0 -> 302512.56 | AN61: =(AN60+5000)*1.00407-0 -> 379233.76 | AO61: =(AO60+5000)*1.00407-0 -> 459787.06 | AP61: =(AP60+5000)*1.00407-0 -> 544363.85 | ... BJ61: =(BJ60+5000)*1.00407-0 -> 3479056.7
D62: =(D61+5000)*1.00407-(0.00146*(D61+5000)) -> 35367.314 | E62: =(E61+5000)*1.00407-(0.00146*(E61+5000)) -> 97518.763 | F62: =(F61+5000)*1.00407-(0.00146*(F61+5000)) -> 161644.98 | G62: =(G61+5000)*1.00407-(0.00146*(G61+5000)) -> 227808.72 | H62: =(H61+5000)*1.00407-(0.00125*(H61+5000)) -> 296595.23 | I62: =(I61+5000)*1.00407-(0.00125*(I61+5000)) -> 367900.41 | J62: =(J61+5000)*1.00407-(0.00125*(J61+5000)) -> 441656.33 | K62: =(K61+5000)*1.00407-(0.00104*(K61+5000)) -> 518269.54 | L62: =(L61+5000)*1.00407-(0.00104*(L61+5000)) -> 598625.98 | M62: =(M61+5000)*1.00407-(0.00104*(M61+5000)) -> 681953.37 | N62: =(N61+5000)*1.00407-(0.00104*(N61+5000)) -> 768361.55 | O62: =(O61+5000)*1.00407-(0.00104*(O61+5000)) -> 857964.42 | P62: =(P61+5000)*1.00407-(0.00104*(P61+5000)) -> 950880.1 | Q62: =(Q61+5000)*1.00407-(0.000833*(Q61+5000)) -> 1048512.9 | R62: =(R61+5000)*1.00407-(0.000833*(R61+5000)) -> 1151251.8 | S62: =(S61+5000)*1.00407-(0.000833*(S61+5000)) -> 1258053.4 | T62: =(T61+5000)*1.00407-(0.000833*(T61+5000)) -> 1369078.2 | U62: =(U61+5000)*1.00407-(0.00125*(U61+5000)) -> 1480223.4 | V62: =(V61+5000)*1.00407-(0.00125*(V61+5000)) -> 1592209.7 | W62: =(W61+5000)*1.00407-(0.00125*(W61+5000)) -> 1708044.9 | X62: =(X61+5000)*1.00407-(0.00125*(X61+5000)) -> 1827861.3 | Y62: =(Y61+5000)*1.00407-(0.00125*(Y61+5000)) -> 1951795.9 | Z62: =(Z61+5000)*1.00407-(0.00125*(Z61+5000)) -> 2079990 | AA62: =(AA61+5000)*1.00407-(0.00125*(AA61+5000)) -> 2212590.1 | AB62: =(AB61+5000)*1.00407-(0.00125*(AB61+5000)) -> 2349747.7 | ... AE62: =(AE61+5000)*1.00407-(0.00125*(AE61+5000)) -> 2790158.6 | AI62: =(AI61+5000)*1.00407-0 -> 35574.462 | AJ62: =(AJ61+5000)*1.00407-0 -> 98962.575 | AK62: =(AK61+5000)*1.00407-0 -> 165516.81 | AL62: =(AL61+5000)*1.00407-0 -> 235395.32 | AM62: =(AM61+5000)*1.00407-0 -> 308764.13 | AN62: =(AN61+5000)*1.00407-0 -> 385797.59 | AO62: =(AO61+5000)*1.00407-0 -> 466678.74 | AP62: =(AP61+5000)*1.00407-0 -> 551599.76 | ... BJ62: =(BJ61+5000)*1.00407-0 -> 3498236.8
D63: =(D62+5000)*1.00407-(0.00146*(D62+5000)) -> 40472.672 | E63: =(E62+5000)*1.00407-(0.00146*(E62+5000)) -> 102786.34 | F63: =(F62+5000)*1.00407-(0.00146*(F62+5000)) -> 167079.93 | G63: =(G62+5000)*1.00407-(0.00146*(G62+5000)) -> 233416.35 | H63: =(H62+5000)*1.00407-(0.00125*(H62+5000)) -> 302445.73 | I63: =(I62+5000)*1.00407-(0.00125*(I62+5000)) -> 373951.99 | J63: =(J62+5000)*1.00407-(0.00125*(J62+5000)) -> 447915.9 | K63: =(K62+5000)*1.00407-(0.00104*(K62+5000)) -> 524855.05 | L63: =(L62+5000)*1.00407-(0.00104*(L62+5000)) -> 605454.97 | M63: =(M62+5000)*1.00407-(0.00104*(M62+5000)) -> 689034.84 | N63: =(N62+5000)*1.00407-(0.00104*(N62+5000)) -> 775704.83 | O63: =(O62+5000)*1.00407-(0.00104*(O62+5000)) -> 865579.2 | P63: =(P62+5000)*1.00407-(0.00104*(P62+5000)) -> 958776.41 | Q63: =(Q62+5000)*1.00407-(0.000833*(Q62+5000)) -> 1056923.1 | R63: =(R62+5000)*1.00407-(0.000833*(R62+5000)) -> 1159994.6 | S63: =(S62+5000)*1.00407-(0.000833*(S62+5000)) -> 1267141.9 | T63: =(T62+5000)*1.00407-(0.000833*(T62+5000)) -> 1378526.1 | U63: =(U62+5000)*1.00407-(0.00125*(U62+5000)) -> 1489411.7 | V63: =(V62+5000)*1.00407-(0.00125*(V62+5000)) -> 1601713.8 | W63: =(W62+5000)*1.00407-(0.00125*(W62+5000)) -> 1717875.7 | X63: =(X62+5000)*1.00407-(0.00125*(X62+5000)) -> 1838030 | Y63: =(Y62+5000)*1.00407-(0.00125*(Y62+5000)) -> 1962314 | Z63: =(Z62+5000)*1.00407-(0.00125*(Z62+5000)) -> 2090869.7 | AA63: =(AA62+5000)*1.00407-(0.00125*(AA62+5000)) -> 2223843.7 | AB63: =(AB62+5000)*1.00407-(0.00125*(AB62+5000)) -> 2361388.1 | ... AE63: =(AE62+5000)*1.00407-(0.00125*(AE62+5000)) -> 2803041 | AI63: =(AI62+5000)*1.00407-0 -> 40739.6 | AJ63: =(AJ62+5000)*1.00407-0 -> 104385.7 | AK63: =(AK62+5000)*1.00407-0 -> 171210.82 | AL63: =(AL62+5000)*1.00407-0 -> 241373.73 | AM63: =(AM62+5000)*1.00407-0 -> 315041.15 | AN63: =(AN62+5000)*1.00407-0 -> 392388.14 | AO63: =(AO62+5000)*1.00407-0 -> 473598.47 | AP63: =(AP62+5000)*1.00407-0 -> 558865.12 | ... BJ63: =(BJ62+5000)*1.00407-0 -> 3517495
D64: =(D63+5000)*1.00407-(0.00146*(D63+5000)) -> 45591.356 | E64: =(E63+5000)*1.00407-(0.00146*(E63+5000)) -> 108067.66 | F64: =(F63+5000)*1.00407-(0.00146*(F63+5000)) -> 172529.06 | G64: =(G63+5000)*1.00407-(0.00146*(G63+5000)) -> 239038.62 | H64: =(H63+5000)*1.00407-(0.00125*(H63+5000)) -> 308312.73 | I64: =(I63+5000)*1.00407-(0.00125*(I63+5000)) -> 380020.63 | J64: =(J63+5000)*1.00407-(0.00125*(J63+5000)) -> 454193.13 | K64: =(K63+5000)*1.00407-(0.00104*(K63+5000)) -> 531460.51 | L64: =(L63+5000)*1.00407-(0.00104*(L63+5000)) -> 612304.65 | M64: =(M63+5000)*1.00407-(0.00104*(M63+5000)) -> 696137.77 | N64: =(N63+5000)*1.00407-(0.00104*(N63+5000)) -> 783070.37 | O64: =(O63+5000)*1.00407-(0.00104*(O63+5000)) -> 873217.06 | P64: =(P63+5000)*1.00407-(0.00104*(P63+5000)) -> 966696.65 | Q64: =(Q63+5000)*1.00407-(0.000833*(Q63+5000)) -> 1065360.5 | R64: =(R63+5000)*1.00407-(0.000833*(R63+5000)) -> 1168765.7 | S64: =(S63+5000)*1.00407-(0.000833*(S63+5000)) -> 1276259.8 | T64: =(T63+5000)*1.00407-(0.000833*(T63+5000)) -> 1388004.6 | U64: =(U63+5000)*1.00407-(0.00125*(U63+5000)) -> 1498626 | V64: =(V63+5000)*1.00407-(0.00125*(V63+5000)) -> 1611244.7 | W64: =(W63+5000)*1.00407-(0.00125*(W63+5000)) -> 1727734.2 | X64: =(X63+5000)*1.00407-(0.00125*(X63+5000)) -> 1848227.4 | Y64: =(Y63+5000)*1.00407-(0.00125*(Y63+5000)) -> 1972861.9 | Z64: =(Z63+5000)*1.00407-(0.00125*(Z63+5000)) -> 2101780 | AA64: =(AA63+5000)*1.00407-(0.00125*(AA63+5000)) -> 2235129.1 | AB64: =(AB63+5000)*1.00407-(0.00125*(AB63+5000)) -> 2373061.3 | ... AE64: =(AE63+5000)*1.00407-(0.00125*(AE63+5000)) -> 2815959.7 | AI64: =(AI63+5000)*1.00407-0 -> 45925.76 | AJ64: =(AJ63+5000)*1.00407-0 -> 109830.9 | AK64: =(AK63+5000)*1.00407-0 -> 176927.99 | AL64: =(AL63+5000)*1.00407-0 -> 247376.47 | AM64: =(AM63+5000)*1.00407-0 -> 321343.72 | AN64: =(AN63+5000)*1.00407-0 -> 399005.51 | AO64: =(AO63+5000)*1.00407-0 -> 480546.37 | AP64: =(AP63+5000)*1.00407-0 -> 566160.05 | ... BJ64: =(BJ63+5000)*1.00407-0 -> 3536831.5
D65: =(D64+5000)*1.00407-(0.00146*(D64+5000)) -> 50723.399 | E65: =(E64+5000)*1.00407-(0.00146*(E64+5000)) -> 113362.77 | F65: =(F64+5000)*1.00407-(0.00146*(F64+5000)) -> 177992.41 | G65: =(G64+5000)*1.00407-(0.00146*(G64+5000)) -> 244675.56 | H65: =(H64+5000)*1.00407-(0.00125*(H64+5000)) -> 314196.27 | I65: =(I64+5000)*1.00407-(0.00125*(I64+5000)) -> 386106.39 | J65: =(J64+5000)*1.00407-(0.00125*(J64+5000)) -> 460488.05 | K65: =(K64+5000)*1.00407-(0.00104*(K64+5000)) -> 538085.98 | L65: =(L64+5000)*1.00407-(0.00104*(L64+5000)) -> 619175.08 | M65: =(M64+5000)*1.00407-(0.00104*(M64+5000)) -> 703262.21 | N65: =(N64+5000)*1.00407-(0.00104*(N64+5000)) -> 790458.22 | O65: =(O64+5000)*1.00407-(0.00104*(O64+5000)) -> 880878.05 | P65: =(P64+5000)*1.00407-(0.00104*(P64+5000)) -> 974640.9 | Q65: =(Q64+5000)*1.00407-(0.000833*(Q64+5000)) -> 1073825.3 | R65: =(R64+5000)*1.00407-(0.000833*(R64+5000)) -> 1177565.2 | S65: =(S64+5000)*1.00407-(0.000833*(S64+5000)) -> 1285407.3 | T65: =(T64+5000)*1.00407-(0.000833*(T64+5000)) -> 1397513.8 | U65: =(U64+5000)*1.00407-(0.00125*(U64+5000)) -> 1507866.2 | V65: =(V64+5000)*1.00407-(0.00125*(V64+5000)) -> 1620802.5 | W65: =(W64+5000)*1.00407-(0.00125*(W64+5000)) -> 1737620.5 | X65: =(X64+5000)*1.00407-(0.00125*(X64+5000)) -> 1858453.5 | Y65: =(Y64+5000)*1.00407-(0.00125*(Y64+5000)) -> 1983439.4 | Z65: =(Z64+5000)*1.00407-(0.00125*(Z64+5000)) -> 2112721.1 | AA65: =(AA64+5000)*1.00407-(0.00125*(AA64+5000)) -> 2246446.2 | AB65: =(AB64+5000)*1.00407-(0.00125*(AB64+5000)) -> 2384767.5 | ... AE65: =(AE64+5000)*1.00407-(0.00125*(AE64+5000)) -> 2828914.8 | AI65: =(AI64+5000)*1.00407-0 -> 51133.028 | AJ65: =(AJ64+5000)*1.00407-0 -> 115298.26 | AK65: =(AK64+5000)*1.00407-0 -> 182668.44 | AL65: =(AL64+5000)*1.00407-0 -> 253403.64 | AM65: =(AM64+5000)*1.00407-0 -> 327671.94 | AN65: =(AN64+5000)*1.00407-0 -> 405649.81 | AO65: =(AO64+5000)*1.00407-0 -> 487522.54 | AP65: =(AP64+5000)*1.00407-0 -> 573484.67 | ... BJ65: =(BJ64+5000)*1.00407-0 -> 3556246.8
D66: =(D65+5000)*1.00407-(0.00146*(D65+5000)) -> 55868.837 | E66: =(E65+5000)*1.00407-(0.00146*(E65+5000)) -> 118671.69 | F66: =(F65+5000)*1.00407-(0.00146*(F65+5000)) -> 183470.02 | G66: =(G65+5000)*1.00407-(0.00125*(G65+5000)) -> 250379.64 | H66: =(H65+5000)*1.00407-(0.00125*(H65+5000)) -> 320096.4 | I66: =(I65+5000)*1.00407-(0.00125*(I65+5000)) -> 392209.31 | J66: =(J65+5000)*1.00407-(0.00125*(J65+5000)) -> 466800.73 | K66: =(K65+5000)*1.00407-(0.00104*(K65+5000)) -> 544731.53 | L66: =(L65+5000)*1.00407-(0.00104*(L65+5000)) -> 626066.33 | M66: =(M65+5000)*1.00407-(0.00104*(M65+5000)) -> 710408.25 | N66: =(N65+5000)*1.00407-(0.00104*(N65+5000)) -> 797868.46 | O66: =(O65+5000)*1.00407-(0.00104*(O65+5000)) -> 888562.26 | P66: =(P65+5000)*1.00407-(0.00104*(P65+5000)) -> 982609.21 | Q66: =(Q65+5000)*1.00407-(0.000833*(Q65+5000)) -> 1082317.4 | R66: =(R65+5000)*1.00407-(0.000833*(R65+5000)) -> 1186393.1 | S66: =(S65+5000)*1.00407-(0.000833*(S65+5000)) -> 1294584.3 | T66: =(T65+5000)*1.00407-(0.000833*(T65+5000)) -> 1407053.7 | U66: =(U65+5000)*1.00407-(0.00125*(U65+5000)) -> 1517132.5 | V66: =(V65+5000)*1.00407-(0.00125*(V65+5000)) -> 1630387.3 | W66: =(W65+5000)*1.00407-(0.00125*(W65+5000)) -> 1747534.7 | X66: =(X65+5000)*1.00407-(0.00125*(X65+5000)) -> 1868708.4 | Y66: =(Y65+5000)*1.00407-(0.00125*(Y65+5000)) -> 1994046.8 | Z66: =(Z65+5000)*1.00407-(0.00125*(Z65+5000)) -> 2123693.1 | AA66: =(AA65+5000)*1.00407-(0.00125*(AA65+5000)) -> 2257795.3 | AB66: =(AB65+5000)*1.00407-(0.00125*(AB65+5000)) -> 2396506.6 | ... AE66: =(AE65+5000)*1.00407-(0.00125*(AE65+5000)) -> 2841906.4 | AI66: =(AI65+5000)*1.00407-0 -> 56361.489 | AJ66: =(AJ65+5000)*1.00407-0 -> 120787.88 | AK66: =(AK65+5000)*1.00407-0 -> 188432.25 | AL66: =(AL65+5000)*1.00407-0 -> 259455.34 | AM66: =(AM65+5000)*1.00407-0 -> 334025.92 | AN66: =(AN65+5000)*1.00407-0 -> 412321.16 | AO66: =(AO65+5000)*1.00407-0 -> 494527.11 | AP66: =(AP65+5000)*1.00407-0 -> 580839.1 | ... BJ66: =(BJ65+5000)*1.00407-0 -> 3575741
D67: =(D66+5000)*1.00407-(0.00146*(D66+5000)) -> 61027.705 | E67: =(E66+5000)*1.00407-(0.00146*(E66+5000)) -> 123994.48 | F67: =(F66+5000)*1.00407-(0.00146*(F66+5000)) -> 188961.92 | G67: =(G66+5000)*1.00407-(0.00125*(G66+5000)) -> 256099.82 | H67: =(H66+5000)*1.00407-(0.00125*(H66+5000)) -> 326013.17 | I67: =(I66+5000)*1.00407-(0.00125*(I66+5000)) -> 398329.44 | J67: =(J66+5000)*1.00407-(0.00125*(J66+5000)) -> 473131.21 | K67: =(K66+5000)*1.00407-(0.00104*(K66+5000)) -> 551397.22 | L67: =(L66+5000)*1.00407-(0.00104*(L66+5000)) -> 632978.46 | M67: =(M66+5000)*1.00407-(0.00104*(M66+5000)) -> 717575.93 | N67: =(N66+5000)*1.00407-(0.00104*(N66+5000)) -> 805301.15 | O67: =(O66+5000)*1.00407-(0.00104*(O66+5000)) -> 896269.76 | P67: =(P66+5000)*1.00407-(0.00104*(P66+5000)) -> 990601.66 | Q67: =(Q66+5000)*1.00407-(0.000833*(Q66+5000)) -> 1090837.1 | R67: =(R66+5000)*1.00407-(0.000833*(R66+5000)) -> 1195249.7 | S67: =(S66+5000)*1.00407-(0.000833*(S66+5000)) -> 1303791.1 | T67: =(T66+5000)*1.00407-(0.000833*(T66+5000)) -> 1416624.5 | U67: =(U66+5000)*1.00407-(0.00125*(U66+5000)) -> 1526424.9 | V67: =(V66+5000)*1.00407-(0.00125*(V66+5000)) -> 1639999.1 | W67: =(W66+5000)*1.00407-(0.00125*(W66+5000)) -> 1757476.8 | X67: =(X66+5000)*1.00407-(0.00125*(X66+5000)) -> 1878992.3 | Y67: =(Y66+5000)*1.00407-(0.00125*(Y66+5000)) -> 2004684.1 | Z67: =(Z66+5000)*1.00407-(0.00125*(Z66+5000)) -> 2134696 | AA67: =(AA66+5000)*1.00407-(0.00125*(AA66+5000)) -> 2269176.4 | AB67: =(AB66+5000)*1.00407-(0.00125*(AB66+5000)) -> 2408278.9 | ... AE67: =(AE66+5000)*1.00407-(0.00125*(AE66+5000)) -> 2854934.7 | AI67: =(AI66+5000)*1.00407-0 -> 61611.231 | AJ67: =(AJ66+5000)*1.00407-0 -> 126299.83 | AK67: =(AK66+5000)*1.00407-0 -> 194219.52 | AL67: =(AL66+5000)*1.00407-0 -> 265531.68 | AM67: =(AM66+5000)*1.00407-0 -> 340405.75 | AN67: =(AN66+5000)*1.00407-0 -> 419019.65 | AO67: =(AO66+5000)*1.00407-0 -> 501560.18 | AP67: =(AP66+5000)*1.00407-0 -> 588223.47 | ... BJ67: =(BJ66+5000)*1.00407-0 -> 3595314.6
D70: Scenario 4 | AI70: Scenario 4 | AJ70: WITHOUT AN ADVISOR
D71: Assume 6% annual return on investments | AI71: Assume 6% annual return on investments
D72: Assume 5K/mo invested | AI72: Assume 5K/mo invested
D73: Y1 | E73: Y2 | F73: Y3 | G73: Y4 | H73: Y5 | I73: Y6 | J73: Y7 | K73: Y8 | L73: Y9 | M73: Y10 | N73: Y11 | O73: Y12 | P73: Y13 | Q73: Y14 | R73: Y15 | S73: Y16 | T73: Y17 | U73: Y18 | V73: Y19 | W73: Y20 | X73: Y21 | Y73: Y22 | Z73: Y23 | AA73: Y24 | AB73: Y25 | AC73: Y26 | AD73: Y27 | AE73: Y28 | AI73: Y1 | AJ73: Y2 | AK73: Y3 | AL73: Y4 | AM73: Y5 | AN73: Y6 | AO73: Y7 | AP73: Y8 | AQ73: Y9 | AR73: Y10 | AS73: Y11 | AT73: Y12 | AU73: Y13 | AV73: Y14 | AW73: Y15 | AX73: Y16 | AY73: Y17 | AZ73: Y18 | BA73: Y19 | BB73: Y20 | BC73: Y21 | BD73: Y22 | BE73: Y23 | BF73: Y24 | BG73: Y25 | BH73: Y26 | BI73: Y27 | BJ73: Y28
D74: 0 | AI74: 0
